{
  "schema_version": 1,
  "run_id": "2026-07-10T18-00-36Z",
  "generated_at": "2026-07-10T18:00:36.820267+00:00",
  "robusta_version": "13",
  "input_universe": [
    "ABEV3",
    "ALOS3",
    "ASAI3",
    "AURE3",
    "AXIA3",
    "AXIA6",
    "AZZA3",
    "B3SA3",
    "BBAS3",
    "BBDC3",
    "BBDC4",
    "BBSE3",
    "BEEF3",
    "BPAC11",
    "BRAP4",
    "BRAV3",
    "BRKM5",
    "CEAB3",
    "CMIG4",
    "CMIN3",
    "COGN3",
    "CPFE3",
    "CPLE3",
    "CSAN3",
    "CSMG3",
    "CSNA3",
    "CURY3",
    "CXSE3",
    "CYRE3",
    "DIRR3",
    "EGIE3",
    "EMBJ3",
    "ENEV3",
    "ENGI11",
    "EQTL3",
    "FLRY3",
    "GGBR4",
    "GOAU4",
    "HAPV3",
    "HYPE3",
    "IGTI11",
    "ISAE4",
    "ITSA4",
    "ITUB4",
    "KLBN11",
    "LREN3",
    "MBRF3",
    "MGLU3",
    "MOTV3",
    "MRVE3",
    "MULT3",
    "NATU3",
    "PETR3",
    "PETR4",
    "POMO4",
    "PRIO3",
    "PSSA3",
    "RADL3",
    "RAIL3",
    "RDOR3",
    "RECV3",
    "RENT3",
    "SANB11",
    "SBSP3",
    "SLCE3",
    "SMFT3",
    "SUZB3",
    "TAEE11",
    "TIMS3",
    "TOTS3",
    "UGPA3",
    "USIM5",
    "VALE3",
    "VAMO3",
    "VBBR3",
    "VIVA3",
    "VIVT3",
    "WEGE3",
    "YDUQ3"
  ],
  "summary": {
    "tickers_ok": 78,
    "tickers_failed": 1,
    "vol_media": 0.32553136948460654,
    "vol_std": 0.12009316130602776
  },
  "portfolio_signals": {
    "longs": [
      {
        "ticker": "BEEF3",
        "subsetor": "Carnes e Derivados",
        "distortion_ranking": 14,
        "pct_to_mma10": 2.0751569305382476
      },
      {
        "ticker": "POMO4",
        "subsetor": "Material Rodoviário",
        "distortion_ranking": 18,
        "pct_to_mma10": -0.2575108954426486
      },
      {
        "ticker": "RECV3",
        "subsetor": "Exploração. Refino e Distribuição",
        "distortion_ranking": 18,
        "pct_to_mma10": 2.811325949431258
      },
      {
        "ticker": "PETR4",
        "subsetor": "Exploração. Refino e Distribuição",
        "distortion_ranking": 23,
        "pct_to_mma10": 2.857443411538475
      },
      {
        "ticker": "CEAB3",
        "subsetor": "Tecidos. Vestuário e Calçados",
        "distortion_ranking": 24,
        "pct_to_mma10": 1.249175410300981
      }
    ],
    "shorts": [
      {
        "ticker": "CXSE3",
        "subsetor": "Seguradoras",
        "distortion_ranking": 72,
        "pct_to_mma10": 6.463511947690893
      },
      {
        "ticker": "CSMG3",
        "subsetor": "Água e Saneamento",
        "distortion_ranking": 69,
        "pct_to_mma10": 6.901843582063092
      },
      {
        "ticker": "BBSE3",
        "subsetor": "Seguradoras",
        "distortion_ranking": 66,
        "pct_to_mma10": 3.2481689550932407
      },
      {
        "ticker": "EMBJ3",
        "subsetor": "Material Aeronáutico e de Defesa",
        "distortion_ranking": 65,
        "pct_to_mma10": 2.1259734094509644
      },
      {
        "ticker": "ENEV3",
        "subsetor": "Energia Elétrica",
        "distortion_ranking": 65,
        "pct_to_mma10": 3.8201577229719312
      }
    ]
  },
  "tickers": {
    "ABEV3": {
      "ticker": "ABEV3",
      "setor": null,
      "subsetor": "Cervejas e Refrigerantes",
      "fundamental_signal": 0,
      "vol_signal": 1,
      "posicao_setorial": "pior",
      "preco": 15.84000015258789,
      "vol_anualizada_30d": 0.18044970505906419,
      "alto_vol_persistente": 0,
      "mma9": 15.972222434149849,
      "mma10": 16.034000205993653,
      "mma26": 16.22461539048415,
      "mma50": 16.16740001678467,
      "mma150": 15.285733343760173,
      "mma200": 14.630250000953675,
      "pct_to_mma10": -1.2099292186190909,
      "pct_to_mma50": -2.0250619385731654,
      "sup_min_by_mslf": 14.2,
      "sup_med_by_mslf": 14.3,
      "sup_max_by_mslf": 14.5,
      "res_min_by_mslf": 17.0,
      "res_med_by_mslf": "Foguete",
      "res_max_by_mslf": "Foguete",
      "std_raking_value_by_mslf": 2,
      "momentum_break_by_mslf": 1,
      "pl": 16.0,
      "pvp": 2.77,
      "ev_ebit": 11.84,
      "roic": 20.0,
      "cres_rec_5a": 4.6,
      "div_liq_vm": -0.07,
      "avaliacao_fundamentalista": 22,
      "distortion_ranking": 35
    },
    "ALOS3": {
      "ticker": "ALOS3",
      "setor": null,
      "subsetor": "Exploração de Imóveis",
      "fundamental_signal": 0,
      "vol_signal": 0,
      "posicao_setorial": "pior",
      "preco": 28.6200008392334,
      "vol_anualizada_30d": 0.22497512326565644,
      "alto_vol_persistente": 0,
      "mma9": 27.823333740234375,
      "mma10": 27.847000312805175,
      "mma26": 27.3115386229295,
      "mma50": 28.123600044250487,
      "mma150": 29.53866667429606,
      "mma200": 28.571150007247926,
      "pct_to_mma10": 2.775884360057146,
      "pct_to_mma50": 1.7650684627923154,
      "sup_min_by_mslf": 24.3,
      "sup_med_by_mslf": 24.5,
      "sup_max_by_mslf": 24.6,
      "res_min_by_mslf": 34.2,
      "res_med_by_mslf": "Foguete",
      "res_max_by_mslf": "Foguete",
      "std_raking_value_by_mslf": 1,
      "momentum_break_by_mslf": 1,
      "pl": 17.45,
      "pvp": 1.11,
      "ev_ebit": 8.31,
      "roic": 6.3,
      "cres_rec_5a": 31.3,
      "div_liq_vm": -0.15,
      "avaliacao_fundamentalista": 24,
      "distortion_ranking": 45
    },
    "ASAI3": {
      "ticker": "ASAI3",
      "setor": null,
      "subsetor": "Alimentos",
      "fundamental_signal": 0,
      "vol_signal": 0,
      "posicao_setorial": "melhor",
      "preco": 8.890000343322754,
      "vol_anualizada_30d": 0.37837185989961625,
      "alto_vol_persistente": 0,
      "mma9": 8.657777680291069,
      "mma10": 8.691999912261963,
      "mma26": 8.35615379993732,
      "mma50": 8.583199949264527,
      "mma150": 8.521599934895834,
      "mma200": 8.6409499502182,
      "pct_to_mma10": 2.2779617241075694,
      "pct_to_mma50": 3.57442906924842,
      "sup_min_by_mslf": 5.1,
      "sup_med_by_mslf": 7.6,
      "sup_max_by_mslf": 8.6,
      "res_min_by_mslf": 9.4,
      "res_med_by_mslf": 9.5,
      "res_max_by_mslf": 9.6,
      "std_raking_value_by_mslf": 3,
      "momentum_break_by_mslf": 0,
      "pl": 17.1,
      "pvp": 2.04,
      "ev_ebit": 3.81,
      "roic": 19.7,
      "cres_rec_5a": 14.9,
      "div_liq_vm": 1.0,
      "avaliacao_fundamentalista": 31,
      "distortion_ranking": 40
    },
    "AURE3": {
      "ticker": "AURE3",
      "setor": null,
      "subsetor": "Energia Elétrica",
      "fundamental_signal": 0,
      "vol_signal": 0,
      "posicao_setorial": "",
      "preco": 12.720000267028809,
      "vol_anualizada_30d": 0.3188316991465945,
      "alto_vol_persistente": 0,
      "mma9": 11.952222188313803,
      "mma10": 11.919999980926514,
      "mma26": 11.663846199329083,
      "mma50": 12.238200035095215,
      "mma150": 12.174066645304363,
      "mma200": 11.89059998512268,
      "pct_to_mma10": 6.711411806899285,
      "pct_to_mma50": 3.9368553427133572,
      "sup_min_by_mslf": 11.8,
      "sup_med_by_mslf": 11.9,
      "sup_max_by_mslf": 12.0,
      "res_min_by_mslf": 14.7,
      "res_med_by_mslf": "Foguete",
      "res_max_by_mslf": "Foguete",
      "std_raking_value_by_mslf": 2,
      "momentum_break_by_mslf": 1,
      "pl": -10.34,
      "pvp": 1.12,
      "ev_ebit": 28.38,
      "roic": 2.7,
      "cres_rec_5a": 39.7,
      "div_liq_vm": 1.52,
      "avaliacao_fundamentalista": 15,
      "distortion_ranking": 62
    },
    "AXIA3": {
      "ticker": "AXIA3",
      "setor": null,
      "subsetor": "Energia Elétrica",
      "fundamental_signal": -1,
      "vol_signal": 0,
      "posicao_setorial": "",
      "preco": 53.63999938964844,
      "vol_anualizada_30d": 0.2703493634131751,
      "alto_vol_persistente": 0,
      "mma9": 53.53555594550239,
      "mma10": 53.693000411987306,
      "mma26": 52.97192309452937,
      "mma50": 54.26059989929199,
      "mma150": 57.065200068155924,
      "mma200": 56.74745002746582,
      "pct_to_mma10": -0.09871123225036944,
      "pct_to_mma50": -1.1437405977733204,
      "sup_min_by_mslf": 45.8,
      "sup_med_by_mslf": 50.0,
      "sup_max_by_mslf": 52.5,
      "res_min_by_mslf": 53.7,
      "res_med_by_mslf": 54.5,
      "res_max_by_mslf": 58.2,
      "std_raking_value_by_mslf": 1,
      "momentum_break_by_mslf": 0,
      "pl": 16.4,
      "pvp": 1.29,
      "ev_ebit": 26.34,
      "roic": 3.0,
      "cres_rec_5a": 4.6,
      "div_liq_vm": 0.29,
      "avaliacao_fundamentalista": 13,
      "distortion_ranking": 45
    },
    "AZZA3": {
      "ticker": "AZZA3",
      "setor": null,
      "subsetor": "Tecidos. Vestuário e Calçados",
      "fundamental_signal": 1,
      "vol_signal": -1,
      "posicao_setorial": "",
      "preco": 19.219999313354492,
      "vol_anualizada_30d": 0.6351792497918222,
      "alto_vol_persistente": 0,
      "mma9": 17.835555182562935,
      "mma10": 17.8899995803833,
      "mma26": 17.8761536524846,
      "mma50": 18.93299987792969,
      "mma150": 23.011666666666667,
      "mma200": 24.322849998474123,
      "pct_to_mma10": 7.434319531396525,
      "pct_to_mma50": 1.5158687861154032,
      "sup_min_by_mslf": "Abismo",
      "sup_med_by_mslf": 16.1,
      "sup_max_by_mslf": 17.1,
      "res_min_by_mslf": 23.0,
      "res_med_by_mslf": 23.1,
      "res_max_by_mslf": 23.3,
      "std_raking_value_by_mslf": 1,
      "momentum_break_by_mslf": 0,
      "pl": 4.77,
      "pvp": 0.5,
      "ev_ebit": 6.19,
      "roic": 7.7,
      "cres_rec_5a": 39.8,
      "div_liq_vm": 0.55,
      "avaliacao_fundamentalista": 33,
      "distortion_ranking": 41
    },
    "B3SA3": {
      "ticker": "B3SA3",
      "setor": null,
      "subsetor": "Serviços Financeiros Diversos",
      "fundamental_signal": 0,
      "vol_signal": 0,
      "posicao_setorial": "pior",
      "preco": 15.460000038146973,
      "vol_anualizada_30d": 0.3200527120253189,
      "alto_vol_persistente": 0,
      "mma9": 14.655555407206217,
      "mma10": 14.660999870300293,
      "mma26": 14.843461440159725,
      "mma50": 15.877600059509277,
      "mma150": 16.331133403778075,
      "mma200": 15.548550057411195,
      "pct_to_mma10": 5.449834083044123,
      "pct_to_mma50": -2.630120545908314,
      "sup_min_by_mslf": 13.6,
      "sup_med_by_mslf": 14.6,
      "sup_max_by_mslf": 14.9,
      "res_min_by_mslf": 20.3,
      "res_med_by_mslf": "Foguete",
      "res_max_by_mslf": "Foguete",
      "std_raking_value_by_mslf": 1,
      "momentum_break_by_mslf": 1,
      "pl": 15.78,
      "pvp": 4.27,
      "ev_ebit": 11.58,
      "roic": 21.6,
      "cres_rec_5a": 3.2,
      "div_liq_vm": -0.01,
      "avaliacao_fundamentalista": 23,
      "distortion_ranking": 37
    },
    "BBAS3": {
      "ticker": "BBAS3",
      "setor": null,
      "subsetor": "Bancos",
      "fundamental_signal": 0,
      "vol_signal": 1,
      "posicao_setorial": "",
      "preco": 20.59000015258789,
      "vol_anualizada_30d": 0.2029741676396409,
      "alto_vol_persistente": 0,
      "mma9": 19.91555553012424,
      "mma10": 19.95,
      "mma26": 19.67153842632587,
      "mma50": 20.309799995422363,
      "mma150": 22.51366667429606,
      "mma200": 22.3078000164032,
      "pct_to_mma10": 3.2080208149768987,
      "pct_to_mma50": 1.3796303126012168,
      "sup_min_by_mslf": 18.1,
      "sup_med_by_mslf": 19.7,
      "sup_max_by_mslf": 20.2,
      "res_min_by_mslf": 20.6,
      "res_med_by_mslf": 21.0,
      "res_max_by_mslf": 21.1,
      "std_raking_value_by_mslf": 1,
      "momentum_break_by_mslf": 0,
      "pl": 8.2,
      "pvp": 0.63,
      "ev_ebit": 0.0,
      "roic": 0.0,
      "cres_rec_5a": -8.6,
      "div_liq_vm": 0.0,
      "avaliacao_fundamentalista": 29,
      "distortion_ranking": 37
    },
    "BBDC3": {
      "ticker": "BBDC3",
      "setor": null,
      "subsetor": "Bancos",
      "fundamental_signal": 0,
      "vol_signal": 0,
      "posicao_setorial": "",
      "preco": 16.43000030517578,
      "vol_anualizada_30d": 0.21674143569874949,
      "alto_vol_persistente": 0,
      "mma9": 15.775555716620552,
      "mma10": 15.779000186920166,
      "mma26": 15.492692470550537,
      "mma50": 15.595400085449219,
      "mma150": 16.52200003306071,
      "mma200": 16.27105001449585,
      "pct_to_mma10": 4.125737439278659,
      "pct_to_mma50": 5.351579409015988,
      "sup_min_by_mslf": 15.8,
      "sup_med_by_mslf": 15.9,
      "sup_max_by_mslf": 16.1,
      "res_min_by_mslf": 16.9,
      "res_med_by_mslf": 19.0,
      "res_max_by_mslf": "Foguete",
      "std_raking_value_by_mslf": 1,
      "momentum_break_by_mslf": 0,
      "pl": 7.33,
      "pvp": 1.0,
      "ev_ebit": 0.0,
      "roic": 0.0,
      "cres_rec_5a": 1.6,
      "div_liq_vm": 0.0,
      "avaliacao_fundamentalista": 28,
      "distortion_ranking": 51
    },
    "BBDC4": {
      "ticker": "BBDC4",
      "setor": null,
      "subsetor": "Bancos",
      "fundamental_signal": 0,
      "vol_signal": 0,
      "posicao_setorial": "",
      "preco": 18.719999313354492,
      "vol_anualizada_30d": 0.21604573354432804,
      "alto_vol_persistente": 0,
      "mma9": 18.087777879503037,
      "mma10": 18.096000099182127,
      "mma26": 17.781153825613167,
      "mma50": 17.91800003051758,
      "mma150": 19.10833334604899,
      "mma200": 18.87279999732971,
      "pct_to_mma10": 3.4482715006205553,
      "pct_to_mma50": 4.4759419660172135,
      "sup_min_by_mslf": 18.3,
      "sup_med_by_mslf": 18.4,
      "sup_max_by_mslf": 18.7,
      "res_min_by_mslf": 18.8,
      "res_med_by_mslf": 19.1,
      "res_max_by_mslf": 19.2,
      "std_raking_value_by_mslf": 1,
      "momentum_break_by_mslf": 0,
      "pl": 8.36,
      "pvp": 1.14,
      "ev_ebit": 0.0,
      "roic": 0.0,
      "cres_rec_5a": 1.6,
      "div_liq_vm": 0.0,
      "avaliacao_fundamentalista": 27,
      "distortion_ranking": 51
    },
    "BBSE3": {
      "ticker": "BBSE3",
      "setor": null,
      "subsetor": "Seguradoras",
      "fundamental_signal": 0,
      "vol_signal": 1,
      "posicao_setorial": "",
      "preco": 40.209999084472656,
      "vol_anualizada_30d": 0.2013354270780263,
      "alto_vol_persistente": 0,
      "mma9": 38.9022216796875,
      "mma10": 38.94499969482422,
      "mma26": 38.3265380859375,
      "mma50": 36.49579986572266,
      "mma150": 35.737866643269854,
      "mma200": 35.064999952316285,
      "pct_to_mma10": 3.2481689550932407,
      "pct_to_mma50": 10.17705936687367,
      "sup_min_by_mslf": 35.7,
      "sup_med_by_mslf": 36.4,
      "sup_max_by_mslf": 38.0,
      "res_min_by_mslf": 42.6,
      "res_med_by_mslf": "Foguete",
      "res_max_by_mslf": "Foguete",
      "std_raking_value_by_mslf": 1,
      "momentum_break_by_mslf": 1,
      "pl": 8.5,
      "pvp": 6.18,
      "ev_ebit": 0.0,
      "roic": 0.0,
      "cres_rec_5a": 0.0,
      "div_liq_vm": 0.0,
      "avaliacao_fundamentalista": 20,
      "distortion_ranking": 66
    },
    "BEEF3": {
      "ticker": "BEEF3",
      "setor": null,
      "subsetor": "Carnes e Derivados",
      "fundamental_signal": 1,
      "vol_signal": 0,
      "posicao_setorial": "melhor",
      "preco": 3.640000104904175,
      "vol_anualizada_30d": 0.41296759240041975,
      "alto_vol_persistente": 0,
      "mma9": 3.5511111153496637,
      "mma10": 3.5660000085830688,
      "mma26": 3.618846159714919,
      "mma50": 3.79480001449585,
      "mma150": 4.695133341153463,
      "mma200": 5.185150004625321,
      "pct_to_mma10": 2.0751569305382476,
      "pct_to_mma50": -4.079263966489697,
      "sup_min_by_mslf": "Abismo",
      "sup_med_by_mslf": "Abismo",
      "sup_max_by_mslf": 3.4,
      "res_min_by_mslf": 4.8,
      "res_med_by_mslf": 5.0,
      "res_max_by_mslf": 5.2,
      "std_raking_value_by_mslf": 3,
      "momentum_break_by_mslf": -1,
      "pl": 5.13,
      "pvp": 2.89,
      "ev_ebit": 4.4,
      "roic": 17.8,
      "cres_rec_5a": 17.7,
      "div_liq_vm": 3.76,
      "avaliacao_fundamentalista": 37,
      "distortion_ranking": 14
    },
    "BPAC11": {
      "ticker": "BPAC11",
      "setor": null,
      "subsetor": "Bancos",
      "fundamental_signal": 0,
      "vol_signal": 0,
      "posicao_setorial": "pior",
      "preco": 58.099998474121094,
      "vol_anualizada_30d": 0.2989063295306507,
      "alto_vol_persistente": 0,
      "mma9": 55.125555674235024,
      "mma10": 55.06399993896484,
      "mma26": 52.83846136239859,
      "mma50": 54.07479995727539,
      "mma150": 56.3265998840332,
      "mma200": 54.534899921417235,
      "pct_to_mma10": 5.513581538793906,
      "pct_to_mma50": 7.44376034682703,
      "sup_min_by_mslf": 54.6,
      "sup_med_by_mslf": 55.0,
      "sup_max_by_mslf": 55.7,
      "res_min_by_mslf": 65.5,
      "res_med_by_mslf": "Foguete",
      "res_max_by_mslf": "Foguete",
      "std_raking_value_by_mslf": 1,
      "momentum_break_by_mslf": 1,
      "pl": 13.06,
      "pvp": 3.03,
      "ev_ebit": 0.0,
      "roic": 0.0,
      "cres_rec_5a": 8.5,
      "div_liq_vm": 0.0,
      "avaliacao_fundamentalista": 23,
      "distortion_ranking": 61
    },
    "BRAP4": {
      "ticker": "BRAP4",
      "setor": null,
      "subsetor": "Minerais Metálicos",
      "fundamental_signal": -1,
      "vol_signal": 0,
      "posicao_setorial": "pior",
      "preco": 21.729999542236328,
      "vol_anualizada_30d": 0.2891339215271041,
      "alto_vol_persistente": 0,
      "mma9": 21.897777981228298,
      "mma10": 21.93300018310547,
      "mma26": 22.179230836721565,
      "mma50": 22.57380012512207,
      "mma150": 22.70599998474121,
      "mma200": 21.50404996871948,
      "pct_to_mma10": -0.9255488951552975,
      "pct_to_mma50": -3.737964269235676,
      "sup_min_by_mslf": 17.3,
      "sup_med_by_mslf": 19.1,
      "sup_max_by_mslf": 19.2,
      "res_min_by_mslf": 25.6,
      "res_med_by_mslf": "Foguete",
      "res_max_by_mslf": "Foguete",
      "std_raking_value_by_mslf": 2,
      "momentum_break_by_mslf": 1,
      "pl": 10.92,
      "pvp": 1.09,
      "ev_ebit": -243.43,
      "roic": -0.5,
      "cres_rec_5a": 0.0,
      "div_liq_vm": -0.03,
      "avaliacao_fundamentalista": 12,
      "distortion_ranking": 41
    },
    "BRAV3": {
      "ticker": "BRAV3",
      "setor": null,
      "subsetor": "Exploração. Refino e Distribuição",
      "fundamental_signal": 0,
      "vol_signal": 0,
      "posicao_setorial": "",
      "preco": 19.1200008392334,
      "vol_anualizada_30d": 0.292798956729318,
      "alto_vol_persistente": 0,
      "mma9": 18.651110967000324,
      "mma10": 18.69099979400635,
      "mma26": 19.49076901949369,
      "mma50": 19.328799896240234,
      "mma150": 18.356466573079427,
      "mma200": 17.676649947166442,
      "pct_to_mma10": 2.295227916939029,
      "pct_to_mma50": -1.0802484278780828,
      "sup_min_by_mslf": 18.9,
      "sup_med_by_mslf": 19.0,
      "sup_max_by_mslf": 19.1,
      "res_min_by_mslf": 19.2,
      "res_med_by_mslf": 19.3,
      "res_max_by_mslf": 19.4,
      "std_raking_value_by_mslf": 2,
      "momentum_break_by_mslf": 0,
      "pl": 38.24,
      "pvp": 0.78,
      "ev_ebit": 7.22,
      "roic": 7.8,
      "cres_rec_5a": 93.8,
      "div_liq_vm": 1.2,
      "avaliacao_fundamentalista": 24,
      "distortion_ranking": 35
    },
    "BRKM5": {
      "ticker": "BRKM5",
      "setor": null,
      "subsetor": "Petroquímicos",
      "fundamental_signal": -1,
      "vol_signal": -1,
      "posicao_setorial": "pior",
      "preco": 6.619999885559082,
      "vol_anualizada_30d": 0.7371757009721811,
      "alto_vol_persistente": 0,
      "mma9": 6.246666643354628,
      "mma10": 6.2829999923706055,
      "mma26": 7.490769184552706,
      "mma50": 9.10439995765686,
      "mma150": 9.18393330891927,
      "mma200": 8.671849982738495,
      "pct_to_mma10": 5.363678077314861,
      "pct_to_mma50": -27.287905668164115,
      "sup_min_by_mslf": "Abismo",
      "sup_med_by_mslf": "Abismo",
      "sup_max_by_mslf": 5.8,
      "res_min_by_mslf": 7.4,
      "res_med_by_mslf": 7.5,
      "res_max_by_mslf": 7.8,
      "std_raking_value_by_mslf": 1,
      "momentum_break_by_mslf": -1,
      "pl": -0.58,
      "pvp": -0.34,
      "ev_ebit": -13.45,
      "roic": -6.5,
      "cres_rec_5a": -10.6,
      "div_liq_vm": 8.15,
      "avaliacao_fundamentalista": 4,
      "distortion_ranking": 48
    },
    "CEAB3": {
      "ticker": "CEAB3",
      "setor": null,
      "subsetor": "Tecidos. Vestuário e Calçados",
      "fundamental_signal": 1,
      "vol_signal": -1,
      "posicao_setorial": "melhor",
      "preco": 10.779999732971191,
      "vol_anualizada_30d": 0.46762597204658274,
      "alto_vol_persistente": 0,
      "mma9": 10.605555534362793,
      "mma10": 10.64700002670288,
      "mma26": 10.623846200796274,
      "mma50": 10.960199966430665,
      "mma150": 11.880600001017253,
      "mma200": 13.095299983024598,
      "pct_to_mma10": 1.249175410300981,
      "pct_to_mma50": -1.6441327166602584,
      "sup_min_by_mslf": 10.5,
      "sup_med_by_mslf": 10.6,
      "sup_max_by_mslf": 10.7,
      "res_min_by_mslf": 10.8,
      "res_med_by_mslf": 10.9,
      "res_max_by_mslf": 11.0,
      "std_raking_value_by_mslf": 2,
      "momentum_break_by_mslf": 0,
      "pl": 5.67,
      "pvp": 0.9,
      "ev_ebit": 3.8,
      "roic": 14.7,
      "cres_rec_5a": 9.9,
      "div_liq_vm": 0.04,
      "avaliacao_fundamentalista": 34,
      "distortion_ranking": 24
    },
    "CMIG4": {
      "ticker": "CMIG4",
      "setor": null,
      "subsetor": "Energia Elétrica",
      "fundamental_signal": 0,
      "vol_signal": 0,
      "posicao_setorial": "",
      "preco": 11.329999923706055,
      "vol_anualizada_30d": 0.20771652928160494,
      "alto_vol_persistente": 0,
      "mma9": 10.966666751437717,
      "mma10": 10.96500005722046,
      "mma26": 10.856153891636776,
      "mma50": 11.131000080108642,
      "mma150": 11.607866719563802,
      "mma200": 11.498000040054322,
      "pct_to_mma10": 3.3287721348003343,
      "pct_to_mma50": 1.7877984203147241,
      "sup_min_by_mslf": 9.8,
      "sup_med_by_mslf": 10.7,
      "sup_max_by_mslf": 11.2,
      "res_min_by_mslf": 13.9,
      "res_med_by_mslf": "Foguete",
      "res_max_by_mslf": "Foguete",
      "std_raking_value_by_mslf": 1,
      "momentum_break_by_mslf": 1,
      "pl": 6.7,
      "pvp": 1.12,
      "ev_ebit": 8.02,
      "roic": 9.6,
      "cres_rec_5a": 6.2,
      "div_liq_vm": 0.55,
      "avaliacao_fundamentalista": 26,
      "distortion_ranking": 44
    },
    "CMIN3": {
      "ticker": "CMIN3",
      "setor": null,
      "subsetor": "Minerais Metálicos",
      "fundamental_signal": 0,
      "vol_signal": 0,
      "posicao_setorial": "melhor",
      "preco": 5.099999904632568,
      "vol_anualizada_30d": 0.4052796507015222,
      "alto_vol_persistente": 0,
      "mma9": 4.483333269755046,
      "mma10": 4.450999927520752,
      "mma26": 4.360769216830914,
      "mma50": 4.487199983596802,
      "mma150": 5.068333326975504,
      "mma200": 5.214650001525879,
      "pct_to_mma10": 14.580992758481468,
      "pct_to_mma50": 13.656621574164053,
      "sup_min_by_mslf": "Abismo",
      "sup_med_by_mslf": "Abismo",
      "sup_max_by_mslf": 4.1,
      "res_min_by_mslf": 5.1,
      "res_med_by_mslf": 7.4,
      "res_max_by_mslf": "Foguete",
      "std_raking_value_by_mslf": 1,
      "momentum_break_by_mslf": -1,
      "pl": 12.44,
      "pvp": 3.92,
      "ev_ebit": 4.86,
      "roic": 21.7,
      "cres_rec_5a": 2.6,
      "div_liq_vm": 0.01,
      "avaliacao_fundamentalista": 28,
      "distortion_ranking": 62
    },
    "COGN3": {
      "ticker": "COGN3",
      "setor": null,
      "subsetor": "Serviços Educacionais",
      "fundamental_signal": 0,
      "vol_signal": 0,
      "posicao_setorial": "melhor",
      "preco": 2.380000114440918,
      "vol_anualizada_30d": 0.3500805544371661,
      "alto_vol_persistente": 0,
      "mma9": 2.268888897365994,
      "mma10": 2.2710000038146974,
      "mma26": 2.312307669566228,
      "mma50": 2.44439998626709,
      "mma150": 3.1001332887013753,
      "mma200": 3.1024180352687836,
      "pct_to_mma10": 4.7996525954702065,
      "pct_to_mma50": -2.63458812747413,
      "sup_min_by_mslf": 1.2,
      "sup_med_by_mslf": 1.3,
      "sup_max_by_mslf": 1.4,
      "res_min_by_mslf": 2.6,
      "res_med_by_mslf": 4.7,
      "res_max_by_mslf": "Foguete",
      "std_raking_value_by_mslf": 1,
      "momentum_break_by_mslf": 0,
      "pl": 7.21,
      "pvp": 0.36,
      "ev_ebit": 4.76,
      "roic": 10.1,
      "cres_rec_5a": 11.6,
      "div_liq_vm": 1.09,
      "avaliacao_fundamentalista": 31,
      "distortion_ranking": 29
    },
    "CPFE3": {
      "ticker": "CPFE3",
      "setor": null,
      "subsetor": "Energia Elétrica",
      "fundamental_signal": 0,
      "vol_signal": 1,
      "posicao_setorial": "melhor",
      "preco": 47.5099983215332,
      "vol_anualizada_30d": 0.2013705710353715,
      "alto_vol_persistente": 0,
      "mma9": 45.48999913533529,
      "mma10": 45.45599937438965,
      "mma26": 44.54807618948129,
      "mma50": 44.955999603271486,
      "mma150": 48.883533198038734,
      "mma200": 47.14189990997315,
      "pct_to_mma10": 4.518653149007208,
      "pct_to_mma50": 5.681107618116137,
      "sup_min_by_mslf": 40.8,
      "sup_med_by_mslf": 41.8,
      "sup_max_by_mslf": 41.9,
      "res_min_by_mslf": 57.2,
      "res_med_by_mslf": "Foguete",
      "res_max_by_mslf": "Foguete",
      "std_raking_value_by_mslf": 2,
      "momentum_break_by_mslf": 1,
      "pl": 9.5,
      "pvp": 2.25,
      "ev_ebit": 6.62,
      "roic": 15.3,
      "cres_rec_5a": 3.1,
      "div_liq_vm": 0.47,
      "avaliacao_fundamentalista": 27,
      "distortion_ranking": 53
    },
    "CPLE3": {
      "ticker": "CPLE3",
      "setor": null,
      "subsetor": "Energia Elétrica",
      "fundamental_signal": 0,
      "vol_signal": 0,
      "posicao_setorial": "",
      "preco": 15.399999618530273,
      "vol_anualizada_30d": 0.21171150767826344,
      "alto_vol_persistente": 0,
      "mma9": 15.02777788374159,
      "mma10": 15.046000099182129,
      "mma26": 14.82153844833374,
      "mma50": 14.900399971008301,
      "mma150": 14.467199954986572,
      "mma200": 14.01889995574951,
      "pct_to_mma10": 2.3527815832420975,
      "pct_to_mma50": 3.352927763644215,
      "sup_min_by_mslf": 11.6,
      "sup_med_by_mslf": 11.7,
      "sup_max_by_mslf": 11.8,
      "res_min_by_mslf": 16.9,
      "res_med_by_mslf": "Foguete",
      "res_max_by_mslf": "Foguete",
      "std_raking_value_by_mslf": 2,
      "momentum_break_by_mslf": 1,
      "pl": 16.92,
      "pvp": 1.93,
      "ev_ebit": 12.52,
      "roic": 8.9,
      "cres_rec_5a": 2.7,
      "div_liq_vm": 0.39,
      "avaliacao_fundamentalista": 16,
      "distortion_ranking": 56
    },
    "CSAN3": {
      "ticker": "CSAN3",
      "setor": null,
      "subsetor": "Exploração. Refino e Distribuição",
      "fundamental_signal": 0,
      "vol_signal": 0,
      "posicao_setorial": "pior",
      "preco": 4.03000020980835,
      "vol_anualizada_30d": 0.441732782654866,
      "alto_vol_persistente": 0,
      "mma9": 3.8022222254011364,
      "mma10": 3.79300000667572,
      "mma26": 3.6115384652064395,
      "mma50": 4.035400004386902,
      "mma150": 5.089800009727478,
      "mma200": 5.340899995565414,
      "pct_to_mma10": 6.248357572251691,
      "pct_to_mma50": -0.13381064015170382,
      "sup_min_by_mslf": "Abismo",
      "sup_med_by_mslf": "Abismo",
      "sup_max_by_mslf": 3.2,
      "res_min_by_mslf": 5.0,
      "res_med_by_mslf": 5.1,
      "res_max_by_mslf": 5.2,
      "std_raking_value_by_mslf": 1,
      "momentum_break_by_mslf": -1,
      "pl": -1.68,
      "pvp": 4.58,
      "ev_ebit": 6.99,
      "roic": 8.5,
      "cres_rec_5a": 7.8,
      "div_liq_vm": 2.97,
      "avaliacao_fundamentalista": 18,
      "distortion_ranking": 51
    },
    "CSMG3": {
      "ticker": "CSMG3",
      "setor": null,
      "subsetor": "Água e Saneamento",
      "fundamental_signal": 0,
      "vol_signal": -1,
      "posicao_setorial": "pior",
      "preco": 66.8499984741211,
      "vol_anualizada_30d": 0.4830315357293746,
      "alto_vol_persistente": 0,
      "mma9": 62.74111090766059,
      "mma10": 62.533999633789065,
      "mma26": 59.64115348229041,
      "mma50": 56.572999801635746,
      "mma150": 53.01999989827474,
      "mma200": 48.85954990386963,
      "pct_to_mma10": 6.901843582063092,
      "pct_to_mma50": 18.165907249960252,
      "sup_min_by_mslf": 27.7,
      "sup_med_by_mslf": 27.9,
      "sup_max_by_mslf": 66.8,
      "res_min_by_mslf": "Foguete",
      "res_med_by_mslf": "Foguete",
      "res_max_by_mslf": "Foguete",
      "std_raking_value_by_mslf": 1,
      "momentum_break_by_mslf": 1,
      "pl": 18.78,
      "pvp": 2.9,
      "ev_ebit": 12.39,
      "roic": 11.6,
      "cres_rec_5a": 9.5,
      "div_liq_vm": 0.27,
      "avaliacao_fundamentalista": 20,
      "distortion_ranking": 69
    },
    "CSNA3": {
      "ticker": "CSNA3",
      "setor": null,
      "subsetor": "Siderurgia",
      "fundamental_signal": -1,
      "vol_signal": -1,
      "posicao_setorial": "",
      "preco": 5.179999828338623,
      "vol_anualizada_30d": 0.6421973061680877,
      "alto_vol_persistente": 0,
      "mma9": 4.755555576748318,
      "mma10": 4.744000005722046,
      "mma26": 5.265769279920137,
      "mma50": 5.864400033950806,
      "mma150": 7.466733344395956,
      "mma200": 7.715849997997284,
      "pct_to_mma10": 9.190552742215214,
      "pct_to_mma50": -11.67042155463441,
      "sup_min_by_mslf": "Abismo",
      "sup_med_by_mslf": "Abismo",
      "sup_max_by_mslf": 4.5,
      "res_min_by_mslf": 7.8,
      "res_med_by_mslf": 7.9,
      "res_max_by_mslf": 8.1,
      "std_raking_value_by_mslf": 2,
      "momentum_break_by_mslf": -1,
      "pl": -3.43,
      "pvp": 0.53,
      "ev_ebit": 7.24,
      "roic": 8.0,
      "cres_rec_5a": -1.2,
      "div_liq_vm": 5.39,
      "avaliacao_fundamentalista": 14,
      "distortion_ranking": 40
    },
    "CURY3": {
      "ticker": "CURY3",
      "setor": null,
      "subsetor": "Incorporações",
      "fundamental_signal": 1,
      "vol_signal": -1,
      "posicao_setorial": "melhor",
      "preco": 33.959999084472656,
      "vol_anualizada_30d": 0.45325733166752535,
      "alto_vol_persistente": 0,
      "mma9": 33.921111424764,
      "mma10": 34.06500034332275,
      "mma26": 33.05615410437951,
      "mma50": 31.949000205993652,
      "mma150": 34.171133308410646,
      "mma200": 34.22959997177124,
      "pct_to_mma10": -0.3082379503650192,
      "pct_to_mma50": 6.29440315976379,
      "sup_min_by_mslf": 33.5,
      "sup_med_by_mslf": 33.7,
      "sup_max_by_mslf": 33.8,
      "res_min_by_mslf": 34.1,
      "res_med_by_mslf": 34.2,
      "res_max_by_mslf": 34.4,
      "std_raking_value_by_mslf": 2,
      "momentum_break_by_mslf": 0,
      "pl": 9.82,
      "pvp": 6.78,
      "ev_ebit": 6.0,
      "roic": 37.6,
      "cres_rec_5a": 33.2,
      "div_liq_vm": -0.04,
      "avaliacao_fundamentalista": 35,
      "distortion_ranking": 43
    },
    "CXSE3": {
      "ticker": "CXSE3",
      "setor": null,
      "subsetor": "Seguradoras",
      "fundamental_signal": 0,
      "vol_signal": 1,
      "posicao_setorial": "pior",
      "preco": 21.940000534057617,
      "vol_anualizada_30d": 0.16565505108538411,
      "alto_vol_persistente": 0,
      "mma9": 20.707777871025932,
      "mma10": 20.607999992370605,
      "mma26": 19.52230768937331,
      "mma50": 18.585200080871584,
      "mma150": 17.851533438364665,
      "mma200": 17.172550082206726,
      "pct_to_mma10": 6.463511947690893,
      "pct_to_mma50": 18.050924599078648,
      "sup_min_by_mslf": 14.9,
      "sup_med_by_mslf": 16.2,
      "sup_max_by_mslf": 16.5,
      "res_min_by_mslf": 22.0,
      "res_med_by_mslf": "Foguete",
      "res_max_by_mslf": "Foguete",
      "std_raking_value_by_mslf": 1,
      "momentum_break_by_mslf": 1,
      "pl": 15.03,
      "pvp": 4.78,
      "ev_ebit": -324.62,
      "roic": -1.1,
      "cres_rec_5a": 0.0,
      "div_liq_vm": -0.02,
      "avaliacao_fundamentalista": 17,
      "distortion_ranking": 72
    },
    "CYRE3": {
      "ticker": "CYRE3",
      "setor": null,
      "subsetor": "Incorporações",
      "fundamental_signal": 0,
      "vol_signal": 0,
      "posicao_setorial": "",
      "preco": 23.270000457763672,
      "vol_anualizada_30d": 0.44285207356520784,
      "alto_vol_persistente": 0,
      "mma9": 22.661110983954536,
      "mma10": 22.720999908447265,
      "mma26": 21.918461579542893,
      "mma50": 22.05740005493164,
      "mma150": 26.605933316548665,
      "mma200": 27.79744996070862,
      "pct_to_mma10": 2.416269317057205,
      "pct_to_mma50": 5.497476582970689,
      "sup_min_by_mslf": 22.7,
      "sup_med_by_mslf": 22.9,
      "sup_max_by_mslf": 23.0,
      "res_min_by_mslf": 23.4,
      "res_med_by_mslf": 23.6,
      "res_max_by_mslf": 23.7,
      "std_raking_value_by_mslf": 1,
      "momentum_break_by_mslf": 0,
      "pl": 5.37,
      "pvp": 1.0,
      "ev_ebit": 9.74,
      "roic": 6.9,
      "cres_rec_5a": 18.5,
      "div_liq_vm": 0.46,
      "avaliacao_fundamentalista": 27,
      "distortion_ranking": 49
    },
    "DIRR3": {
      "ticker": "DIRR3",
      "setor": null,
      "subsetor": "Incorporações",
      "fundamental_signal": 1,
      "vol_signal": 0,
      "posicao_setorial": "",
      "preco": 13.239999771118164,
      "vol_anualizada_30d": 0.425053303445242,
      "alto_vol_persistente": 0,
      "mma9": 13.534444279140896,
      "mma10": 13.597999858856202,
      "mma26": 13.458076880528377,
      "mma50": 13.292999992370605,
      "mma150": 14.247466678619384,
      "mma200": 14.81965000152588,
      "pct_to_mma10": -2.6327407813942356,
      "pct_to_mma50": -0.3987077505669163,
      "sup_min_by_mslf": 10.2,
      "sup_med_by_mslf": 10.3,
      "sup_max_by_mslf": 13.1,
      "res_min_by_mslf": 13.5,
      "res_med_by_mslf": 13.6,
      "res_max_by_mslf": 13.8,
      "std_raking_value_by_mslf": 1,
      "momentum_break_by_mslf": 0,
      "pl": 8.22,
      "pvp": 3.24,
      "ev_ebit": 6.74,
      "roic": 10.1,
      "cres_rec_5a": 26.0,
      "div_liq_vm": 0.11,
      "avaliacao_fundamentalista": 32,
      "distortion_ranking": 25
    },
    "EGIE3": {
      "ticker": "EGIE3",
      "setor": null,
      "subsetor": "Energia Elétrica",
      "fundamental_signal": 0,
      "vol_signal": 0,
      "posicao_setorial": "",
      "preco": 33.45000076293945,
      "vol_anualizada_30d": 0.3234809862201636,
      "alto_vol_persistente": 0,
      "mma9": 32.82222196790907,
      "mma10": 32.957999801635744,
      "mma26": 33.62692319429838,
      "mma50": 33.40660018920899,
      "mma150": 32.95566673278809,
      "mma200": 32.09444277763367,
      "pct_to_mma10": 1.4928119554126915,
      "pct_to_mma50": 0.12991616472389542,
      "sup_min_by_mslf": 32.7,
      "sup_med_by_mslf": 32.9,
      "sup_max_by_mslf": 33.1,
      "res_min_by_mslf": 39.4,
      "res_med_by_mslf": "Foguete",
      "res_max_by_mslf": "Foguete",
      "std_raking_value_by_mslf": 1,
      "momentum_break_by_mslf": 1,
      "pl": 14.87,
      "pvp": 2.81,
      "ev_ebit": 10.96,
      "roic": 11.1,
      "cres_rec_5a": 1.3,
      "div_liq_vm": 0.65,
      "avaliacao_fundamentalista": 19,
      "distortion_ranking": 43
    },
    "EMBJ3": {
      "ticker": "EMBJ3",
      "setor": null,
      "subsetor": "Material Aeronáutico e de Defesa",
      "fundamental_signal": 0,
      "vol_signal": 0,
      "posicao_setorial": "pior",
      "preco": 85.16999816894531,
      "vol_anualizada_30d": 0.38831499096987077,
      "alto_vol_persistente": 0,
      "mma9": 83.75444454616971,
      "mma10": 83.39700012207031,
      "mma26": 79.12961519681491,
      "mma50": 76.58359954833985,
      "mma150": 84.20353317260742,
      "mma200": 83.80749988555908,
      "pct_to_mma10": 2.1259734094509644,
      "pct_to_mma50": 11.211798180347607,
      "sup_min_by_mslf": 84.4,
      "sup_med_by_mslf": 84.6,
      "sup_max_by_mslf": 85.1,
      "res_min_by_mslf": 85.3,
      "res_med_by_mslf": 86.4,
      "res_max_by_mslf": 86.8,
      "std_raking_value_by_mslf": 1,
      "momentum_break_by_mslf": 0,
      "pl": 37.19,
      "pvp": 3.67,
      "ev_ebit": 12.43,
      "roic": 9.1,
      "cres_rec_5a": 20.3,
      "div_liq_vm": 0.05,
      "avaliacao_fundamentalista": 18,
      "distortion_ranking": 65
    },
    "ENEV3": {
      "ticker": "ENEV3",
      "setor": null,
      "subsetor": "Energia Elétrica",
      "fundamental_signal": 0,
      "vol_signal": 0,
      "posicao_setorial": "",
      "preco": 27.34000015258789,
      "vol_anualizada_30d": 0.3484512421595306,
      "alto_vol_persistente": 0,
      "mma9": 26.292222128974068,
      "mma10": 26.333999824523925,
      "mma26": 25.367692360511192,
      "mma50": 25.568799896240236,
      "mma150": 23.384466654459636,
      "mma200": 21.976300010681154,
      "pct_to_mma10": 3.8201577229719312,
      "pct_to_mma50": 6.927193546569625,
      "sup_min_by_mslf": 14.4,
      "sup_med_by_mslf": 14.5,
      "sup_max_by_mslf": 14.6,
      "res_min_by_mslf": 28.1,
      "res_med_by_mslf": "Foguete",
      "res_max_by_mslf": "Foguete",
      "std_raking_value_by_mslf": 1,
      "momentum_break_by_mslf": 1,
      "pl": 40.81,
      "pvp": 2.6,
      "ev_ebit": 20.52,
      "roic": 6.1,
      "cres_rec_5a": 38.1,
      "div_liq_vm": 0.35,
      "avaliacao_fundamentalista": 18,
      "distortion_ranking": 65
    },
    "ENGI11": {
      "ticker": "ENGI11",
      "setor": null,
      "subsetor": "Energia Elétrica",
      "fundamental_signal": 0,
      "vol_signal": 0,
      "posicao_setorial": "",
      "preco": 51.68000030517578,
      "vol_anualizada_30d": 0.23910462156156606,
      "alto_vol_persistente": 0,
      "mma9": 48.78222190009223,
      "mma10": 48.69699974060059,
      "mma26": 47.316153893103966,
      "mma50": 48.46180015563965,
      "mma150": 50.322466659545896,
      "mma200": 49.44535888671875,
      "pct_to_mma10": 6.1256352146231885,
      "pct_to_mma50": 6.640694607300135,
      "sup_min_by_mslf": 49.0,
      "sup_med_by_mslf": 49.2,
      "sup_max_by_mslf": 49.8,
      "res_min_by_mslf": 51.7,
      "res_med_by_mslf": 58.6,
      "res_max_by_mslf": "Foguete",
      "std_raking_value_by_mslf": 1,
      "momentum_break_by_mslf": 0,
      "pl": 13.67,
      "pvp": 1.32,
      "ev_ebit": 8.37,
      "roic": 9.6,
      "cres_rec_5a": 8.0,
      "div_liq_vm": 0.26,
      "avaliacao_fundamentalista": 22,
      "distortion_ranking": 63
    },
    "EQTL3": {
      "ticker": "EQTL3",
      "setor": null,
      "subsetor": "Energia Elétrica",
      "fundamental_signal": 0,
      "vol_signal": 0,
      "posicao_setorial": "",
      "preco": 40.689998626708984,
      "vol_anualizada_30d": 0.23005291960408808,
      "alto_vol_persistente": 0,
      "mma9": 39.27444415622287,
      "mma10": 39.32099990844726,
      "mma26": 38.662307445819565,
      "mma50": 39.19419990539551,
      "mma150": 40.18826667785645,
      "mma200": 39.46529998779297,
      "pct_to_mma10": 3.481596911190506,
      "pct_to_mma50": 3.81637774192085,
      "sup_min_by_mslf": 39.5,
      "sup_med_by_mslf": 39.7,
      "sup_max_by_mslf": 39.8,
      "res_min_by_mslf": 46.3,
      "res_med_by_mslf": "Foguete",
      "res_max_by_mslf": "Foguete",
      "std_raking_value_by_mslf": 1,
      "momentum_break_by_mslf": 1,
      "pl": 33.08,
      "pvp": 1.99,
      "ev_ebit": 9.62,
      "roic": 10.2,
      "cres_rec_5a": 20.2,
      "div_liq_vm": 0.9,
      "avaliacao_fundamentalista": 21,
      "distortion_ranking": 54
    },
    "FLRY3": {
      "ticker": "FLRY3",
      "setor": null,
      "subsetor": "ServMédHospit Análises e Diagnósticos00",
      "fundamental_signal": 0,
      "vol_signal": 0,
      "posicao_setorial": "melhor",
      "preco": 16.329999923706055,
      "vol_anualizada_30d": 0.2757134198472585,
      "alto_vol_persistente": 0,
      "mma9": 15.67666647169325,
      "mma10": 15.666999816894531,
      "mma26": 15.264999866485596,
      "mma50": 15.557799892425537,
      "mma150": 15.871200014750162,
      "mma200": 15.76204999446869,
      "pct_to_mma10": 4.2318255860102605,
      "pct_to_mma50": 4.963426940955003,
      "sup_min_by_mslf": 15.6,
      "sup_med_by_mslf": 15.8,
      "sup_max_by_mslf": 16.0,
      "res_min_by_mslf": 16.6,
      "res_med_by_mslf": 18.1,
      "res_max_by_mslf": "Foguete",
      "std_raking_value_by_mslf": 1,
      "momentum_break_by_mslf": 0,
      "pl": 14.08,
      "pvp": 1.72,
      "ev_ebit": 9.01,
      "roic": 12.3,
      "cres_rec_5a": 22.1,
      "div_liq_vm": 0.36,
      "avaliacao_fundamentalista": 28,
      "distortion_ranking": 52
    },
    "GGBR4": {
      "ticker": "GGBR4",
      "setor": null,
      "subsetor": "Siderurgia",
      "fundamental_signal": 0,
      "vol_signal": 0,
      "posicao_setorial": "",
      "preco": 22.93000030517578,
      "vol_anualizada_30d": 0.3380869949572933,
      "alto_vol_persistente": 0,
      "mma9": 21.72222222222222,
      "mma10": 21.679000091552734,
      "mma26": 22.27538460951585,
      "mma50": 22.89780002593994,
      "mma150": 21.40880001068115,
      "mma200": 20.577200021743774,
      "pct_to_mma10": 5.770562333778956,
      "pct_to_mma50": 0.14062608285233866,
      "sup_min_by_mslf": 18.6,
      "sup_med_by_mslf": 18.9,
      "sup_max_by_mslf": 19.0,
      "res_min_by_mslf": 24.6,
      "res_med_by_mslf": "Foguete",
      "res_max_by_mslf": "Foguete",
      "std_raking_value_by_mslf": 1,
      "momentum_break_by_mslf": 1,
      "pl": 27.63,
      "pvp": 0.86,
      "ev_ebit": 8.72,
      "roic": 8.9,
      "cres_rec_5a": -5.1,
      "div_liq_vm": 0.18,
      "avaliacao_fundamentalista": 15,
      "distortion_ranking": 54
    },
    "GOAU4": {
      "ticker": "GOAU4",
      "setor": null,
      "subsetor": "Siderurgia",
      "fundamental_signal": 0,
      "vol_signal": 0,
      "posicao_setorial": "melhor",
      "preco": 10.119999885559082,
      "vol_anualizada_30d": 0.3350860546336217,
      "alto_vol_persistente": 0,
      "mma9": 9.585555500454372,
      "mma10": 9.56899995803833,
      "mma26": 9.815384644728441,
      "mma50": 10.016800022125244,
      "mma150": 9.442236636479695,
      "mma200": 9.037163753509521,
      "pct_to_mma10": 5.758176715821714,
      "pct_to_mma50": 1.0302677821848194,
      "sup_min_by_mslf": 8.0,
      "sup_med_by_mslf": 8.1,
      "sup_max_by_mslf": 8.3,
      "res_min_by_mslf": 10.8,
      "res_med_by_mslf": "Foguete",
      "res_max_by_mslf": "Foguete",
      "std_raking_value_by_mslf": 1,
      "momentum_break_by_mslf": 1,
      "pl": 23.53,
      "pvp": 0.71,
      "ev_ebit": 3.46,
      "roic": 8.9,
      "cres_rec_5a": -5.1,
      "div_liq_vm": 0.61,
      "avaliacao_fundamentalista": 19,
      "distortion_ranking": 50
    },
    "HAPV3": {
      "ticker": "HAPV3",
      "setor": null,
      "subsetor": "ServMédHospit Análises e Diagnósticos00",
      "fundamental_signal": 0,
      "vol_signal": 0,
      "posicao_setorial": "pior",
      "preco": 10.619999885559082,
      "vol_anualizada_30d": 0.4447957721395674,
      "alto_vol_persistente": 0,
      "mma9": 10.335555500454372,
      "mma10": 10.336999988555908,
      "mma26": 10.634615347935604,
      "mma50": 11.41879997253418,
      "mma150": 11.977333316802978,
      "mma200": 16.50444996356964,
      "pct_to_mma10": 2.7377372285622847,
      "pct_to_mma50": -6.995481914881283,
      "sup_min_by_mslf": 10.4,
      "sup_med_by_mslf": 10.5,
      "sup_max_by_mslf": 10.6,
      "res_min_by_mslf": 10.7,
      "res_med_by_mslf": 11.0,
      "res_max_by_mslf": 11.1,
      "std_raking_value_by_mslf": 2,
      "momentum_break_by_mslf": 0,
      "pl": -12.49,
      "pvp": 0.11,
      "ev_ebit": 10.11,
      "roic": 1.7,
      "cres_rec_5a": 25.1,
      "div_liq_vm": 0.93,
      "avaliacao_fundamentalista": 18,
      "distortion_ranking": 34
    },
    "HYPE3": {
      "ticker": "HYPE3",
      "setor": null,
      "subsetor": "Medicamentos e Outros Produtos",
      "fundamental_signal": 0,
      "vol_signal": 0,
      "posicao_setorial": "",
      "preco": 20.969999313354492,
      "vol_anualizada_30d": 0.2759474369733895,
      "alto_vol_persistente": 0,
      "mma9": 20.67888895670573,
      "mma10": 20.727000045776368,
      "mma26": 20.769615393418533,
      "mma50": 21.672800025939942,
      "mma150": 22.87593334197998,
      "mma200": 23.121900005340578,
      "pct_to_mma10": 1.172380310905829,
      "pct_to_mma50": -3.2427776371501396,
      "sup_min_by_mslf": 16.8,
      "sup_med_by_mslf": 19.4,
      "sup_max_by_mslf": 19.5,
      "res_min_by_mslf": 22.4,
      "res_med_by_mslf": 22.5,
      "res_max_by_mslf": 22.6,
      "std_raking_value_by_mslf": 1,
      "momentum_break_by_mslf": 0,
      "pl": 8.77,
      "pvp": 1.05,
      "ev_ebit": 8.66,
      "roic": 10.6,
      "cres_rec_5a": 5.1,
      "div_liq_vm": 0.42,
      "avaliacao_fundamentalista": 24,
      "distortion_ranking": 30
    },
    "IGTI11": {
      "ticker": "IGTI11",
      "setor": null,
      "subsetor": "Exploração de Imóveis",
      "fundamental_signal": 0,
      "vol_signal": 0,
      "posicao_setorial": "",
      "preco": 26.309999465942383,
      "vol_anualizada_30d": 0.2750017017156561,
      "alto_vol_persistente": 0,
      "mma9": 25.357777701483833,
      "mma10": 25.351000022888183,
      "mma26": 24.765384747431828,
      "mma50": 25.652799949645996,
      "mma150": 26.9000665918986,
      "mma200": 26.32859992980957,
      "pct_to_mma10": 3.7828860486306897,
      "pct_to_mma50": 2.561901693329412,
      "sup_min_by_mslf": 24.0,
      "sup_med_by_mslf": 24.1,
      "sup_max_by_mslf": 24.2,
      "res_min_by_mslf": 26.4,
      "res_med_by_mslf": 30.6,
      "res_max_by_mslf": "Foguete",
      "std_raking_value_by_mslf": 1,
      "momentum_break_by_mslf": 0,
      "pl": 10.96,
      "pvp": 1.6,
      "ev_ebit": 9.99,
      "roic": 12.6,
      "cres_rec_5a": 12.8,
      "div_liq_vm": 0.03,
      "avaliacao_fundamentalista": 27,
      "distortion_ranking": 44
    },
    "ISAE4": {
      "ticker": "ISAE4",
      "setor": null,
      "subsetor": "Energia Elétrica",
      "fundamental_signal": 0,
      "vol_signal": 0,
      "posicao_setorial": "",
      "preco": 29.829999923706055,
      "vol_anualizada_30d": 0.252742461049487,
      "alto_vol_persistente": 0,
      "mma9": 28.54000006781684,
      "mma10": 28.511000061035155,
      "mma26": 27.912307885976936,
      "mma50": 28.2206001663208,
      "mma150": 28.30213333129883,
      "mma200": 27.57060002326965,
      "pct_to_mma10": 4.626284100337555,
      "pct_to_mma50": 5.702925337874119,
      "sup_min_by_mslf": 25.5,
      "sup_med_by_mslf": 27.1,
      "sup_max_by_mslf": 27.7,
      "res_min_by_mslf": 32.2,
      "res_med_by_mslf": "Foguete",
      "res_max_by_mslf": "Foguete",
      "std_raking_value_by_mslf": 1,
      "momentum_break_by_mslf": 1,
      "pl": 8.38,
      "pvp": 0.92,
      "ev_ebit": 9.12,
      "roic": 7.7,
      "cres_rec_5a": 14.8,
      "div_liq_vm": 0.76,
      "avaliacao_fundamentalista": 25,
      "distortion_ranking": 55
    },
    "ITSA4": {
      "ticker": "ITSA4",
      "setor": null,
      "subsetor": "Bancos",
      "fundamental_signal": 0,
      "vol_signal": 0,
      "posicao_setorial": "",
      "preco": 14.109999656677246,
      "vol_anualizada_30d": 0.21390295259674716,
      "alto_vol_persistente": 0,
      "mma9": 13.539999961853027,
      "mma10": 13.538000011444092,
      "mma26": 13.13999997652494,
      "mma50": 13.122399997711181,
      "mma150": 13.241079699198405,
      "mma200": 12.74737828731537,
      "pct_to_mma10": 4.225141414903419,
      "pct_to_mma50": 7.526059708119879,
      "sup_min_by_mslf": 11.1,
      "sup_med_by_mslf": 11.2,
      "sup_max_by_mslf": 11.4,
      "res_min_by_mslf": 15.2,
      "res_med_by_mslf": "Foguete",
      "res_max_by_mslf": "Foguete",
      "std_raking_value_by_mslf": 1,
      "momentum_break_by_mslf": 1,
      "pl": 9.34,
      "pvp": 1.75,
      "ev_ebit": 387.73,
      "roic": 0.4,
      "cres_rec_5a": -0.2,
      "div_liq_vm": 0.03,
      "avaliacao_fundamentalista": 24,
      "distortion_ranking": 59
    },
    "ITUB4": {
      "ticker": "ITUB4",
      "setor": null,
      "subsetor": "Bancos",
      "fundamental_signal": 0,
      "vol_signal": 0,
      "posicao_setorial": "",
      "preco": 44.04999923706055,
      "vol_anualizada_30d": 0.21001247809195397,
      "alto_vol_persistente": 0,
      "mma9": 42.5944446987576,
      "mma10": 42.57600021362305,
      "mma26": 41.21923109201285,
      "mma50": 40.7902001953125,
      "mma150": 42.35322898864746,
      "mma200": 41.231426525115964,
      "pct_to_mma10": 3.462042033168405,
      "pct_to_mma50": 7.991623051957106,
      "sup_min_by_mslf": 40.6,
      "sup_med_by_mslf": 41.4,
      "sup_max_by_mslf": 42.1,
      "res_min_by_mslf": 49.7,
      "res_med_by_mslf": "Foguete",
      "res_max_by_mslf": "Foguete",
      "std_raking_value_by_mslf": 1,
      "momentum_break_by_mslf": 1,
      "pl": 10.46,
      "pvp": 2.43,
      "ev_ebit": 0.0,
      "roic": 0.0,
      "cres_rec_5a": 71.6,
      "div_liq_vm": 0.0,
      "avaliacao_fundamentalista": 29,
      "distortion_ranking": 57
    },
    "KLBN11": {
      "ticker": "KLBN11",
      "setor": null,
      "subsetor": "Papel e Celulose",
      "fundamental_signal": -1,
      "vol_signal": 1,
      "posicao_setorial": "pior",
      "preco": 17.510000228881836,
      "vol_anualizada_30d": 0.14093415728421765,
      "alto_vol_persistente": 0,
      "mma9": 17.109999974568684,
      "mma10": 17.08799991607666,
      "mma26": 17.026922959547775,
      "mma50": 16.912199935913087,
      "mma150": 18.35943955739339,
      "mma200": 18.196460695266722,
      "pct_to_mma10": 2.469571131072805,
      "pct_to_mma50": 3.534728156207042,
      "sup_min_by_mslf": "Abismo",
      "sup_med_by_mslf": "Abismo",
      "sup_max_by_mslf": 16.1,
      "res_min_by_mslf": 17.7,
      "res_med_by_mslf": 17.8,
      "res_max_by_mslf": 17.9,
      "std_raking_value_by_mslf": 1,
      "momentum_break_by_mslf": -1,
      "pl": 29.18,
      "pvp": 2.42,
      "ev_ebit": 14.72,
      "roic": 6.3,
      "cres_rec_5a": 3.4,
      "div_liq_vm": 0.23,
      "avaliacao_fundamentalista": 13,
      "distortion_ranking": 59
    },
    "LREN3": {
      "ticker": "LREN3",
      "setor": null,
      "subsetor": "Tecidos. Vestuário e Calçados",
      "fundamental_signal": 1,
      "vol_signal": 0,
      "posicao_setorial": "",
      "preco": 14.739999771118164,
      "vol_anualizada_30d": 0.38444578363391857,
      "alto_vol_persistente": 0,
      "mma9": 14.39555549621582,
      "mma10": 14.454999923706055,
      "mma26": 14.64846159861638,
      "mma50": 14.525200080871581,
      "mma150": 14.643333384195964,
      "mma200": 14.708800039291383,
      "pct_to_mma10": 1.9716350668719997,
      "pct_to_mma50": 1.4788071011115032,
      "sup_min_by_mslf": 13.4,
      "sup_med_by_mslf": 14.4,
      "sup_max_by_mslf": 14.6,
      "res_min_by_mslf": 15.0,
      "res_med_by_mslf": 15.1,
      "res_max_by_mslf": 15.2,
      "std_raking_value_by_mslf": 2,
      "momentum_break_by_mslf": 0,
      "pl": 9.96,
      "pvp": 1.43,
      "ev_ebit": 3.73,
      "roic": 23.8,
      "cres_rec_5a": 7.6,
      "div_liq_vm": -0.1,
      "avaliacao_fundamentalista": 32,
      "distortion_ranking": 31
    },
    "MBRF3": {
      "ticker": "MBRF3",
      "setor": null,
      "subsetor": "Carnes e Derivados",
      "fundamental_signal": 0,
      "vol_signal": -1,
      "posicao_setorial": "pior",
      "preco": 15.800000190734863,
      "vol_anualizada_30d": 0.45861396590406295,
      "alto_vol_persistente": 0,
      "mma9": 16.497777938842773,
      "mma10": 16.61800022125244,
      "mma26": 16.184230731083797,
      "mma50": 16.499200038909912,
      "mma150": 18.331933409372965,
      "mma200": 18.40395005226135,
      "pct_to_mma10": -4.922373448229065,
      "pct_to_mma50": -4.237780295566646,
      "sup_min_by_mslf": 15.3,
      "sup_med_by_mslf": 15.5,
      "sup_max_by_mslf": 15.7,
      "res_min_by_mslf": 15.9,
      "res_med_by_mslf": 16.1,
      "res_max_by_mslf": 16.4,
      "std_raking_value_by_mslf": 1,
      "momentum_break_by_mslf": 0,
      "pl": 58.52,
      "pvp": 1.94,
      "ev_ebit": 12.35,
      "roic": 6.3,
      "cres_rec_5a": 13.9,
      "div_liq_vm": 2.24,
      "avaliacao_fundamentalista": 16,
      "distortion_ranking": 33
    },
    "MGLU3": {
      "ticker": "MGLU3",
      "setor": null,
      "subsetor": "Eletrodomésticos",
      "fundamental_signal": 0,
      "vol_signal": -1,
      "posicao_setorial": "pior",
      "preco": 5.210000038146973,
      "vol_anualizada_30d": 0.6580847403055448,
      "alto_vol_persistente": 0,
      "mma9": 4.575555536482069,
      "mma10": 4.581999969482422,
      "mma26": 4.779615347202007,
      "mma50": 5.775799961090088,
      "mma150": 8.122939580281576,
      "mma200": 8.285871212482453,
      "pct_to_mma10": 13.70580691504214,
      "pct_to_mma50": -9.796044301304534,
      "sup_min_by_mslf": "Abismo",
      "sup_med_by_mslf": "Abismo",
      "sup_max_by_mslf": 4.0,
      "res_min_by_mslf": 8.4,
      "res_med_by_mslf": 8.5,
      "res_max_by_mslf": 8.6,
      "std_raking_value_by_mslf": 1,
      "momentum_break_by_mslf": -1,
      "pl": 28.94,
      "pvp": 0.36,
      "ev_ebit": 5.29,
      "roic": 6.1,
      "cres_rec_5a": 1.6,
      "div_liq_vm": 0.85,
      "avaliacao_fundamentalista": 17,
      "distortion_ranking": 37
    },
    "MOTV3": {
      "ticker": "MOTV3",
      "setor": null,
      "subsetor": "Exploração de Rodovias",
      "fundamental_signal": 0,
      "vol_signal": 1,
      "posicao_setorial": "melhor",
      "preco": 15.069999694824219,
      "vol_anualizada_30d": 0.19056438032965428,
      "alto_vol_persistente": 0,
      "mma9": 14.667777803209093,
      "mma10": 14.671000003814697,
      "mma26": 14.265769224900465,
      "mma50": 14.571399974822999,
      "mma150": 15.536933358510336,
      "mma200": 15.464550008773804,
      "pct_to_mma10": 2.7196489053627912,
      "pct_to_mma50": 3.421769499586306,
      "sup_min_by_mslf": 13.9,
      "sup_med_by_mslf": 14.0,
      "sup_max_by_mslf": 14.8,
      "res_min_by_mslf": 15.4,
      "res_med_by_mslf": 17.8,
      "res_max_by_mslf": "Foguete",
      "std_raking_value_by_mslf": 1,
      "momentum_break_by_mslf": 0,
      "pl": 9.08,
      "pvp": 1.86,
      "ev_ebit": 8.5,
      "roic": 10.9,
      "cres_rec_5a": 5.7,
      "div_liq_vm": 1.01,
      "avaliacao_fundamentalista": 26,
      "distortion_ranking": 46
    },
    "MRVE3": {
      "ticker": "MRVE3",
      "setor": null,
      "subsetor": "Incorporações",
      "fundamental_signal": 0,
      "vol_signal": 0,
      "posicao_setorial": "pior",
      "preco": 5.070000171661377,
      "vol_anualizada_30d": 0.4219741427283121,
      "alto_vol_persistente": 0,
      "mma9": 5.166666719648573,
      "mma10": 5.174000024795532,
      "mma26": 5.163461538461538,
      "mma50": 5.705399980545044,
      "mma150": 7.4400666777292885,
      "mma200": 7.454950010776519,
      "pct_to_mma10": -2.010047403087617,
      "pct_to_mma50": -11.13681443983471,
      "sup_min_by_mslf": "Abismo",
      "sup_med_by_mslf": 4.4,
      "sup_max_by_mslf": 5.0,
      "res_min_by_mslf": 5.1,
      "res_med_by_mslf": 5.3,
      "res_max_by_mslf": 5.4,
      "std_raking_value_by_mslf": 2,
      "momentum_break_by_mslf": 0,
      "pl": -3.76,
      "pvp": 0.55,
      "ev_ebit": 6.32,
      "roic": 6.6,
      "cres_rec_5a": 13.5,
      "div_liq_vm": 2.78,
      "avaliacao_fundamentalista": 20,
      "distortion_ranking": 25
    },
    "MULT3": {
      "ticker": "MULT3",
      "setor": null,
      "subsetor": "Exploração de Imóveis",
      "fundamental_signal": 0,
      "vol_signal": 0,
      "posicao_setorial": "melhor",
      "preco": 30.299999237060547,
      "vol_anualizada_30d": 0.23803126846589623,
      "alto_vol_persistente": 0,
      "mma9": 29.107777913411457,
      "mma10": 29.1560001373291,
      "mma26": 28.75846165877122,
      "mma50": 29.478999977111815,
      "mma150": 30.645733350118,
      "mma200": 30.094350070953368,
      "pct_to_mma10": 3.9237175687441326,
      "pct_to_mma50": 2.7850309053433784,
      "sup_min_by_mslf": 27.5,
      "sup_med_by_mslf": 28.8,
      "sup_max_by_mslf": 29.0,
      "res_min_by_mslf": 36.0,
      "res_med_by_mslf": "Foguete",
      "res_max_by_mslf": "Foguete",
      "std_raking_value_by_mslf": 1,
      "momentum_break_by_mslf": 1,
      "pl": 12.73,
      "pvp": 2.4,
      "ev_ebit": 9.38,
      "roic": 17.3,
      "cres_rec_5a": 19.9,
      "div_liq_vm": 0.29,
      "avaliacao_fundamentalista": 29,
      "distortion_ranking": 42
    },
    "NATU3": {
      "ticker": "NATU3",
      "setor": null,
      "subsetor": "Produtos de Uso Pessoal",
      "fundamental_signal": 0,
      "vol_signal": -1,
      "posicao_setorial": "pior",
      "preco": 8.550000190734863,
      "vol_anualizada_30d": 0.4886259753053786,
      "alto_vol_persistente": 0,
      "mma9": 8.420000076293945,
      "mma10": 8.408000087738037,
      "mma26": 8.347307737057026,
      "mma50": 9.19460000038147,
      "mma150": 8.957133293151855,
      "mma200": 8.86004997253418,
      "pct_to_mma10": 1.6888689523673415,
      "pct_to_mma50": -7.010634607485519,
      "sup_min_by_mslf": 8.1,
      "sup_med_by_mslf": 8.4,
      "sup_max_by_mslf": 8.5,
      "res_min_by_mslf": 8.6,
      "res_med_by_mslf": 8.7,
      "res_max_by_mslf": 8.9,
      "std_raking_value_by_mslf": 1,
      "momentum_break_by_mslf": 0,
      "pl": -5.06,
      "pvp": 0.94,
      "ev_ebit": 7.12,
      "roic": 11.6,
      "cres_rec_5a": 1.8,
      "div_liq_vm": 0.34,
      "avaliacao_fundamentalista": 19,
      "distortion_ranking": 32
    },
    "PETR3": {
      "ticker": "PETR3",
      "setor": null,
      "subsetor": "Exploração. Refino e Distribuição",
      "fundamental_signal": 0,
      "vol_signal": 0,
      "posicao_setorial": "",
      "preco": 43.95000076293945,
      "vol_anualizada_30d": 0.2549862621201565,
      "alto_vol_persistente": 0,
      "mma9": 42.69888814290365,
      "mma10": 42.659999465942384,
      "mma26": 43.70346128023588,
      "mma50": 46.6833999633789,
      "mma150": 43.688200035095214,
      "mma200": 41.0799000453949,
      "pct_to_mma10": 3.023913064103392,
      "pct_to_mma50": -5.855184503664435,
      "sup_min_by_mslf": 42.1,
      "sup_med_by_mslf": 42.6,
      "sup_max_by_mslf": 42.8,
      "res_min_by_mslf": 56.1,
      "res_med_by_mslf": "Foguete",
      "res_max_by_mslf": "Foguete",
      "std_raking_value_by_mslf": 1,
      "momentum_break_by_mslf": 1,
      "pl": 5.26,
      "pvp": 1.27,
      "ev_ebit": 4.8,
      "roic": 16.8,
      "cres_rec_5a": -2.9,
      "div_liq_vm": 0.57,
      "avaliacao_fundamentalista": 29,
      "distortion_ranking": 24
    },
    "PETR4": {
      "ticker": "PETR4",
      "setor": null,
      "subsetor": "Exploração. Refino e Distribuição",
      "fundamental_signal": 0,
      "vol_signal": 0,
      "posicao_setorial": "",
      "preco": 39.560001373291016,
      "vol_anualizada_30d": 0.23929489216169278,
      "alto_vol_persistente": 0,
      "mma9": 38.496666802300346,
      "mma10": 38.46100006103516,
      "mma26": 39.21538470341609,
      "mma50": 41.97819999694824,
      "mma150": 40.008333371480305,
      "mma200": 37.799250049591066,
      "pct_to_mma10": 2.857443411538475,
      "pct_to_mma50": -5.760605799755648,
      "sup_min_by_mslf": 38.5,
      "sup_med_by_mslf": 38.7,
      "sup_max_by_mslf": 39.4,
      "res_min_by_mslf": 50.7,
      "res_med_by_mslf": "Foguete",
      "res_max_by_mslf": "Foguete",
      "std_raking_value_by_mslf": 1,
      "momentum_break_by_mslf": 1,
      "pl": 4.74,
      "pvp": 1.15,
      "ev_ebit": 4.47,
      "roic": 16.8,
      "cres_rec_5a": -2.9,
      "div_liq_vm": 0.64,
      "avaliacao_fundamentalista": 30,
      "distortion_ranking": 23
    },
    "POMO4": {
      "ticker": "POMO4",
      "setor": null,
      "subsetor": "Material Rodoviário",
      "fundamental_signal": 1,
      "vol_signal": 0,
      "posicao_setorial": "melhor",
      "preco": 5.809999942779541,
      "vol_anualizada_30d": 0.27152261509307624,
      "alto_vol_persistente": 0,
      "mma9": 5.816666603088379,
      "mma10": 5.8249999523162845,
      "mma26": 5.8273076460911675,
      "mma50": 5.969599962234497,
      "mma150": 6.1470544751485185,
      "mma200": 6.454199843406677,
      "pct_to_mma10": -0.2575108954426486,
      "pct_to_mma50": -2.673546309043056,
      "sup_min_by_mslf": "Abismo",
      "sup_med_by_mslf": "Abismo",
      "sup_max_by_mslf": 5.3,
      "res_min_by_mslf": 7.1,
      "res_med_by_mslf": 7.2,
      "res_max_by_mslf": 9.0,
      "std_raking_value_by_mslf": 1,
      "momentum_break_by_mslf": -1,
      "pl": 5.81,
      "pvp": 1.79,
      "ev_ebit": 6.46,
      "roic": 20.5,
      "cres_rec_5a": 24.2,
      "div_liq_vm": 0.21,
      "avaliacao_fundamentalista": 36,
      "distortion_ranking": 18
    },
    "PRIO3": {
      "ticker": "PRIO3",
      "setor": null,
      "subsetor": "Exploração. Refino e Distribuição",
      "fundamental_signal": 0,
      "vol_signal": 0,
      "posicao_setorial": "",
      "preco": 55.369998931884766,
      "vol_anualizada_30d": 0.3169668699283435,
      "alto_vol_persistente": 0,
      "mma9": 54.14222208658854,
      "mma10": 54.043000030517575,
      "mma26": 56.58192297128531,
      "mma50": 60.98060005187988,
      "mma150": 55.612266565958656,
      "mma200": 51.127499923706054,
      "pct_to_mma10": 2.4554501056896294,
      "pct_to_mma50": -9.20063284917144,
      "sup_min_by_mslf": 43.0,
      "sup_med_by_mslf": 43.3,
      "sup_max_by_mslf": 43.8,
      "res_min_by_mslf": 73.0,
      "res_med_by_mslf": "Foguete",
      "res_max_by_mslf": "Foguete",
      "std_raking_value_by_mslf": 1,
      "momentum_break_by_mslf": 1,
      "pl": 18.64,
      "pvp": 1.81,
      "ev_ebit": 20.97,
      "roic": 6.4,
      "cres_rec_5a": 36.8,
      "div_liq_vm": 0.5,
      "avaliacao_fundamentalista": 19,
      "distortion_ranking": 29
    },
    "PSSA3": {
      "ticker": "PSSA3",
      "setor": null,
      "subsetor": "Seguradoras",
      "fundamental_signal": 0,
      "vol_signal": 0,
      "posicao_setorial": "melhor",
      "preco": 54.45000076293945,
      "vol_anualizada_30d": 0.2226797320111523,
      "alto_vol_persistente": 0,
      "mma9": 53.193333095974396,
      "mma10": 53.20399971008301,
      "mma26": 51.753076846782974,
      "mma50": 50.4710001373291,
      "mma150": 50.033200073242185,
      "mma200": 49.46309999465942,
      "pct_to_mma10": 2.3419311699235,
      "pct_to_mma50": 7.883736432374413,
      "sup_min_by_mslf": 53.8,
      "sup_med_by_mslf": 53.9,
      "sup_max_by_mslf": 54.2,
      "res_min_by_mslf": 54.5,
      "res_med_by_mslf": 54.9,
      "res_max_by_mslf": 55.5,
      "std_raking_value_by_mslf": 1,
      "momentum_break_by_mslf": 0,
      "pl": 9.55,
      "pvp": 2.27,
      "ev_ebit": 0.52,
      "roic": 77.5,
      "cres_rec_5a": 15.8,
      "div_liq_vm": -0.37,
      "avaliacao_fundamentalista": 28,
      "distortion_ranking": 52
    },
    "RADL3": {
      "ticker": "RADL3",
      "setor": null,
      "subsetor": "Medicamentos e Outros Produtos",
      "fundamental_signal": 0,
      "vol_signal": 0,
      "posicao_setorial": "pior",
      "preco": 18.899999618530273,
      "vol_anualizada_30d": 0.36837745873843997,
      "alto_vol_persistente": 0,
      "mma9": 17.427777608235676,
      "mma10": 17.40099983215332,
      "mma26": 17.343846174386833,
      "mma50": 18.395200080871582,
      "mma150": 22.162219619750978,
      "mma200": 21.57784107208252,
      "pct_to_mma10": 8.61444630099428,
      "pct_to_mma50": 2.7441916121565404,
      "sup_min_by_mslf": 18.6,
      "sup_med_by_mslf": 18.7,
      "sup_max_by_mslf": 18.8,
      "res_min_by_mslf": 18.9,
      "res_med_by_mslf": 19.0,
      "res_max_by_mslf": 19.4,
      "std_raking_value_by_mslf": 1,
      "momentum_break_by_mslf": 0,
      "pl": 25.54,
      "pvp": 4.51,
      "ev_ebit": 12.08,
      "roic": 15.6,
      "cres_rec_5a": 15.4,
      "div_liq_vm": 0.09,
      "avaliacao_fundamentalista": 22,
      "distortion_ranking": 52
    },
    "RAIL3": {
      "ticker": "RAIL3",
      "setor": null,
      "subsetor": "Transporte Ferroviário",
      "fundamental_signal": 0,
      "vol_signal": 0,
      "posicao_setorial": "pior",
      "preco": 14.0600004196167,
      "vol_anualizada_30d": 0.3162918814617463,
      "alto_vol_persistente": 0,
      "mma9": 13.526666747199165,
      "mma10": 13.535000038146972,
      "mma26": 13.287307629218468,
      "mma50": 14.134800033569336,
      "mma150": 15.13846669514974,
      "mma200": 15.271300010681152,
      "pct_to_mma10": 3.8788354635394833,
      "pct_to_mma50": -0.5291876345968249,
      "sup_min_by_mslf": "Abismo",
      "sup_med_by_mslf": "Abismo",
      "sup_max_by_mslf": 12.2,
      "res_min_by_mslf": 14.2,
      "res_med_by_mslf": 14.6,
      "res_max_by_mslf": 14.8,
      "std_raking_value_by_mslf": 1,
      "momentum_break_by_mslf": -1,
      "pl": 25.11,
      "pvp": 1.88,
      "ev_ebit": 7.55,
      "roic": 12.1,
      "cres_rec_5a": 16.0,
      "div_liq_vm": 0.67,
      "avaliacao_fundamentalista": 25,
      "distortion_ranking": 38
    },
    "RDOR3": {
      "ticker": "RDOR3",
      "setor": null,
      "subsetor": "ServMédHospit Análises e Diagnósticos00",
      "fundamental_signal": 0,
      "vol_signal": 0,
      "posicao_setorial": "melhor",
      "preco": 36.04999923706055,
      "vol_anualizada_30d": 0.2822956639590739,
      "alto_vol_persistente": 0,
      "mma9": 35.124444749620224,
      "mma10": 35.08000030517578,
      "mma26": 34.21615395179162,
      "mma50": 34.869800109863284,
      "mma150": 39.07413330078125,
      "mma200": 40.071349964141845,
      "pct_to_mma10": 2.7651052549781516,
      "pct_to_mma50": 3.3845881636225124,
      "sup_min_by_mslf": 34.8,
      "sup_med_by_mslf": 35.0,
      "sup_max_by_mslf": 35.1,
      "res_min_by_mslf": 37.7,
      "res_med_by_mslf": 38.6,
      "res_max_by_mslf": 38.7,
      "std_raking_value_by_mslf": 3,
      "momentum_break_by_mslf": 0,
      "pl": 17.85,
      "pvp": 4.17,
      "ev_ebit": 8.33,
      "roic": 15.2,
      "cres_rec_5a": 29.3,
      "div_liq_vm": 0.09,
      "avaliacao_fundamentalista": 28,
      "distortion_ranking": 45
    },
    "RECV3": {
      "ticker": "RECV3",
      "setor": null,
      "subsetor": "Exploração. Refino e Distribuição",
      "fundamental_signal": 0,
      "vol_signal": 0,
      "posicao_setorial": "melhor",
      "preco": 10.130000114440918,
      "vol_anualizada_30d": 0.3698727596009049,
      "alto_vol_persistente": 0,
      "mma9": 9.83000013563368,
      "mma10": 9.853000164031982,
      "mma26": 10.151153857891376,
      "mma50": 11.07140001296997,
      "mma150": 11.651133352915446,
      "mma200": 11.76180000782013,
      "pct_to_mma10": 2.811325949431258,
      "pct_to_mma50": -8.502988758659406,
      "sup_min_by_mslf": "Abismo",
      "sup_med_by_mslf": "Abismo",
      "sup_max_by_mslf": 9.4,
      "res_min_by_mslf": 11.5,
      "res_med_by_mslf": 12.3,
      "res_max_by_mslf": 12.4,
      "std_raking_value_by_mslf": 1,
      "momentum_break_by_mslf": -1,
      "pl": 5.57,
      "pvp": 0.71,
      "ev_ebit": 7.15,
      "roic": 9.4,
      "cres_rec_5a": 16.2,
      "div_liq_vm": 0.51,
      "avaliacao_fundamentalista": 31,
      "distortion_ranking": 18
    },
    "RENT3": {
      "ticker": "RENT3",
      "setor": null,
      "subsetor": "Aluguel de carros",
      "fundamental_signal": 0,
      "vol_signal": 0,
      "posicao_setorial": "",
      "preco": 40.779998779296875,
      "vol_anualizada_30d": 0.31586951999141166,
      "alto_vol_persistente": 0,
      "mma9": 40.41666709052192,
      "mma10": 40.60000038146973,
      "mma26": 40.78423059903658,
      "mma50": 42.420000076293945,
      "mma150": 45.51320004781087,
      "mma200": 44.1354500579834,
      "pct_to_mma10": 0.4433458032904395,
      "pct_to_mma50": -3.866103946363666,
      "sup_min_by_mslf": 40.2,
      "sup_med_by_mslf": 40.3,
      "sup_max_by_mslf": 40.4,
      "res_min_by_mslf": 40.9,
      "res_med_by_mslf": 41.1,
      "res_max_by_mslf": 41.2,
      "std_raking_value_by_mslf": 2,
      "momentum_break_by_mslf": 0,
      "pl": 20.39,
      "pvp": 1.74,
      "ev_ebit": 9.61,
      "roic": 12.4,
      "cres_rec_5a": 40.1,
      "div_liq_vm": 0.7,
      "avaliacao_fundamentalista": 26,
      "distortion_ranking": 28
    },
    "SANB11": {
      "ticker": "SANB11",
      "setor": null,
      "subsetor": "Bancos",
      "fundamental_signal": 0,
      "vol_signal": 0,
      "posicao_setorial": "melhor",
      "preco": 27.389999389648438,
      "vol_anualizada_30d": 0.2162349690581285,
      "alto_vol_persistente": 0,
      "mma9": 26.57111104329427,
      "mma10": 26.595999908447265,
      "mma26": 26.74730763068566,
      "mma50": 27.169999923706055,
      "mma150": 30.981933275858562,
      "mma200": 30.850849990844726,
      "pct_to_mma10": 2.9854093996630944,
      "pct_to_mma50": 0.8097146358489002,
      "sup_min_by_mslf": 26.8,
      "sup_med_by_mslf": 27.0,
      "sup_max_by_mslf": 27.1,
      "res_min_by_mslf": 27.5,
      "res_med_by_mslf": 27.6,
      "res_max_by_mslf": 27.7,
      "std_raking_value_by_mslf": 1,
      "momentum_break_by_mslf": 0,
      "pl": 6.63,
      "pvp": 1.06,
      "ev_ebit": 0.0,
      "roic": 0.0,
      "cres_rec_5a": 3.3,
      "div_liq_vm": 0.0,
      "avaliacao_fundamentalista": 30,
      "distortion_ranking": 35
    },
    "SBSP3": {
      "ticker": "SBSP3",
      "setor": null,
      "subsetor": "Água e Saneamento",
      "fundamental_signal": 0,
      "vol_signal": 0,
      "posicao_setorial": "melhor",
      "preco": 30.950000762939453,
      "vol_anualizada_30d": 0.24490950906161427,
      "alto_vol_persistente": 0,
      "mma9": 29.90555551317003,
      "mma10": 29.879999923706055,
      "mma26": 28.616923038776104,
      "mma50": 29.105400047302247,
      "mma150": 29.16744970957438,
      "mma200": 28.303717727661134,
      "pct_to_mma10": 3.580993447006288,
      "pct_to_mma50": 6.337658003804626,
      "sup_min_by_mslf": 23.4,
      "sup_med_by_mslf": 24.0,
      "sup_max_by_mslf": 25.9,
      "res_min_by_mslf": 35.3,
      "res_med_by_mslf": "Foguete",
      "res_max_by_mslf": "Foguete",
      "std_raking_value_by_mslf": 1,
      "momentum_break_by_mslf": 1,
      "pl": 12.48,
      "pvp": 2.5,
      "ev_ebit": 10.0,
      "roic": 13.3,
      "cres_rec_5a": 21.0,
      "div_liq_vm": 0.3,
      "avaliacao_fundamentalista": 28,
      "distortion_ranking": 55
    },
    "SLCE3": {
      "ticker": "SLCE3",
      "setor": null,
      "subsetor": "Agricultura",
      "fundamental_signal": 0,
      "vol_signal": 0,
      "posicao_setorial": "pior",
      "preco": 14.029999732971191,
      "vol_anualizada_30d": 0.2684652575167745,
      "alto_vol_persistente": 0,
      "mma9": 13.107777701483833,
      "mma10": 13.097999954223633,
      "mma26": 13.630384665269117,
      "mma50": 15.073000049591064,
      "mma150": 15.911636950174968,
      "mma200": 15.534172048568726,
      "pct_to_mma10": 7.115588502098154,
      "pct_to_mma50": -6.919659743835599,
      "sup_min_by_mslf": "Abismo",
      "sup_med_by_mslf": "Abismo",
      "sup_max_by_mslf": 12.6,
      "res_min_by_mslf": 15.1,
      "res_med_by_mslf": 15.4,
      "res_max_by_mslf": 15.5,
      "std_raking_value_by_mslf": 1,
      "momentum_break_by_mslf": -1,
      "pl": 21.58,
      "pvp": 1.32,
      "ev_ebit": 7.99,
      "roic": 9.8,
      "cres_rec_5a": 2.4,
      "div_liq_vm": 0.91,
      "avaliacao_fundamentalista": 18,
      "distortion_ranking": 40
    },
    "SMFT3": {
      "ticker": "SMFT3",
      "setor": null,
      "subsetor": "Atividades Esportivas",
      "fundamental_signal": 0,
      "vol_signal": 0,
      "posicao_setorial": "pior",
      "preco": 20.8799991607666,
      "vol_anualizada_30d": 0.26273004203651756,
      "alto_vol_persistente": 0,
      "mma9": 19.962222417195637,
      "mma10": 19.913000106811523,
      "mma26": 19.251538496751053,
      "mma50": 19.025799980163573,
      "mma150": 20.379054590861003,
      "mma200": 21.58254093170166,
      "pct_to_mma10": 4.85611936307027,
      "pct_to_mma50": 9.745709418454043,
      "sup_min_by_mslf": 19.4,
      "sup_med_by_mslf": 19.6,
      "sup_max_by_mslf": 19.9,
      "res_min_by_mslf": 22.0,
      "res_med_by_mslf": 22.1,
      "res_max_by_mslf": 22.5,
      "std_raking_value_by_mslf": 2,
      "momentum_break_by_mslf": 0,
      "pl": 18.64,
      "pvp": 2.17,
      "ev_ebit": 8.43,
      "roic": 10.5,
      "cres_rec_5a": 51.5,
      "div_liq_vm": 0.32,
      "avaliacao_fundamentalista": 26,
      "distortion_ranking": 62
    },
    "SUZB3": {
      "ticker": "SUZB3",
      "setor": null,
      "subsetor": "Papel e Celulose",
      "fundamental_signal": 0,
      "vol_signal": 0,
      "posicao_setorial": "melhor",
      "preco": 41.4900016784668,
      "vol_anualizada_30d": 0.2549512616043405,
      "alto_vol_persistente": 0,
      "mma9": 40.76777776082357,
      "mma10": 40.65900001525879,
      "mma26": 41.518077263465294,
      "mma50": 41.83380027770996,
      "mma150": 48.24200002034505,
      "mma200": 48.335200023651126,
      "pct_to_mma10": 2.0438320246345025,
      "pct_to_mma50": -0.8218201477295595,
      "sup_min_by_mslf": "Abismo",
      "sup_med_by_mslf": "Abismo",
      "sup_max_by_mslf": 39.2,
      "res_min_by_mslf": 48.9,
      "res_med_by_mslf": 49.5,
      "res_max_by_mslf": 50.1,
      "std_raking_value_by_mslf": 1,
      "momentum_break_by_mslf": -1,
      "pl": 4.61,
      "pvp": 1.09,
      "ev_ebit": 12.67,
      "roic": 6.8,
      "cres_rec_5a": 3.1,
      "div_liq_vm": 1.3,
      "avaliacao_fundamentalista": 20,
      "distortion_ranking": 39
    },
    "TAEE11": {
      "ticker": "TAEE11",
      "setor": null,
      "subsetor": "Energia Elétrica",
      "fundamental_signal": 0,
      "vol_signal": 1,
      "posicao_setorial": "",
      "preco": 41.72999954223633,
      "vol_anualizada_30d": 0.19343946997330022,
      "alto_vol_persistente": 0,
      "mma9": 40.45444446139865,
      "mma10": 40.420999908447264,
      "mma26": 39.800769365750824,
      "mma50": 39.729800109863284,
      "mma150": 41.58973350524902,
      "mma200": 40.90095014572144,
      "pct_to_mma10": 3.2384147763635767,
      "pct_to_mma50": 5.034506659590458,
      "sup_min_by_mslf": 36.4,
      "sup_med_by_mslf": 36.7,
      "sup_max_by_mslf": 37.0,
      "res_min_by_mslf": 46.1,
      "res_med_by_mslf": "Foguete",
      "res_max_by_mslf": "Foguete",
      "std_raking_value_by_mslf": 1,
      "momentum_break_by_mslf": 1,
      "pl": 9.17,
      "pvp": 1.81,
      "ev_ebit": 10.26,
      "roic": 10.7,
      "cres_rec_5a": 11.8,
      "div_liq_vm": 0.23,
      "avaliacao_fundamentalista": 25,
      "distortion_ranking": 53
    },
    "TIMS3": {
      "ticker": "TIMS3",
      "setor": null,
      "subsetor": "Telecomunicações",
      "fundamental_signal": -1,
      "vol_signal": 0,
      "posicao_setorial": "pior",
      "preco": 22.780000686645508,
      "vol_anualizada_30d": 0.26360080040112627,
      "alto_vol_persistente": 0,
      "mma9": 22.421111212836372,
      "mma10": 22.408000183105468,
      "mma26": 22.225000088031475,
      "mma50": 22.592400093078613,
      "mma150": 24.37400001525879,
      "mma200": 24.274700031280517,
      "pct_to_mma10": 1.6601236187980304,
      "pct_to_mma50": 0.8303703581469776,
      "sup_min_by_mslf": 22.4,
      "sup_med_by_mslf": 22.5,
      "sup_max_by_mslf": 22.7,
      "res_min_by_mslf": 22.8,
      "res_med_by_mslf": 22.9,
      "res_max_by_mslf": 23.0,
      "std_raking_value_by_mslf": 2,
      "momentum_break_by_mslf": 0,
      "pl": 2278.0,
      "pvp": 2.23,
      "ev_ebit": 257.0,
      "roic": 0.4,
      "cres_rec_5a": -69.6,
      "div_liq_vm": -0.06,
      "avaliacao_fundamentalista": 7,
      "distortion_ranking": 56
    },
    "TOTS3": {
      "ticker": "TOTS3",
      "setor": null,
      "subsetor": "Programas e Serviços",
      "fundamental_signal": 0,
      "vol_signal": -1,
      "posicao_setorial": "pior",
      "preco": 30.079999923706055,
      "vol_anualizada_30d": 0.4612863147120049,
      "alto_vol_persistente": 0,
      "mma9": 29.223333570692276,
      "mma10": 29.151000213623046,
      "mma26": 29.02000009096586,
      "mma50": 30.742199935913085,
      "mma150": 36.566200014750166,
      "mma200": 38.463049993515014,
      "pct_to_mma10": 3.186853635467582,
      "pct_to_mma50": -2.1540423703817217,
      "sup_min_by_mslf": 29.7,
      "sup_med_by_mslf": 29.8,
      "sup_max_by_mslf": 30.0,
      "res_min_by_mslf": 30.2,
      "res_med_by_mslf": 30.5,
      "res_max_by_mslf": 30.7,
      "std_raking_value_by_mslf": 2,
      "momentum_break_by_mslf": 0,
      "pl": 19.53,
      "pvp": 3.63,
      "ev_ebit": 10.53,
      "roic": 20.3,
      "cres_rec_5a": 15.1,
      "div_liq_vm": 0.19,
      "avaliacao_fundamentalista": 25,
      "distortion_ranking": 32
    },
    "UGPA3": {
      "ticker": "UGPA3",
      "setor": null,
      "subsetor": "Exploração. Refino e Distribuição",
      "fundamental_signal": 0,
      "vol_signal": 0,
      "posicao_setorial": "",
      "preco": 30.540000915527344,
      "vol_anualizada_30d": 0.30755623416019684,
      "alto_vol_persistente": 0,
      "mma9": 28.04111162821452,
      "mma10": 27.86900043487549,
      "mma26": 26.052307789142315,
      "mma50": 27.221400108337402,
      "mma150": 26.005200055440266,
      "mma200": 24.886650009155275,
      "pct_to_mma10": 9.584127306228552,
      "pct_to_mma50": 12.191146649262603,
      "sup_min_by_mslf": 22.0,
      "sup_med_by_mslf": 22.7,
      "sup_max_by_mslf": 23.2,
      "res_min_by_mslf": 31.0,
      "res_med_by_mslf": "Foguete",
      "res_max_by_mslf": "Foguete",
      "std_raking_value_by_mslf": 2,
      "momentum_break_by_mslf": 1,
      "pl": 11.35,
      "pvp": 2.07,
      "ev_ebit": 7.8,
      "roic": 14.1,
      "cres_rec_5a": 4.0,
      "div_liq_vm": 0.41,
      "avaliacao_fundamentalista": 26,
      "distortion_ranking": 64
    },
    "USIM5": {
      "ticker": "USIM5",
      "setor": null,
      "subsetor": "Siderurgia",
      "fundamental_signal": -1,
      "vol_signal": -1,
      "posicao_setorial": "pior",
      "preco": 8.460000038146973,
      "vol_anualizada_30d": 0.47506940684754034,
      "alto_vol_persistente": 0,
      "mma9": 8.520000245836046,
      "mma10": 8.501000213623048,
      "mma26": 9.3561540383559,
      "mma50": 9.506600074768066,
      "mma150": 7.5180000241597496,
      "mma200": 6.878750014305115,
      "pct_to_mma10": -0.48229825250881897,
      "pct_to_mma50": -11.00919391149025,
      "sup_min_by_mslf": 6.2,
      "sup_med_by_mslf": 6.3,
      "sup_max_by_mslf": 6.4,
      "res_min_by_mslf": 12.2,
      "res_med_by_mslf": "Foguete",
      "res_max_by_mslf": "Foguete",
      "std_raking_value_by_mslf": 1,
      "momentum_break_by_mslf": 1,
      "pl": -4.07,
      "pvp": 0.52,
      "ev_ebit": 15.79,
      "roic": 3.3,
      "cres_rec_5a": -7.8,
      "div_liq_vm": -0.05,
      "avaliacao_fundamentalista": 8,
      "distortion_ranking": 37
    },
    "VALE3": {
      "ticker": "VALE3",
      "setor": null,
      "subsetor": "Minerais Metálicos",
      "fundamental_signal": 0,
      "vol_signal": 0,
      "posicao_setorial": "",
      "preco": 74.52999877929688,
      "vol_anualizada_30d": 0.2972415458003613,
      "alto_vol_persistente": 0,
      "mma9": 76.36666531032986,
      "mma10": 76.54299850463867,
      "mma26": 78.24115371704102,
      "mma50": 80.15859985351562,
      "mma150": 80.32293334960937,
      "mma200": 75.74800003051757,
      "pct_to_mma10": -2.629894000324285,
      "pct_to_mma50": -7.021830576512857,
      "sup_min_by_mslf": 64.0,
      "sup_med_by_mslf": 65.3,
      "sup_max_by_mslf": 65.9,
      "res_min_by_mslf": 91.6,
      "res_med_by_mslf": "Foguete",
      "res_max_by_mslf": "Foguete",
      "std_raking_value_by_mslf": 1,
      "momentum_break_by_mslf": 1,
      "pl": 21.23,
      "pvp": 1.73,
      "ev_ebit": 6.03,
      "roic": 17.9,
      "cres_rec_5a": -5.3,
      "div_liq_vm": 0.21,
      "avaliacao_fundamentalista": 22,
      "distortion_ranking": 27
    },
    "VAMO3": {
      "ticker": "VAMO3",
      "setor": null,
      "subsetor": "Aluguel de carros",
      "fundamental_signal": 0,
      "vol_signal": -1,
      "posicao_setorial": "",
      "preco": 3.0899999141693115,
      "vol_anualizada_30d": 0.45829500335848394,
      "alto_vol_persistente": 0,
      "mma9": 2.8722221851348877,
      "mma10": 2.872999978065491,
      "mma26": 2.8534615406623254,
      "mma50": 3.1338000106811523,
      "mma150": 3.6361947933832806,
      "mma200": 3.573746094703674,
      "pct_to_mma10": 7.5530782374017145,
      "pct_to_mma50": -1.3976672526183496,
      "sup_min_by_mslf": "Abismo",
      "sup_med_by_mslf": "Abismo",
      "sup_max_by_mslf": 2.7,
      "res_min_by_mslf": 3.6,
      "res_med_by_mslf": 3.7,
      "res_max_by_mslf": 3.8,
      "std_raking_value_by_mslf": 1,
      "momentum_break_by_mslf": -1,
      "pl": 12.36,
      "pvp": 1.45,
      "ev_ebit": 5.77,
      "roic": 15.3,
      "cres_rec_5a": 10.2,
      "div_liq_vm": 3.14,
      "avaliacao_fundamentalista": 30,
      "distortion_ranking": 36
    },
    "VBBR3": {
      "ticker": "VBBR3",
      "setor": null,
      "subsetor": "Exploração. Refino e Distribuição",
      "fundamental_signal": 0,
      "vol_signal": 0,
      "posicao_setorial": "",
      "preco": 32.7599983215332,
      "vol_anualizada_30d": 0.2630881111158813,
      "alto_vol_persistente": 0,
      "mma9": 30.785555097791885,
      "mma10": 30.69899959564209,
      "mma26": 29.658461277301495,
      "mma50": 30.92099979400635,
      "mma150": 29.744733238220213,
      "mma200": 28.012331237792967,
      "pct_to_mma10": 6.71356967014549,
      "pct_to_mma50": 5.947409656149997,
      "sup_min_by_mslf": 24.2,
      "sup_med_by_mslf": 24.6,
      "sup_max_by_mslf": 25.3,
      "res_min_by_mslf": 33.3,
      "res_med_by_mslf": 34.2,
      "res_max_by_mslf": "Foguete",
      "std_raking_value_by_mslf": 1,
      "momentum_break_by_mslf": 0,
      "pl": 13.05,
      "pvp": 1.81,
      "ev_ebit": 10.26,
      "roic": 9.9,
      "cres_rec_5a": 5.9,
      "div_liq_vm": 0.46,
      "avaliacao_fundamentalista": 22,
      "distortion_ranking": 63
    },
    "VIVA3": {
      "ticker": "VIVA3",
      "setor": null,
      "subsetor": "Acessórios",
      "fundamental_signal": 1,
      "vol_signal": 0,
      "posicao_setorial": "pior",
      "preco": 23.40999984741211,
      "vol_anualizada_30d": 0.32634286936675566,
      "alto_vol_persistente": 0,
      "mma9": 22.697777854071724,
      "mma10": 22.72800006866455,
      "mma26": 21.913461465101975,
      "mma50": 22.63939998626709,
      "mma150": 27.118599993387857,
      "mma200": 27.93119999885559,
      "pct_to_mma10": 3.000702994927582,
      "pct_to_mma50": 3.4037998428070524,
      "sup_min_by_mslf": "Abismo",
      "sup_med_by_mslf": 16.3,
      "sup_max_by_mslf": 21.2,
      "res_min_by_mslf": 23.9,
      "res_med_by_mslf": 24.4,
      "res_max_by_mslf": 24.9,
      "std_raking_value_by_mslf": 1,
      "momentum_break_by_mslf": 0,
      "pl": 9.44,
      "pvp": 1.82,
      "ev_ebit": 7.14,
      "roic": 17.5,
      "cres_rec_5a": 18.2,
      "div_liq_vm": 0.04,
      "avaliacao_fundamentalista": 33,
      "distortion_ranking": 40
    },
    "VIVT3": {
      "ticker": "VIVT3",
      "setor": null,
      "subsetor": "Telecomunicações",
      "fundamental_signal": 0,
      "vol_signal": 0,
      "posicao_setorial": "melhor",
      "preco": 35.650001525878906,
      "vol_anualizada_30d": 0.23840874225147185,
      "alto_vol_persistente": 0,
      "mma9": 34.48444493611654,
      "mma10": 34.47600059509277,
      "mma26": 33.8765387901893,
      "mma50": 34.76860023498535,
      "mma150": 36.948866780598955,
      "mma200": 36.12335012435913,
      "pct_to_mma10": 3.4052700734470926,
      "pct_to_mma50": 2.53504968545343,
      "sup_min_by_mslf": 35.1,
      "sup_med_by_mslf": 35.4,
      "sup_max_by_mslf": 35.6,
      "res_min_by_mslf": 43.5,
      "res_med_by_mslf": "Foguete",
      "res_max_by_mslf": "Foguete",
      "std_raking_value_by_mslf": 1,
      "momentum_break_by_mslf": 1,
      "pl": 18.1,
      "pvp": 1.66,
      "ev_ebit": 12.05,
      "roic": 8.8,
      "cres_rec_5a": 7.8,
      "div_liq_vm": 0.09,
      "avaliacao_fundamentalista": 17,
      "distortion_ranking": 53
    },
    "WEGE3": {
      "ticker": "WEGE3",
      "setor": null,
      "subsetor": "Motores. Compressores e Outros",
      "fundamental_signal": 0,
      "vol_signal": 0,
      "posicao_setorial": "pior",
      "preco": 46.52000045776367,
      "vol_anualizada_30d": 0.25813140118321937,
      "alto_vol_persistente": 0,
      "mma9": 46.18333265516493,
      "mma10": 46.24399948120117,
      "mma26": 45.035769095787636,
      "mma50": 44.258200073242186,
      "mma150": 47.39726666768392,
      "mma200": 45.65419994354248,
      "pct_to_mma10": 0.5968363023503152,
      "pct_to_mma50": 5.11046626563771,
      "sup_min_by_mslf": 46.0,
      "sup_med_by_mslf": 46.2,
      "sup_max_by_mslf": 46.5,
      "res_min_by_mslf": 46.8,
      "res_med_by_mslf": 46.9,
      "res_max_by_mslf": 47.1,
      "std_raking_value_by_mslf": 2,
      "momentum_break_by_mslf": 0,
      "pl": 31.01,
      "pvp": 11.0,
      "ev_ebit": 20.82,
      "roic": 26.0,
      "cres_rec_5a": 12.6,
      "div_liq_vm": -0.02,
      "avaliacao_fundamentalista": 21,
      "distortion_ranking": 53
    },
    "YDUQ3": {
      "ticker": "YDUQ3",
      "setor": null,
      "subsetor": "Serviços Educacionais",
      "fundamental_signal": 0,
      "vol_signal": 0,
      "posicao_setorial": "pior",
      "preco": 8.989999771118164,
      "vol_anualizada_30d": 0.4177166325905513,
      "alto_vol_persistente": 0,
      "mma9": 8.751111030578613,
      "mma10": 8.761999893188477,
      "mma26": 8.688846019598154,
      "mma50": 9.21759991645813,
      "mma150": 11.310866651535035,
      "mma200": 11.700899980068208,
      "pct_to_mma10": 2.6021442673941646,
      "pct_to_mma50": -2.4691909759891386,
      "sup_min_by_mslf": "Abismo",
      "sup_med_by_mslf": "Abismo",
      "sup_max_by_mslf": 7.8,
      "res_min_by_mslf": 9.4,
      "res_med_by_mslf": 9.5,
      "res_max_by_mslf": 9.7,
      "std_raking_value_by_mslf": 1,
      "momentum_break_by_mslf": -1,
      "pl": 20.91,
      "pvp": 0.82,
      "ev_ebit": 7.5,
      "roic": 10.9,
      "cres_rec_5a": 5.7,
      "div_liq_vm": 1.74,
      "avaliacao_fundamentalista": 23,
      "distortion_ranking": 33
    }
  },
  "warnings": [],
  "failed_tickers": [
    {
      "ticker": "AXIA6",
      "reason": "sem dados tecnicos ou baixa liquidez"
    }
  ]
}