{
  "schema_version": 1,
  "run_id": "2026-07-06T18-20-11Z",
  "generated_at": "2026-07-06T18:20:11.267017+00:00",
  "robusta_version": "13",
  "input_universe": [
    "ABEV3",
    "ALOS3",
    "ASAI3",
    "AURE3",
    "AXIA3",
    "AXIA6",
    "AZZA3",
    "B3SA3",
    "BBAS3",
    "BBDC3",
    "BBDC4",
    "BBSE3",
    "BEEF3",
    "BPAC11",
    "BRAP4",
    "BRAV3",
    "BRKM5",
    "CEAB3",
    "CMIG4",
    "CMIN3",
    "COGN3",
    "CPFE3",
    "CPLE3",
    "CSAN3",
    "CSMG3",
    "CSNA3",
    "CURY3",
    "CXSE3",
    "CYRE3",
    "DIRR3",
    "EGIE3",
    "EMBJ3",
    "ENEV3",
    "ENGI11",
    "EQTL3",
    "FLRY3",
    "GGBR4",
    "GOAU4",
    "HAPV3",
    "HYPE3",
    "IGTI11",
    "ISAE4",
    "ITSA4",
    "ITUB4",
    "KLBN11",
    "LREN3",
    "MBRF3",
    "MGLU3",
    "MOTV3",
    "MRVE3",
    "MULT3",
    "NATU3",
    "PETR3",
    "PETR4",
    "POMO4",
    "PRIO3",
    "PSSA3",
    "RADL3",
    "RAIL3",
    "RDOR3",
    "RECV3",
    "RENT3",
    "SANB11",
    "SBSP3",
    "SLCE3",
    "SMFT3",
    "SUZB3",
    "TAEE11",
    "TIMS3",
    "TOTS3",
    "UGPA3",
    "USIM5",
    "VALE3",
    "VAMO3",
    "VBBR3",
    "VIVA3",
    "VIVT3",
    "WEGE3",
    "YDUQ3"
  ],
  "summary": {
    "tickers_ok": 79,
    "tickers_failed": 0,
    "vol_media": 0.3028775217358703,
    "vol_std": 0.11926097536472369
  },
  "portfolio_signals": {
    "longs": [
      {
        "ticker": "BEEF3",
        "subsetor": "Carnes e Derivados",
        "distortion_ranking": 14,
        "pct_to_mma10": -1.8456371699901146
      },
      {
        "ticker": "RECV3",
        "subsetor": "Exploração. Refino e Distribuição",
        "distortion_ranking": 14,
        "pct_to_mma10": -4.428901409908941
      },
      {
        "ticker": "AZZA3",
        "subsetor": "Tecidos. Vestuário e Calçados",
        "distortion_ranking": 20,
        "pct_to_mma10": -3.98649586329082
      },
      {
        "ticker": "VAMO3",
        "subsetor": "Aluguel de carros",
        "distortion_ranking": 20,
        "pct_to_mma10": -0.035450079303124715
      },
      {
        "ticker": "PETR4",
        "subsetor": "Exploração. Refino e Distribuição",
        "distortion_ranking": 21,
        "pct_to_mma10": -1.2833988332901374
      }
    ],
    "shorts": [
      {
        "ticker": "CXSE3",
        "subsetor": "Seguradoras",
        "distortion_ranking": 72,
        "pct_to_mma10": 3.147385954458233
      },
      {
        "ticker": "EMBJ3",
        "subsetor": "Material Aeronáutico e de Defesa",
        "distortion_ranking": 72,
        "pct_to_mma10": 4.731336250596228
      },
      {
        "ticker": "CSMG3",
        "subsetor": "Água e Saneamento",
        "distortion_ranking": 70,
        "pct_to_mma10": 2.8043556905140212
      },
      {
        "ticker": "KLBN11",
        "subsetor": "Papel e Celulose",
        "distortion_ranking": 66,
        "pct_to_mma10": 0.2481074370023723
      },
      {
        "ticker": "BBSE3",
        "subsetor": "Seguradoras",
        "distortion_ranking": 65,
        "pct_to_mma10": -0.2579979370321853
      }
    ]
  },
  "tickers": {
    "ABEV3": {
      "ticker": "ABEV3",
      "setor": null,
      "subsetor": "Cervejas e Refrigerantes",
      "fundamental_signal": 0,
      "vol_signal": 0,
      "posicao_setorial": "pior",
      "preco": 15.9399995803833,
      "vol_anualizada_30d": 0.18785995971417083,
      "alto_vol_persistente": 0,
      "mma9": 16.345555517408584,
      "mma10": 16.348000049591064,
      "mma26": 16.322307696709267,
      "mma50": 16.07180000305176,
      "mma150": 15.234133338928222,
      "mma200": 14.569850001335144,
      "pct_to_mma10": -2.495720993210846,
      "pct_to_mma50": -0.820072565882054,
      "sup_min_by_mslf": 14.2,
      "sup_med_by_mslf": 14.3,
      "sup_max_by_mslf": 14.5,
      "res_min_by_mslf": 17.0,
      "res_med_by_mslf": "Foguete",
      "res_max_by_mslf": "Foguete",
      "std_raking_value_by_mslf": 2,
      "momentum_break_by_mslf": 1,
      "pl": 16.1,
      "pvp": 2.79,
      "ev_ebit": 11.84,
      "roic": 20.0,
      "cres_rec_5a": 4.6,
      "div_liq_vm": -0.07,
      "avaliacao_fundamentalista": 22,
      "distortion_ranking": 48
    },
    "ALOS3": {
      "ticker": "ALOS3",
      "setor": null,
      "subsetor": "Exploração de Imóveis",
      "fundamental_signal": 0,
      "vol_signal": 0,
      "posicao_setorial": "pior",
      "preco": 27.81999969482422,
      "vol_anualizada_30d": 0.18539584584445623,
      "alto_vol_persistente": 0,
      "mma9": 27.89111116197374,
      "mma10": 27.79600009918213,
      "mma26": 27.337307709913986,
      "mma50": 28.398800010681153,
      "mma150": 29.55226665496826,
      "mma200": 28.519149980545045,
      "pct_to_mma10": 0.08634190371439303,
      "pct_to_mma50": -2.0381153979718873,
      "sup_min_by_mslf": 24.3,
      "sup_med_by_mslf": 24.5,
      "sup_max_by_mslf": 24.6,
      "res_min_by_mslf": 34.2,
      "res_med_by_mslf": "Foguete",
      "res_max_by_mslf": "Foguete",
      "std_raking_value_by_mslf": 1,
      "momentum_break_by_mslf": 1,
      "pl": 16.96,
      "pvp": 1.08,
      "ev_ebit": 8.31,
      "roic": 6.3,
      "cres_rec_5a": 31.3,
      "div_liq_vm": -0.15,
      "avaliacao_fundamentalista": 24,
      "distortion_ranking": 46
    },
    "ASAI3": {
      "ticker": "ASAI3",
      "setor": null,
      "subsetor": "Alimentos",
      "fundamental_signal": 0,
      "vol_signal": -1,
      "posicao_setorial": "melhor",
      "preco": 8.609999656677246,
      "vol_anualizada_30d": 0.43102429726383495,
      "alto_vol_persistente": 0,
      "mma9": 8.688888761732313,
      "mma10": 8.613999891281129,
      "mma26": 8.385384577971239,
      "mma50": 8.629999933242798,
      "mma150": 8.551466598510743,
      "mma200": 8.67424994468689,
      "pct_to_mma10": -0.04643875846726539,
      "pct_to_mma50": -0.23175291680491328,
      "sup_min_by_mslf": 7.6,
      "sup_med_by_mslf": 7.8,
      "sup_max_by_mslf": 8.6,
      "res_min_by_mslf": 8.7,
      "res_med_by_mslf": 8.9,
      "res_max_by_mslf": 9.4,
      "std_raking_value_by_mslf": 1,
      "momentum_break_by_mslf": 0,
      "pl": 16.56,
      "pvp": 1.98,
      "ev_ebit": 3.81,
      "roic": 19.7,
      "cres_rec_5a": 14.9,
      "div_liq_vm": 1.03,
      "avaliacao_fundamentalista": 31,
      "distortion_ranking": 46
    },
    "AURE3": {
      "ticker": "AURE3",
      "setor": null,
      "subsetor": "Energia Elétrica",
      "fundamental_signal": 0,
      "vol_signal": 0,
      "posicao_setorial": "",
      "preco": 12.34000015258789,
      "vol_anualizada_30d": 0.24649596536655544,
      "alto_vol_persistente": 0,
      "mma9": 11.657777892218697,
      "mma10": 11.628000068664551,
      "mma26": 11.67346165730403,
      "mma50": 12.380800037384033,
      "mma150": 12.175866654713948,
      "mma200": 11.86749999523163,
      "pct_to_mma10": 6.123151700368975,
      "pct_to_mma50": -0.32954158594716015,
      "sup_min_by_mslf": 11.8,
      "sup_med_by_mslf": 11.9,
      "sup_max_by_mslf": 12.0,
      "res_min_by_mslf": 14.7,
      "res_med_by_mslf": "Foguete",
      "res_max_by_mslf": "Foguete",
      "std_raking_value_by_mslf": 2,
      "momentum_break_by_mslf": 1,
      "pl": -10.03,
      "pvp": 1.09,
      "ev_ebit": 28.38,
      "roic": 2.7,
      "cres_rec_5a": 39.7,
      "div_liq_vm": 1.56,
      "avaliacao_fundamentalista": 15,
      "distortion_ranking": 63
    },
    "AXIA3": {
      "ticker": "AXIA3",
      "setor": null,
      "subsetor": "Energia Elétrica",
      "fundamental_signal": -1,
      "vol_signal": 0,
      "posicao_setorial": "",
      "preco": 53.25,
      "vol_anualizada_30d": 0.24476666523197116,
      "alto_vol_persistente": 0,
      "mma9": 54.42111163669162,
      "mma10": 54.401000595092775,
      "mma26": 52.767692419198845,
      "mma50": 54.97859992980957,
      "mma150": 57.3342667388916,
      "mma200": 56.65475002288818,
      "pct_to_mma10": -2.115771001455809,
      "pct_to_mma50": -3.144132320605561,
      "sup_min_by_mslf": 45.8,
      "sup_med_by_mslf": 50.0,
      "sup_max_by_mslf": 52.5,
      "res_min_by_mslf": 53.7,
      "res_med_by_mslf": 54.5,
      "res_max_by_mslf": 58.2,
      "std_raking_value_by_mslf": 1,
      "momentum_break_by_mslf": 0,
      "pl": 16.28,
      "pvp": 1.28,
      "ev_ebit": 26.34,
      "roic": 3.0,
      "cres_rec_5a": 4.6,
      "div_liq_vm": 0.3,
      "avaliacao_fundamentalista": 13,
      "distortion_ranking": 49
    },
    "AXIA6": {
      "ticker": "AXIA6",
      "setor": null,
      "subsetor": "Energia Elétrica",
      "fundamental_signal": -1,
      "vol_signal": 0,
      "posicao_setorial": "pior",
      "preco": 55.779998779296875,
      "vol_anualizada_30d": 0.22009490044560953,
      "alto_vol_persistente": 0,
      "mma9": 55.779998779296875,
      "mma10": 55.779998779296875,
      "mma26": 57.46653791574332,
      "mma50": 62.66279968261719,
      "mma150": 59.532662353515626,
      "mma200": 55.361797924041745,
      "pct_to_mma10": 0.0,
      "pct_to_mma50": -10.983870714652447,
      "sup_min_by_mslf": 37.7,
      "sup_med_by_mslf": 37.8,
      "sup_max_by_mslf": 38.0,
      "res_min_by_mslf": 55.8,
      "res_med_by_mslf": 57.9,
      "res_max_by_mslf": 74.5,
      "std_raking_value_by_mslf": 1,
      "momentum_break_by_mslf": 0,
      "pl": 17.06,
      "pvp": 1.34,
      "ev_ebit": 28.32,
      "roic": 3.0,
      "cres_rec_5a": 4.6,
      "div_liq_vm": 0.28,
      "avaliacao_fundamentalista": 12,
      "distortion_ranking": 42
    },
    "AZZA3": {
      "ticker": "AZZA3",
      "setor": null,
      "subsetor": "Tecidos. Vestuário e Calçados",
      "fundamental_signal": 1,
      "vol_signal": -1,
      "posicao_setorial": "",
      "preco": 17.6299991607666,
      "vol_anualizada_30d": 0.6195302437148142,
      "alto_vol_persistente": 0,
      "mma9": 18.168888303968643,
      "mma10": 18.36199951171875,
      "mma26": 17.913845942570614,
      "mma50": 19.19739986419678,
      "mma150": 23.28973332722982,
      "mma200": 24.621950016021728,
      "pct_to_mma10": -3.98649586329082,
      "pct_to_mma50": -8.16465101794012,
      "sup_min_by_mslf": "Abismo",
      "sup_med_by_mslf": "Abismo",
      "sup_max_by_mslf": 16.1,
      "res_min_by_mslf": 23.0,
      "res_med_by_mslf": 23.1,
      "res_max_by_mslf": 23.3,
      "std_raking_value_by_mslf": 1,
      "momentum_break_by_mslf": -1,
      "pl": 4.37,
      "pvp": 0.45,
      "ev_ebit": 6.19,
      "roic": 7.7,
      "cres_rec_5a": 39.8,
      "div_liq_vm": 0.6,
      "avaliacao_fundamentalista": 33,
      "distortion_ranking": 20
    },
    "B3SA3": {
      "ticker": "B3SA3",
      "setor": null,
      "subsetor": "Serviços Financeiros Diversos",
      "fundamental_signal": 0,
      "vol_signal": 0,
      "posicao_setorial": "pior",
      "preco": 14.600000381469727,
      "vol_anualizada_30d": 0.2912687616283653,
      "alto_vol_persistente": 0,
      "mma9": 14.685555458068848,
      "mma10": 14.688999938964844,
      "mma26": 15.056923059316782,
      "mma50": 16.179800052642822,
      "mma150": 16.32826674143473,
      "mma200": 15.525050058364869,
      "pct_to_mma10": -0.6058925581382352,
      "pct_to_mma50": -9.764024685305364,
      "sup_min_by_mslf": 13.3,
      "sup_med_by_mslf": 13.6,
      "sup_max_by_mslf": 14.6,
      "res_min_by_mslf": 20.3,
      "res_med_by_mslf": "Foguete",
      "res_max_by_mslf": "Foguete",
      "std_raking_value_by_mslf": 1,
      "momentum_break_by_mslf": 1,
      "pl": 14.9,
      "pvp": 4.03,
      "ev_ebit": 11.58,
      "roic": 21.6,
      "cres_rec_5a": 3.2,
      "div_liq_vm": -0.01,
      "avaliacao_fundamentalista": 23,
      "distortion_ranking": 29
    },
    "BBAS3": {
      "ticker": "BBAS3",
      "setor": null,
      "subsetor": "Bancos",
      "fundamental_signal": 0,
      "vol_signal": 0,
      "posicao_setorial": "",
      "preco": 19.81999969482422,
      "vol_anualizada_30d": 0.21459365169041206,
      "alto_vol_persistente": 0,
      "mma9": 19.979999754163956,
      "mma10": 19.967999839782713,
      "mma26": 19.67153835296631,
      "mma50": 20.502999992370604,
      "mma150": 22.57379998524984,
      "mma200": 22.34770002365112,
      "pct_to_mma10": -0.741186629336958,
      "pct_to_mma50": -3.3312212739625306,
      "sup_min_by_mslf": "Abismo",
      "sup_med_by_mslf": 18.1,
      "sup_max_by_mslf": 19.7,
      "res_min_by_mslf": 20.6,
      "res_med_by_mslf": 21.0,
      "res_max_by_mslf": 21.1,
      "std_raking_value_by_mslf": 1,
      "momentum_break_by_mslf": 0,
      "pl": 7.9,
      "pvp": 0.61,
      "ev_ebit": 0.0,
      "roic": 0.0,
      "cres_rec_5a": -8.6,
      "div_liq_vm": 0.0,
      "avaliacao_fundamentalista": 29,
      "distortion_ranking": 34
    },
    "BBDC3": {
      "ticker": "BBDC3",
      "setor": null,
      "subsetor": "Bancos",
      "fundamental_signal": 0,
      "vol_signal": 1,
      "posicao_setorial": "",
      "preco": 15.510000228881836,
      "vol_anualizada_30d": 0.1748020667518317,
      "alto_vol_persistente": 0,
      "mma9": 15.660000165303549,
      "mma10": 15.648000144958496,
      "mma26": 15.419615525465746,
      "mma50": 15.680200099945068,
      "mma150": 16.5417333539327,
      "mma200": 16.250500016212463,
      "pct_to_mma10": -0.8819012960012119,
      "pct_to_mma50": -1.0854445094985024,
      "sup_min_by_mslf": 15.3,
      "sup_med_by_mslf": 15.4,
      "sup_max_by_mslf": 15.5,
      "res_min_by_mslf": 15.6,
      "res_med_by_mslf": 15.9,
      "res_max_by_mslf": 16.1,
      "std_raking_value_by_mslf": 2,
      "momentum_break_by_mslf": 0,
      "pl": 6.92,
      "pvp": 0.95,
      "ev_ebit": 0.0,
      "roic": 0.0,
      "cres_rec_5a": 1.6,
      "div_liq_vm": 0.0,
      "avaliacao_fundamentalista": 28,
      "distortion_ranking": 43
    },
    "BBDC4": {
      "ticker": "BBDC4",
      "setor": null,
      "subsetor": "Bancos",
      "fundamental_signal": 0,
      "vol_signal": 0,
      "posicao_setorial": "",
      "preco": 17.850000381469727,
      "vol_anualizada_30d": 0.19841327891218152,
      "alto_vol_persistente": 0,
      "mma9": 17.983333587646484,
      "mma10": 17.969000244140624,
      "mma26": 17.70500007042518,
      "mma50": 18.038600044250487,
      "mma150": 19.14366668701172,
      "mma200": 18.856300001144408,
      "pct_to_mma10": -0.6622508823756112,
      "pct_to_mma50": -1.0455338125913662,
      "sup_min_by_mslf": 17.1,
      "sup_med_by_mslf": 17.5,
      "sup_max_by_mslf": 17.6,
      "res_min_by_mslf": 18.0,
      "res_med_by_mslf": 18.2,
      "res_max_by_mslf": 18.3,
      "std_raking_value_by_mslf": 1,
      "momentum_break_by_mslf": 0,
      "pl": 7.97,
      "pvp": 1.09,
      "ev_ebit": 0.0,
      "roic": 0.0,
      "cres_rec_5a": 1.6,
      "div_liq_vm": 0.0,
      "avaliacao_fundamentalista": 28,
      "distortion_ranking": 44
    },
    "BBSE3": {
      "ticker": "BBSE3",
      "setor": null,
      "subsetor": "Seguradoras",
      "fundamental_signal": 0,
      "vol_signal": 0,
      "posicao_setorial": "",
      "preco": 38.65999984741211,
      "vol_anualizada_30d": 0.19347776189134636,
      "alto_vol_persistente": 0,
      "mma9": 38.81444422403971,
      "mma10": 38.75999984741211,
      "mma26": 37.70192293020395,
      "mma50": 36.07959999084473,
      "mma150": 35.60786666870117,
      "mma200": 34.929699964523316,
      "pct_to_mma10": -0.2579979370321853,
      "pct_to_mma50": 7.151963595001508,
      "sup_min_by_mslf": 35.7,
      "sup_med_by_mslf": 36.4,
      "sup_max_by_mslf": 38.0,
      "res_min_by_mslf": 42.6,
      "res_med_by_mslf": "Foguete",
      "res_max_by_mslf": "Foguete",
      "std_raking_value_by_mslf": 1,
      "momentum_break_by_mslf": 1,
      "pl": 8.17,
      "pvp": 5.94,
      "ev_ebit": 0.0,
      "roic": 0.0,
      "cres_rec_5a": 0.0,
      "div_liq_vm": 0.0,
      "avaliacao_fundamentalista": 20,
      "distortion_ranking": 65
    },
    "BEEF3": {
      "ticker": "BEEF3",
      "setor": null,
      "subsetor": "Carnes e Derivados",
      "fundamental_signal": 1,
      "vol_signal": 0,
      "posicao_setorial": "melhor",
      "preco": 3.509999990463257,
      "vol_anualizada_30d": 0.4070076282748831,
      "alto_vol_persistente": 0,
      "mma9": 3.576666646533542,
      "mma10": 3.5759999752044678,
      "mma26": 3.6234615399287295,
      "mma50": 3.82560001373291,
      "mma150": 4.76800000667572,
      "mma200": 5.244450002908707,
      "pct_to_mma10": -1.8456371699901146,
      "pct_to_mma50": -8.249686902361228,
      "sup_min_by_mslf": "Abismo",
      "sup_med_by_mslf": "Abismo",
      "sup_max_by_mslf": 3.4,
      "res_min_by_mslf": 4.8,
      "res_med_by_mslf": 5.0,
      "res_max_by_mslf": 5.2,
      "std_raking_value_by_mslf": 3,
      "momentum_break_by_mslf": -1,
      "pl": 4.94,
      "pvp": 2.79,
      "ev_ebit": 4.4,
      "roic": 17.8,
      "cres_rec_5a": 17.7,
      "div_liq_vm": 3.9,
      "avaliacao_fundamentalista": 37,
      "distortion_ranking": 14
    },
    "BPAC11": {
      "ticker": "BPAC11",
      "setor": null,
      "subsetor": "Bancos",
      "fundamental_signal": 0,
      "vol_signal": 0,
      "posicao_setorial": "pior",
      "preco": 55.2400016784668,
      "vol_anualizada_30d": 0.2772194710686723,
      "alto_vol_persistente": 0,
      "mma9": 54.53777779473199,
      "mma10": 54.363999938964845,
      "mma26": 52.378461397611176,
      "mma50": 54.42919998168945,
      "mma150": 56.25113321940104,
      "mma200": 54.34959993362427,
      "pct_to_mma10": 1.6113636606678132,
      "pct_to_mma50": 1.4896447073447867,
      "sup_min_by_mslf": 54.6,
      "sup_med_by_mslf": 54.7,
      "sup_max_by_mslf": 55.0,
      "res_min_by_mslf": 55.7,
      "res_med_by_mslf": 65.5,
      "res_max_by_mslf": "Foguete",
      "std_raking_value_by_mslf": 1,
      "momentum_break_by_mslf": 0,
      "pl": 12.41,
      "pvp": 2.88,
      "ev_ebit": 0.0,
      "roic": 0.0,
      "cres_rec_5a": 8.5,
      "div_liq_vm": 0.0,
      "avaliacao_fundamentalista": 23,
      "distortion_ranking": 62
    },
    "BRAP4": {
      "ticker": "BRAP4",
      "setor": null,
      "subsetor": "Minerais Metálicos",
      "fundamental_signal": -1,
      "vol_signal": 0,
      "posicao_setorial": "pior",
      "preco": 22.25,
      "vol_anualizada_30d": 0.24826789284027995,
      "alto_vol_persistente": 0,
      "mma9": 22.25555568271213,
      "mma10": 22.292000198364256,
      "mma26": 22.44269246321458,
      "mma50": 22.743000144958497,
      "mma150": 22.6435999806722,
      "mma200": 21.416049966812135,
      "pct_to_mma10": -0.18840928579992694,
      "pct_to_mma50": -2.167700575193382,
      "sup_min_by_mslf": 19.1,
      "sup_med_by_mslf": 19.2,
      "sup_max_by_mslf": 19.4,
      "res_min_by_mslf": 25.6,
      "res_med_by_mslf": "Foguete",
      "res_max_by_mslf": "Foguete",
      "std_raking_value_by_mslf": 2,
      "momentum_break_by_mslf": 1,
      "pl": 11.18,
      "pvp": 1.12,
      "ev_ebit": -243.43,
      "roic": -0.5,
      "cres_rec_5a": 0.0,
      "div_liq_vm": -0.03,
      "avaliacao_fundamentalista": 12,
      "distortion_ranking": 57
    },
    "BRAV3": {
      "ticker": "BRAV3",
      "setor": null,
      "subsetor": "Exploração. Refino e Distribuição",
      "fundamental_signal": 0,
      "vol_signal": 0,
      "posicao_setorial": "",
      "preco": 17.729999542236328,
      "vol_anualizada_30d": 0.2715803586612608,
      "alto_vol_persistente": 0,
      "mma9": 18.646666208902996,
      "mma10": 18.678999519348146,
      "mma26": 19.714615161602314,
      "mma50": 19.317199897766113,
      "mma150": 18.210533243815103,
      "mma200": 17.668749947547912,
      "pct_to_mma10": -5.080571773283796,
      "pct_to_mma50": -8.216513593739496,
      "sup_min_by_mslf": 17.4,
      "sup_med_by_mslf": 17.5,
      "sup_max_by_mslf": 17.6,
      "res_min_by_mslf": 17.8,
      "res_med_by_mslf": 17.9,
      "res_max_by_mslf": 18.0,
      "std_raking_value_by_mslf": 1,
      "momentum_break_by_mslf": 0,
      "pl": 35.46,
      "pvp": 0.72,
      "ev_ebit": 7.22,
      "roic": 7.8,
      "cres_rec_5a": 93.8,
      "div_liq_vm": 1.29,
      "avaliacao_fundamentalista": 24,
      "distortion_ranking": 29
    },
    "BRKM5": {
      "ticker": "BRKM5",
      "setor": null,
      "subsetor": "Petroquímicos",
      "fundamental_signal": -1,
      "vol_signal": -1,
      "posicao_setorial": "pior",
      "preco": 6.150000095367432,
      "vol_anualizada_30d": 0.7119804159571057,
      "alto_vol_persistente": 0,
      "mma9": 6.504444440205892,
      "mma10": 6.61399998664856,
      "mma26": 8.073461495912992,
      "mma50": 9.29339994430542,
      "mma150": 9.222133309046427,
      "mma200": 8.724449982643128,
      "pct_to_mma10": -7.015420202869488,
      "pct_to_mma50": -33.82400270919281,
      "sup_min_by_mslf": "Abismo",
      "sup_med_by_mslf": "Abismo",
      "sup_max_by_mslf": 5.8,
      "res_min_by_mslf": 7.4,
      "res_med_by_mslf": 7.5,
      "res_max_by_mslf": 7.7,
      "std_raking_value_by_mslf": 1,
      "momentum_break_by_mslf": -1,
      "pl": -0.54,
      "pvp": -0.31,
      "ev_ebit": -13.45,
      "roic": -6.5,
      "cres_rec_5a": -10.6,
      "div_liq_vm": 8.77,
      "avaliacao_fundamentalista": 4,
      "distortion_ranking": 41
    },
    "CEAB3": {
      "ticker": "CEAB3",
      "setor": null,
      "subsetor": "Tecidos. Vestuário e Calçados",
      "fundamental_signal": 1,
      "vol_signal": -1,
      "posicao_setorial": "melhor",
      "preco": 10.6899995803833,
      "vol_anualizada_30d": 0.4908598789613217,
      "alto_vol_persistente": 0,
      "mma9": 10.827777862548828,
      "mma10": 10.726000118255616,
      "mma26": 10.773846186124361,
      "mma50": 11.03299997329712,
      "mma150": 12.092466672261557,
      "mma200": 13.246949982643127,
      "pct_to_mma10": -0.335638052166738,
      "pct_to_mma50": -3.108858821208861,
      "sup_min_by_mslf": 10.3,
      "sup_med_by_mslf": 10.5,
      "sup_max_by_mslf": 10.6,
      "res_min_by_mslf": 10.7,
      "res_med_by_mslf": 10.8,
      "res_max_by_mslf": 10.9,
      "std_raking_value_by_mslf": 1,
      "momentum_break_by_mslf": 0,
      "pl": 5.63,
      "pvp": 0.89,
      "ev_ebit": 3.8,
      "roic": 14.7,
      "cres_rec_5a": 9.9,
      "div_liq_vm": 0.04,
      "avaliacao_fundamentalista": 34,
      "distortion_ranking": 31
    },
    "CMIG4": {
      "ticker": "CMIG4",
      "setor": null,
      "subsetor": "Energia Elétrica",
      "fundamental_signal": 0,
      "vol_signal": 1,
      "posicao_setorial": "",
      "preco": 10.960000038146973,
      "vol_anualizada_30d": 0.17820930859250572,
      "alto_vol_persistente": 0,
      "mma9": 10.895555602179634,
      "mma10": 10.905000019073487,
      "mma26": 10.831923118004433,
      "mma50": 11.270800075531007,
      "mma150": 11.618733386993409,
      "mma200": 11.50265003681183,
      "pct_to_mma10": 0.5043559741154273,
      "pct_to_mma50": -2.7575685426164496,
      "sup_min_by_mslf": 9.8,
      "sup_med_by_mslf": 10.6,
      "sup_max_by_mslf": 10.7,
      "res_min_by_mslf": 11.2,
      "res_med_by_mslf": 13.9,
      "res_max_by_mslf": "Foguete",
      "std_raking_value_by_mslf": 1,
      "momentum_break_by_mslf": 0,
      "pl": 6.49,
      "pvp": 1.09,
      "ev_ebit": 8.02,
      "roic": 9.6,
      "cres_rec_5a": 6.2,
      "div_liq_vm": 0.57,
      "avaliacao_fundamentalista": 26,
      "distortion_ranking": 40
    },
    "CMIN3": {
      "ticker": "CMIN3",
      "setor": null,
      "subsetor": "Minerais Metálicos",
      "fundamental_signal": 0,
      "vol_signal": 0,
      "posicao_setorial": "melhor",
      "preco": 4.300000190734863,
      "vol_anualizada_30d": 0.32908044478017245,
      "alto_vol_persistente": 0,
      "mma9": 4.233333269755046,
      "mma10": 4.237999963760376,
      "mma26": 4.334230771431556,
      "mma50": 4.478999996185303,
      "mma150": 5.0843999989827475,
      "mma200": 5.222000005245209,
      "pct_to_mma10": 1.4629595918985026,
      "pct_to_mma50": -3.9964234338667395,
      "sup_min_by_mslf": "Abismo",
      "sup_med_by_mslf": "Abismo",
      "sup_max_by_mslf": 4.1,
      "res_min_by_mslf": 5.1,
      "res_med_by_mslf": 7.4,
      "res_max_by_mslf": "Foguete",
      "std_raking_value_by_mslf": 1,
      "momentum_break_by_mslf": -1,
      "pl": 10.49,
      "pvp": 3.31,
      "ev_ebit": 4.86,
      "roic": 21.7,
      "cres_rec_5a": 2.6,
      "div_liq_vm": 0.01,
      "avaliacao_fundamentalista": 29,
      "distortion_ranking": 36
    },
    "COGN3": {
      "ticker": "COGN3",
      "setor": null,
      "subsetor": "Serviços Educacionais",
      "fundamental_signal": 0,
      "vol_signal": 0,
      "posicao_setorial": "melhor",
      "preco": 2.2799999713897705,
      "vol_anualizada_30d": 0.30592982210110453,
      "alto_vol_persistente": 0,
      "mma9": 2.2866666316986084,
      "mma10": 2.28699996471405,
      "mma26": 2.345384588608375,
      "mma50": 2.4949999856948852,
      "mma150": 3.134199940363566,
      "mma200": 3.113786209821701,
      "pct_to_mma10": -0.3060775440438157,
      "pct_to_mma50": -8.617235091696196,
      "sup_min_by_mslf": 1.2,
      "sup_med_by_mslf": 1.3,
      "sup_max_by_mslf": 1.4,
      "res_min_by_mslf": 2.6,
      "res_med_by_mslf": 4.7,
      "res_max_by_mslf": "Foguete",
      "std_raking_value_by_mslf": 1,
      "momentum_break_by_mslf": 0,
      "pl": 6.91,
      "pvp": 0.35,
      "ev_ebit": 4.76,
      "roic": 10.1,
      "cres_rec_5a": 11.6,
      "div_liq_vm": 1.13,
      "avaliacao_fundamentalista": 31,
      "distortion_ranking": 22
    },
    "CPFE3": {
      "ticker": "CPFE3",
      "setor": null,
      "subsetor": "Energia Elétrica",
      "fundamental_signal": 0,
      "vol_signal": 0,
      "posicao_setorial": "melhor",
      "preco": 45.22999954223633,
      "vol_anualizada_30d": 0.19663484165306155,
      "alto_vol_persistente": 0,
      "mma9": 45.02222145928277,
      "mma10": 44.93199920654297,
      "mma26": 44.11307613666241,
      "mma50": 45.434599609375,
      "mma150": 48.95633321126302,
      "mma200": 46.99234991073608,
      "pct_to_mma10": 0.6632251868507216,
      "pct_to_mma50": -0.4503177510041344,
      "sup_min_by_mslf": 40.8,
      "sup_med_by_mslf": 41.8,
      "sup_max_by_mslf": 41.9,
      "res_min_by_mslf": 57.2,
      "res_med_by_mslf": "Foguete",
      "res_max_by_mslf": "Foguete",
      "std_raking_value_by_mslf": 2,
      "momentum_break_by_mslf": 1,
      "pl": 9.05,
      "pvp": 2.14,
      "ev_ebit": 6.62,
      "roic": 15.3,
      "cres_rec_5a": 3.1,
      "div_liq_vm": 0.5,
      "avaliacao_fundamentalista": 27,
      "distortion_ranking": 48
    },
    "CPLE3": {
      "ticker": "CPLE3",
      "setor": null,
      "subsetor": "Energia Elétrica",
      "fundamental_signal": 0,
      "vol_signal": 0,
      "posicao_setorial": "",
      "preco": 14.949999809265137,
      "vol_anualizada_30d": 0.20441135017570441,
      "alto_vol_persistente": 0,
      "mma9": 15.073333422342936,
      "mma10": 15.065000057220459,
      "mma26": 14.73999995451707,
      "mma50": 14.993199939727782,
      "mma150": 14.428599948883056,
      "mma200": 13.955749955177307,
      "pct_to_mma10": -0.7633604216297639,
      "pct_to_mma50": -0.288131490517761,
      "sup_min_by_mslf": 11.6,
      "sup_med_by_mslf": 11.7,
      "sup_max_by_mslf": 11.8,
      "res_min_by_mslf": 16.9,
      "res_med_by_mslf": "Foguete",
      "res_max_by_mslf": "Foguete",
      "std_raking_value_by_mslf": 2,
      "momentum_break_by_mslf": 1,
      "pl": 16.43,
      "pvp": 1.87,
      "ev_ebit": 12.52,
      "roic": 8.9,
      "cres_rec_5a": 2.7,
      "div_liq_vm": 0.41,
      "avaliacao_fundamentalista": 16,
      "distortion_ranking": 59
    },
    "CSAN3": {
      "ticker": "CSAN3",
      "setor": null,
      "subsetor": "Exploração. Refino e Distribuição",
      "fundamental_signal": 0,
      "vol_signal": -1,
      "posicao_setorial": "pior",
      "preco": 3.869999885559082,
      "vol_anualizada_30d": 0.46274405177673533,
      "alto_vol_persistente": 0,
      "mma9": 3.73888889948527,
      "mma10": 3.740000009536743,
      "mma26": 3.5996153904841495,
      "mma50": 4.131199998855591,
      "mma150": 5.148266674677531,
      "mma200": 5.419349994659424,
      "pct_to_mma10": 3.4759325051028904,
      "pct_to_mma50": -6.322620869695618,
      "sup_min_by_mslf": "Abismo",
      "sup_med_by_mslf": "Abismo",
      "sup_max_by_mslf": 3.2,
      "res_min_by_mslf": 5.0,
      "res_med_by_mslf": 5.1,
      "res_max_by_mslf": 5.2,
      "std_raking_value_by_mslf": 1,
      "momentum_break_by_mslf": -1,
      "pl": -1.61,
      "pvp": 4.4,
      "ev_ebit": 6.99,
      "roic": 8.5,
      "cres_rec_5a": 7.8,
      "div_liq_vm": 3.09,
      "avaliacao_fundamentalista": 18,
      "distortion_ranking": 44
    },
    "CSMG3": {
      "ticker": "CSMG3",
      "setor": null,
      "subsetor": "Água e Saneamento",
      "fundamental_signal": 0,
      "vol_signal": -1,
      "posicao_setorial": "pior",
      "preco": 62.209999084472656,
      "vol_anualizada_30d": 0.5090412293721991,
      "alto_vol_persistente": 0,
      "mma9": 60.69777721828885,
      "mma10": 60.51299934387207,
      "mma26": 58.11692281869742,
      "mma50": 55.87099975585937,
      "mma150": 52.382466608683266,
      "mma200": 48.23364990234375,
      "pct_to_mma10": 2.8043556905140212,
      "pct_to_mma50": 11.345777516623894,
      "sup_min_by_mslf": 25.8,
      "sup_med_by_mslf": 27.7,
      "sup_max_by_mslf": 27.9,
      "res_min_by_mslf": 62.7,
      "res_med_by_mslf": "Foguete",
      "res_max_by_mslf": "Foguete",
      "std_raking_value_by_mslf": 1,
      "momentum_break_by_mslf": 1,
      "pl": 17.47,
      "pvp": 2.7,
      "ev_ebit": 12.39,
      "roic": 11.6,
      "cres_rec_5a": 9.5,
      "div_liq_vm": 0.29,
      "avaliacao_fundamentalista": 20,
      "distortion_ranking": 70
    },
    "CSNA3": {
      "ticker": "CSNA3",
      "setor": null,
      "subsetor": "Siderurgia",
      "fundamental_signal": -1,
      "vol_signal": -1,
      "posicao_setorial": "",
      "preco": 4.829999923706055,
      "vol_anualizada_30d": 0.5953976556014767,
      "alto_vol_persistente": 0,
      "mma9": 4.747777779897054,
      "mma10": 4.8,
      "mma26": 5.563846202997061,
      "mma50": 5.98620002746582,
      "mma150": 7.563733342488606,
      "mma200": 7.77904999256134,
      "pct_to_mma10": 0.6249984105428097,
      "pct_to_mma50": -19.314424817996397,
      "sup_min_by_mslf": "Abismo",
      "sup_med_by_mslf": "Abismo",
      "sup_max_by_mslf": 4.5,
      "res_min_by_mslf": 7.8,
      "res_med_by_mslf": 7.9,
      "res_max_by_mslf": 8.1,
      "std_raking_value_by_mslf": 2,
      "momentum_break_by_mslf": -1,
      "pl": -3.2,
      "pvp": 0.5,
      "ev_ebit": 7.24,
      "roic": 8.0,
      "cres_rec_5a": -1.2,
      "div_liq_vm": 5.78,
      "avaliacao_fundamentalista": 14,
      "distortion_ranking": 36
    },
    "CURY3": {
      "ticker": "CURY3",
      "setor": null,
      "subsetor": "Incorporações",
      "fundamental_signal": 1,
      "vol_signal": 0,
      "posicao_setorial": "melhor",
      "preco": 34.130001068115234,
      "vol_anualizada_30d": 0.3731925105422642,
      "alto_vol_persistente": 0,
      "mma9": 34.863333808051216,
      "mma10": 34.810000610351565,
      "mma26": 32.75500033451961,
      "mma50": 31.756000289916994,
      "mma150": 34.32479998270671,
      "mma200": 34.23824999809265,
      "pct_to_mma10": -1.9534602996649109,
      "pct_to_mma50": 7.475754995984244,
      "sup_min_by_mslf": 33.7,
      "sup_med_by_mslf": 33.8,
      "sup_max_by_mslf": 34.1,
      "res_min_by_mslf": 34.4,
      "res_med_by_mslf": 34.5,
      "res_max_by_mslf": 34.6,
      "std_raking_value_by_mslf": 3,
      "momentum_break_by_mslf": 0,
      "pl": 9.86,
      "pvp": 6.81,
      "ev_ebit": 6.0,
      "roic": 37.6,
      "cres_rec_5a": 33.2,
      "div_liq_vm": -0.04,
      "avaliacao_fundamentalista": 35,
      "distortion_ranking": 47
    },
    "CXSE3": {
      "ticker": "CXSE3",
      "setor": null,
      "subsetor": "Seguradoras",
      "fundamental_signal": 0,
      "vol_signal": 1,
      "posicao_setorial": "pior",
      "preco": 20.450000762939453,
      "vol_anualizada_30d": 0.1654440476227454,
      "alto_vol_persistente": 0,
      "mma9": 19.869999991522896,
      "mma10": 19.826000022888184,
      "mma26": 18.93423080444336,
      "mma50": 18.321800079345703,
      "mma150": 17.71286677678426,
      "mma200": 17.026800084114075,
      "pct_to_mma10": 3.147385954458233,
      "pct_to_mma50": 11.615674630097542,
      "sup_min_by_mslf": 14.9,
      "sup_med_by_mslf": 16.2,
      "sup_max_by_mslf": 16.5,
      "res_min_by_mslf": 20.6,
      "res_med_by_mslf": "Foguete",
      "res_max_by_mslf": "Foguete",
      "std_raking_value_by_mslf": 1,
      "momentum_break_by_mslf": 1,
      "pl": 14.01,
      "pvp": 4.46,
      "ev_ebit": -324.62,
      "roic": -1.1,
      "cres_rec_5a": 0.0,
      "div_liq_vm": -0.02,
      "avaliacao_fundamentalista": 18,
      "distortion_ranking": 72
    },
    "CYRE3": {
      "ticker": "CYRE3",
      "setor": null,
      "subsetor": "Incorporações",
      "fundamental_signal": 0,
      "vol_signal": -1,
      "posicao_setorial": "",
      "preco": 22.75,
      "vol_anualizada_30d": 0.42583933398225815,
      "alto_vol_persistente": 0,
      "mma9": 23.021111170450848,
      "mma10": 22.879000091552733,
      "mma26": 21.89230779501108,
      "mma50": 22.266800079345703,
      "mma150": 26.94826665242513,
      "mma200": 27.965799980163574,
      "pct_to_mma10": -0.5638362298899666,
      "pct_to_mma50": 2.1700465218731835,
      "sup_min_by_mslf": 22.0,
      "sup_med_by_mslf": 22.4,
      "sup_max_by_mslf": 22.7,
      "res_min_by_mslf": 23.0,
      "res_med_by_mslf": 23.4,
      "res_max_by_mslf": 23.6,
      "std_raking_value_by_mslf": 1,
      "momentum_break_by_mslf": 0,
      "pl": 5.25,
      "pvp": 0.98,
      "ev_ebit": 9.74,
      "roic": 6.9,
      "cres_rec_5a": 18.5,
      "div_liq_vm": 0.47,
      "avaliacao_fundamentalista": 27,
      "distortion_ranking": 53
    },
    "DIRR3": {
      "ticker": "DIRR3",
      "setor": null,
      "subsetor": "Incorporações",
      "fundamental_signal": 0,
      "vol_signal": 0,
      "posicao_setorial": "",
      "preco": 14.020000457763672,
      "vol_anualizada_30d": 0.3798834981928473,
      "alto_vol_persistente": 0,
      "mma9": 14.011111047532824,
      "mma10": 13.989999961853027,
      "mma26": 13.487692319429838,
      "mma50": 13.308600025177002,
      "mma150": 14.392400023142496,
      "mma200": 14.866600003242493,
      "pct_to_mma10": 0.21444243025338486,
      "pct_to_mma50": 5.345418986526409,
      "sup_min_by_mslf": 13.8,
      "sup_med_by_mslf": 13.9,
      "sup_max_by_mslf": 14.0,
      "res_min_by_mslf": 15.0,
      "res_med_by_mslf": 18.8,
      "res_max_by_mslf": "Foguete",
      "std_raking_value_by_mslf": 1,
      "momentum_break_by_mslf": 0,
      "pl": 8.71,
      "pvp": 3.43,
      "ev_ebit": 6.74,
      "roic": 10.1,
      "cres_rec_5a": 26.0,
      "div_liq_vm": 0.1,
      "avaliacao_fundamentalista": 31,
      "distortion_ranking": 55
    },
    "EGIE3": {
      "ticker": "EGIE3",
      "setor": null,
      "subsetor": "Energia Elétrica",
      "fundamental_signal": 0,
      "vol_signal": 0,
      "posicao_setorial": "",
      "preco": 32.189998626708984,
      "vol_anualizada_30d": 0.3140923788362826,
      "alto_vol_persistente": 0,
      "mma9": 33.317777421739365,
      "mma10": 33.405999755859376,
      "mma26": 33.73230772752028,
      "mma50": 33.63600021362305,
      "mma150": 32.914419123331704,
      "mma200": 32.02045705795288,
      "pct_to_mma10": -3.6400680657285425,
      "pct_to_mma50": -4.298970084821244,
      "sup_min_by_mslf": 31.7,
      "sup_med_by_mslf": 31.8,
      "sup_max_by_mslf": 32.0,
      "res_min_by_mslf": 32.5,
      "res_med_by_mslf": 32.7,
      "res_max_by_mslf": 33.1,
      "std_raking_value_by_mslf": 1,
      "momentum_break_by_mslf": 0,
      "pl": 14.31,
      "pvp": 2.7,
      "ev_ebit": 10.96,
      "roic": 11.1,
      "cres_rec_5a": 1.3,
      "div_liq_vm": 0.67,
      "avaliacao_fundamentalista": 18,
      "distortion_ranking": 39
    },
    "EMBJ3": {
      "ticker": "EMBJ3",
      "setor": null,
      "subsetor": "Material Aeronáutico e de Defesa",
      "fundamental_signal": 0,
      "vol_signal": 0,
      "posicao_setorial": "pior",
      "preco": 85.81999969482422,
      "vol_anualizada_30d": 0.35228122414986895,
      "alto_vol_persistente": 0,
      "mma9": 82.29222276475694,
      "mma10": 81.94300079345703,
      "mma26": 77.23923022930438,
      "mma50": 76.08959945678711,
      "mma150": 84.18099985758464,
      "mma200": 83.64229988098144,
      "pct_to_mma10": 4.731336250596228,
      "pct_to_mma50": 12.78808182393338,
      "sup_min_by_mslf": 84.6,
      "sup_med_by_mslf": 85.1,
      "sup_max_by_mslf": 85.3,
      "res_min_by_mslf": 86.4,
      "res_med_by_mslf": 87.2,
      "res_max_by_mslf": 89.1,
      "std_raking_value_by_mslf": 2,
      "momentum_break_by_mslf": 0,
      "pl": 37.48,
      "pvp": 3.7,
      "ev_ebit": 12.43,
      "roic": 9.1,
      "cres_rec_5a": 20.3,
      "div_liq_vm": 0.05,
      "avaliacao_fundamentalista": 18,
      "distortion_ranking": 72
    },
    "ENEV3": {
      "ticker": "ENEV3",
      "setor": null,
      "subsetor": "Energia Elétrica",
      "fundamental_signal": 0,
      "vol_signal": 0,
      "posicao_setorial": "",
      "preco": 26.270000457763672,
      "vol_anualizada_30d": 0.3118388361744947,
      "alto_vol_persistente": 0,
      "mma9": 26.407777574327255,
      "mma10": 26.286999893188476,
      "mma26": 25.196538411653957,
      "mma50": 25.64159984588623,
      "mma150": 23.217666664123534,
      "mma200": 21.77560001373291,
      "pct_to_mma10": -0.06466860232768097,
      "pct_to_mma50": 2.450707505203731,
      "sup_min_by_mslf": 14.4,
      "sup_med_by_mslf": 14.5,
      "sup_max_by_mslf": 14.6,
      "res_min_by_mslf": 28.1,
      "res_med_by_mslf": "Foguete",
      "res_max_by_mslf": "Foguete",
      "std_raking_value_by_mslf": 1,
      "momentum_break_by_mslf": 1,
      "pl": 39.21,
      "pvp": 2.5,
      "ev_ebit": 20.52,
      "roic": 6.1,
      "cres_rec_5a": 38.1,
      "div_liq_vm": 0.36,
      "avaliacao_fundamentalista": 18,
      "distortion_ranking": 63
    },
    "ENGI11": {
      "ticker": "ENGI11",
      "setor": null,
      "subsetor": "Energia Elétrica",
      "fundamental_signal": 0,
      "vol_signal": 0,
      "posicao_setorial": "",
      "preco": 48.099998474121094,
      "vol_anualizada_30d": 0.2059544290169102,
      "alto_vol_persistente": 0,
      "mma9": 47.69999991522895,
      "mma10": 47.59599990844727,
      "mma26": 47.048846171452446,
      "mma50": 48.79640014648437,
      "mma150": 50.32067876180013,
      "mma200": 49.35773614883423,
      "pct_to_mma10": 1.0589095021499408,
      "pct_to_mma50": -1.4271578851569302,
      "sup_min_by_mslf": 47.4,
      "sup_med_by_mslf": 47.7,
      "sup_max_by_mslf": 47.9,
      "res_min_by_mslf": 48.2,
      "res_med_by_mslf": 48.5,
      "res_max_by_mslf": 48.8,
      "std_raking_value_by_mslf": 1,
      "momentum_break_by_mslf": 0,
      "pl": 12.72,
      "pvp": 1.23,
      "ev_ebit": 8.37,
      "roic": 9.6,
      "cres_rec_5a": 8.0,
      "div_liq_vm": 0.28,
      "avaliacao_fundamentalista": 22,
      "distortion_ranking": 50
    },
    "EQTL3": {
      "ticker": "EQTL3",
      "setor": null,
      "subsetor": "Energia Elétrica",
      "fundamental_signal": 0,
      "vol_signal": 0,
      "posicao_setorial": "",
      "preco": 39.08000183105469,
      "vol_anualizada_30d": 0.21661743299479477,
      "alto_vol_persistente": 0,
      "mma9": 39.115555657280815,
      "mma10": 39.02400016784668,
      "mma26": 38.58115372290978,
      "mma50": 39.47159996032715,
      "mma150": 40.1902666982015,
      "mma200": 39.40585000991821,
      "pct_to_mma10": 0.14350569641025593,
      "pct_to_mma50": -0.9921009780856471,
      "sup_min_by_mslf": 37.8,
      "sup_med_by_mslf": 38.2,
      "sup_max_by_mslf": 38.8,
      "res_min_by_mslf": 39.2,
      "res_med_by_mslf": 46.3,
      "res_max_by_mslf": "Foguete",
      "std_raking_value_by_mslf": 1,
      "momentum_break_by_mslf": 0,
      "pl": 31.77,
      "pvp": 1.92,
      "ev_ebit": 9.62,
      "roic": 10.2,
      "cres_rec_5a": 20.2,
      "div_liq_vm": 0.93,
      "avaliacao_fundamentalista": 21,
      "distortion_ranking": 53
    },
    "FLRY3": {
      "ticker": "FLRY3",
      "setor": null,
      "subsetor": "ServMédHospit Análises e Diagnósticos00",
      "fundamental_signal": 0,
      "vol_signal": 0,
      "posicao_setorial": "melhor",
      "preco": 15.720000267028809,
      "vol_anualizada_30d": 0.2524698021316681,
      "alto_vol_persistente": 0,
      "mma9": 15.544444296095106,
      "mma10": 15.496999835968017,
      "mma26": 15.178076854118935,
      "mma50": 15.580999908447266,
      "mma150": 15.866200021107991,
      "mma200": 15.758549995422364,
      "pct_to_mma10": 1.4389909880699285,
      "pct_to_mma50": 0.8921144945658025,
      "sup_min_by_mslf": 15.2,
      "sup_med_by_mslf": 15.5,
      "sup_max_by_mslf": 15.6,
      "res_min_by_mslf": 15.8,
      "res_med_by_mslf": 16.0,
      "res_max_by_mslf": 16.6,
      "std_raking_value_by_mslf": 1,
      "momentum_break_by_mslf": 0,
      "pl": 13.55,
      "pvp": 1.66,
      "ev_ebit": 9.01,
      "roic": 12.3,
      "cres_rec_5a": 22.1,
      "div_liq_vm": 0.37,
      "avaliacao_fundamentalista": 28,
      "distortion_ranking": 52
    },
    "GGBR4": {
      "ticker": "GGBR4",
      "setor": null,
      "subsetor": "Siderurgia",
      "fundamental_signal": 0,
      "vol_signal": 0,
      "posicao_setorial": "",
      "preco": 21.68000030517578,
      "vol_anualizada_30d": 0.33039745212393656,
      "alto_vol_persistente": 0,
      "mma9": 21.274444580078125,
      "mma10": 21.31700019836426,
      "mma26": 22.472692269545334,
      "mma50": 22.87560001373291,
      "mma150": 21.318666687011717,
      "mma200": 20.46505002975464,
      "pct_to_mma10": 1.702866742194698,
      "pct_to_mma50": -5.226528300194857,
      "sup_min_by_mslf": 18.8,
      "sup_med_by_mslf": 18.9,
      "sup_max_by_mslf": 19.0,
      "res_min_by_mslf": 24.6,
      "res_med_by_mslf": "Foguete",
      "res_max_by_mslf": "Foguete",
      "std_raking_value_by_mslf": 1,
      "momentum_break_by_mslf": 1,
      "pl": 26.12,
      "pvp": 0.82,
      "ev_ebit": 8.72,
      "roic": 8.9,
      "cres_rec_5a": -5.1,
      "div_liq_vm": 0.19,
      "avaliacao_fundamentalista": 15,
      "distortion_ranking": 50
    },
    "GOAU4": {
      "ticker": "GOAU4",
      "setor": null,
      "subsetor": "Siderurgia",
      "fundamental_signal": 0,
      "vol_signal": 0,
      "posicao_setorial": "melhor",
      "preco": 9.630000114440918,
      "vol_anualizada_30d": 0.32653604556619176,
      "alto_vol_persistente": 0,
      "mma9": 9.438888973659939,
      "mma10": 9.450000095367432,
      "mma26": 9.868846196394701,
      "mma50": 10.003000030517578,
      "mma150": 9.399792114893595,
      "mma200": 8.983729825019836,
      "pct_to_mma10": 1.9047620873752689,
      "pct_to_mma50": -3.728880485241387,
      "sup_min_by_mslf": 7.8,
      "sup_med_by_mslf": 8.0,
      "sup_max_by_mslf": 8.3,
      "res_min_by_mslf": 10.8,
      "res_med_by_mslf": "Foguete",
      "res_max_by_mslf": "Foguete",
      "std_raking_value_by_mslf": 1,
      "momentum_break_by_mslf": 1,
      "pl": 22.4,
      "pvp": 0.67,
      "ev_ebit": 3.46,
      "roic": 8.9,
      "cres_rec_5a": -5.1,
      "div_liq_vm": 0.64,
      "avaliacao_fundamentalista": 19,
      "distortion_ranking": 50
    },
    "HAPV3": {
      "ticker": "HAPV3",
      "setor": null,
      "subsetor": "ServMédHospit Análises e Diagnósticos00",
      "fundamental_signal": 0,
      "vol_signal": 0,
      "posicao_setorial": "pior",
      "preco": 10.420000076293945,
      "vol_anualizada_30d": 0.4188828362685007,
      "alto_vol_persistente": 0,
      "mma9": 10.34444448682997,
      "mma10": 10.338000011444091,
      "mma26": 10.903846117166372,
      "mma50": 11.623399982452392,
      "mma150": 12.118666655222574,
      "mma200": 17.074999966621398,
      "pct_to_mma10": 0.7931907985981886,
      "pct_to_mma50": -10.35325212911192,
      "sup_min_by_mslf": 10.1,
      "sup_med_by_mslf": 10.3,
      "sup_max_by_mslf": 10.4,
      "res_min_by_mslf": 10.5,
      "res_med_by_mslf": 10.6,
      "res_max_by_mslf": 10.7,
      "std_raking_value_by_mslf": 2,
      "momentum_break_by_mslf": 0,
      "pl": -12.26,
      "pvp": 0.11,
      "ev_ebit": 10.11,
      "roic": 1.7,
      "cres_rec_5a": 25.1,
      "div_liq_vm": 0.95,
      "avaliacao_fundamentalista": 17,
      "distortion_ranking": 38
    },
    "HYPE3": {
      "ticker": "HYPE3",
      "setor": null,
      "subsetor": "Medicamentos e Outros Produtos",
      "fundamental_signal": 0,
      "vol_signal": 0,
      "posicao_setorial": "",
      "preco": 20.760000228881836,
      "vol_anualizada_30d": 0.2555649690643649,
      "alto_vol_persistente": 0,
      "mma9": 20.98444430033366,
      "mma10": 20.918999862670898,
      "mma26": 20.934999979459324,
      "mma50": 21.831599998474122,
      "mma150": 23.026733334859212,
      "mma200": 23.17994999885559,
      "pct_to_mma10": -0.7600728277301161,
      "pct_to_mma50": -4.908480228967109,
      "sup_min_by_mslf": 16.8,
      "sup_med_by_mslf": 19.4,
      "sup_max_by_mslf": 19.5,
      "res_min_by_mslf": 22.4,
      "res_med_by_mslf": 22.5,
      "res_max_by_mslf": 22.6,
      "std_raking_value_by_mslf": 1,
      "momentum_break_by_mslf": 0,
      "pl": 8.69,
      "pvp": 1.03,
      "ev_ebit": 8.66,
      "roic": 10.6,
      "cres_rec_5a": 5.1,
      "div_liq_vm": 0.43,
      "avaliacao_fundamentalista": 24,
      "distortion_ranking": 35
    },
    "IGTI11": {
      "ticker": "IGTI11",
      "setor": null,
      "subsetor": "Exploração de Imóveis",
      "fundamental_signal": 0,
      "vol_signal": 0,
      "posicao_setorial": "",
      "preco": 25.489999771118164,
      "vol_anualizada_30d": 0.24637460033348715,
      "alto_vol_persistente": 0,
      "mma9": 25.30333349439833,
      "mma10": 25.191000175476074,
      "mma26": 24.80307703751784,
      "mma50": 25.88379997253418,
      "mma150": 26.927799936930338,
      "mma200": 26.305499925613404,
      "pct_to_mma10": 1.186930227300671,
      "pct_to_mma50": -1.5214157188430066,
      "sup_min_by_mslf": 24.1,
      "sup_med_by_mslf": 24.2,
      "sup_max_by_mslf": 24.7,
      "res_min_by_mslf": 26.4,
      "res_med_by_mslf": 30.6,
      "res_max_by_mslf": "Foguete",
      "std_raking_value_by_mslf": 1,
      "momentum_break_by_mslf": 0,
      "pl": 10.62,
      "pvp": 1.55,
      "ev_ebit": 9.99,
      "roic": 12.6,
      "cres_rec_5a": 12.8,
      "div_liq_vm": 0.04,
      "avaliacao_fundamentalista": 27,
      "distortion_ranking": 45
    },
    "ISAE4": {
      "ticker": "ISAE4",
      "setor": null,
      "subsetor": "Energia Elétrica",
      "fundamental_signal": 0,
      "vol_signal": 0,
      "posicao_setorial": "",
      "preco": 27.530000686645508,
      "vol_anualizada_30d": 0.23845585612889694,
      "alto_vol_persistente": 0,
      "mma9": 28.103333367241753,
      "mma10": 28.07800006866455,
      "mma26": 27.616538708026592,
      "mma50": 28.227400131225586,
      "mma150": 28.262933336893717,
      "mma200": 27.459800033569337,
      "pct_to_mma10": -1.9517037562465787,
      "pct_to_mma50": -2.4706471064921223,
      "sup_min_by_mslf": 25.5,
      "sup_med_by_mslf": 26.8,
      "sup_max_by_mslf": 27.1,
      "res_min_by_mslf": 27.7,
      "res_med_by_mslf": 32.2,
      "res_max_by_mslf": "Foguete",
      "std_raking_value_by_mslf": 1,
      "momentum_break_by_mslf": 0,
      "pl": 7.73,
      "pvp": 0.85,
      "ev_ebit": 9.12,
      "roic": 7.7,
      "cres_rec_5a": 14.8,
      "div_liq_vm": 0.83,
      "avaliacao_fundamentalista": 26,
      "distortion_ranking": 40
    },
    "ITSA4": {
      "ticker": "ITSA4",
      "setor": null,
      "subsetor": "Bancos",
      "fundamental_signal": 0,
      "vol_signal": 0,
      "posicao_setorial": "",
      "preco": 13.460000038146973,
      "vol_anualizada_30d": 0.18602264369115012,
      "alto_vol_persistente": 0,
      "mma9": 13.407777892218697,
      "mma10": 13.370000076293945,
      "mma26": 13.011538468874418,
      "mma50": 13.152400016784668,
      "mma150": 13.193103224436442,
      "mma200": 12.695366506576539,
      "pct_to_mma10": 0.6731485515292182,
      "pct_to_mma50": 2.3387368158644466,
      "sup_min_by_mslf": 11.1,
      "sup_med_by_mslf": 11.2,
      "sup_max_by_mslf": 11.4,
      "res_min_by_mslf": 15.2,
      "res_med_by_mslf": "Foguete",
      "res_max_by_mslf": "Foguete",
      "std_raking_value_by_mslf": 1,
      "momentum_break_by_mslf": 1,
      "pl": 8.91,
      "pvp": 1.67,
      "ev_ebit": 387.73,
      "roic": 0.4,
      "cres_rec_5a": -0.2,
      "div_liq_vm": 0.03,
      "avaliacao_fundamentalista": 24,
      "distortion_ranking": 59
    },
    "ITUB4": {
      "ticker": "ITUB4",
      "setor": null,
      "subsetor": "Bancos",
      "fundamental_signal": 0,
      "vol_signal": 0,
      "posicao_setorial": "",
      "preco": 42.439998626708984,
      "vol_anualizada_30d": 0.19270952946564204,
      "alto_vol_persistente": 0,
      "mma9": 42.17666710747613,
      "mma10": 42.06400032043457,
      "mma26": 40.703846564659706,
      "mma50": 40.87520011901856,
      "mma150": 42.26842379252116,
      "mma200": 41.11791971206665,
      "pct_to_mma10": 0.8938719651248964,
      "pct_to_mma50": 3.828234487254171,
      "sup_min_by_mslf": 40.6,
      "sup_med_by_mslf": 41.4,
      "sup_max_by_mslf": 42.1,
      "res_min_by_mslf": 49.7,
      "res_med_by_mslf": "Foguete",
      "res_max_by_mslf": "Foguete",
      "std_raking_value_by_mslf": 1,
      "momentum_break_by_mslf": 1,
      "pl": 10.08,
      "pvp": 2.34,
      "ev_ebit": 0.0,
      "roic": 0.0,
      "cres_rec_5a": 71.6,
      "div_liq_vm": 0.0,
      "avaliacao_fundamentalista": 29,
      "distortion_ranking": 54
    },
    "KLBN11": {
      "ticker": "KLBN11",
      "setor": null,
      "subsetor": "Papel e Celulose",
      "fundamental_signal": -1,
      "vol_signal": 1,
      "posicao_setorial": "pior",
      "preco": 16.969999313354492,
      "vol_anualizada_30d": 0.13874581224162005,
      "alto_vol_persistente": 0,
      "mma9": 16.94111082288954,
      "mma10": 16.927999687194824,
      "mma26": 16.938846001258263,
      "mma50": 16.951599960327147,
      "mma150": 18.36483425140381,
      "mma200": 18.213724536895754,
      "pct_to_mma10": 0.2481074370023723,
      "pct_to_mma50": 0.10854050986576996,
      "sup_min_by_mslf": "Abismo",
      "sup_med_by_mslf": "Abismo",
      "sup_max_by_mslf": 16.1,
      "res_min_by_mslf": 17.7,
      "res_med_by_mslf": 17.8,
      "res_max_by_mslf": 17.9,
      "std_raking_value_by_mslf": 1,
      "momentum_break_by_mslf": -1,
      "pl": 28.28,
      "pvp": 2.34,
      "ev_ebit": 14.72,
      "roic": 6.3,
      "cres_rec_5a": 3.4,
      "div_liq_vm": 0.23,
      "avaliacao_fundamentalista": 12,
      "distortion_ranking": 66
    },
    "LREN3": {
      "ticker": "LREN3",
      "setor": null,
      "subsetor": "Tecidos. Vestuário e Calçados",
      "fundamental_signal": 1,
      "vol_signal": 0,
      "posicao_setorial": "",
      "preco": 14.319999694824219,
      "vol_anualizada_30d": 0.33897111199694624,
      "alto_vol_persistente": 0,
      "mma9": 14.724444495307075,
      "mma10": 14.70600004196167,
      "mma26": 14.804615497589111,
      "mma50": 14.518400096893311,
      "mma150": 14.685266717274983,
      "mma200": 14.76465003490448,
      "pct_to_mma10": -2.624781354794291,
      "pct_to_mma50": -1.3665445279438637,
      "sup_min_by_mslf": "Abismo",
      "sup_med_by_mslf": 11.0,
      "sup_max_by_mslf": 13.4,
      "res_min_by_mslf": 14.4,
      "res_med_by_mslf": 14.6,
      "res_max_by_mslf": 14.7,
      "std_raking_value_by_mslf": 2,
      "momentum_break_by_mslf": 0,
      "pl": 9.68,
      "pvp": 1.39,
      "ev_ebit": 3.73,
      "roic": 23.8,
      "cres_rec_5a": 7.6,
      "div_liq_vm": -0.1,
      "avaliacao_fundamentalista": 32,
      "distortion_ranking": 33
    },
    "MBRF3": {
      "ticker": "MBRF3",
      "setor": null,
      "subsetor": "Carnes e Derivados",
      "fundamental_signal": 0,
      "vol_signal": -1,
      "posicao_setorial": "pior",
      "preco": 16.649999618530273,
      "vol_anualizada_30d": 0.431936797609819,
      "alto_vol_persistente": 0,
      "mma9": 17.11000018649631,
      "mma10": 17.079000091552736,
      "mma26": 16.237692282750057,
      "mma50": 16.692400035858153,
      "mma150": 18.445466747283934,
      "mma200": 18.628800048828126,
      "pct_to_mma10": -2.5118594222307298,
      "pct_to_mma50": -0.25401031149982134,
      "sup_min_by_mslf": 15.9,
      "sup_med_by_mslf": 16.1,
      "sup_max_by_mslf": 16.4,
      "res_min_by_mslf": 16.8,
      "res_med_by_mslf": 16.9,
      "res_max_by_mslf": 17.1,
      "std_raking_value_by_mslf": 1,
      "momentum_break_by_mslf": 0,
      "pl": 61.67,
      "pvp": 2.04,
      "ev_ebit": 12.35,
      "roic": 6.3,
      "cres_rec_5a": 13.9,
      "div_liq_vm": 2.13,
      "avaliacao_fundamentalista": 16,
      "distortion_ranking": 58
    },
    "MGLU3": {
      "ticker": "MGLU3",
      "setor": null,
      "subsetor": "Eletrodomésticos",
      "fundamental_signal": 0,
      "vol_signal": -1,
      "posicao_setorial": "pior",
      "preco": 4.360000133514404,
      "vol_anualizada_30d": 0.5578914865286383,
      "alto_vol_persistente": 0,
      "mma9": 4.449999968210856,
      "mma10": 4.446999979019165,
      "mma26": 4.926923036575317,
      "mma50": 6.073599939346313,
      "mma150": 8.255196708043416,
      "mma200": 8.399778347015381,
      "pct_to_mma10": -1.956371619411379,
      "pct_to_mma50": -28.21390646313033,
      "sup_min_by_mslf": "Abismo",
      "sup_med_by_mslf": "Abismo",
      "sup_max_by_mslf": 4.0,
      "res_min_by_mslf": 8.4,
      "res_med_by_mslf": 8.5,
      "res_max_by_mslf": 8.6,
      "std_raking_value_by_mslf": 1,
      "momentum_break_by_mslf": -1,
      "pl": 24.22,
      "pvp": 0.3,
      "ev_ebit": 5.29,
      "roic": 6.1,
      "cres_rec_5a": 1.6,
      "div_liq_vm": 1.02,
      "avaliacao_fundamentalista": 17,
      "distortion_ranking": 29
    },
    "MOTV3": {
      "ticker": "MOTV3",
      "setor": null,
      "subsetor": "Exploração de Rodovias",
      "fundamental_signal": 0,
      "vol_signal": 0,
      "posicao_setorial": "melhor",
      "preco": 14.720000267028809,
      "vol_anualizada_30d": 0.18383813792088718,
      "alto_vol_persistente": 0,
      "mma9": 14.55888885921902,
      "mma10": 14.523999977111817,
      "mma26": 14.17269226220938,
      "mma50": 14.677399959564209,
      "mma150": 15.573400020599365,
      "mma200": 15.46845000743866,
      "pct_to_mma10": 1.3494924967355122,
      "pct_to_mma50": 0.29024423659478044,
      "sup_min_by_mslf": 13.8,
      "sup_med_by_mslf": 13.9,
      "sup_max_by_mslf": 14.0,
      "res_min_by_mslf": 14.9,
      "res_med_by_mslf": 17.8,
      "res_max_by_mslf": "Foguete",
      "std_raking_value_by_mslf": 2,
      "momentum_break_by_mslf": 0,
      "pl": 8.87,
      "pvp": 1.82,
      "ev_ebit": 8.5,
      "roic": 10.9,
      "cres_rec_5a": 5.7,
      "div_liq_vm": 1.04,
      "avaliacao_fundamentalista": 26,
      "distortion_ranking": 54
    },
    "MRVE3": {
      "ticker": "MRVE3",
      "setor": null,
      "subsetor": "Incorporações",
      "fundamental_signal": 0,
      "vol_signal": 0,
      "posicao_setorial": "pior",
      "preco": 5.400000095367432,
      "vol_anualizada_30d": 0.3925935546196483,
      "alto_vol_persistente": 0,
      "mma9": 5.25,
      "mma10": 5.215000009536743,
      "mma26": 5.2903845860407905,
      "mma50": 5.865599985122681,
      "mma150": 7.547866678237915,
      "mma200": 7.508950009346008,
      "pct_to_mma10": 3.5474608915124946,
      "pct_to_mma50": -7.937805014596661,
      "sup_min_by_mslf": 5.1,
      "sup_med_by_mslf": 5.3,
      "sup_max_by_mslf": 5.4,
      "res_min_by_mslf": 5.5,
      "res_med_by_mslf": 5.6,
      "res_max_by_mslf": 5.9,
      "std_raking_value_by_mslf": 1,
      "momentum_break_by_mslf": 0,
      "pl": -4.0,
      "pvp": 0.58,
      "ev_ebit": 6.32,
      "roic": 6.6,
      "cres_rec_5a": 13.5,
      "div_liq_vm": 2.61,
      "avaliacao_fundamentalista": 20,
      "distortion_ranking": 42
    },
    "MULT3": {
      "ticker": "MULT3",
      "setor": null,
      "subsetor": "Exploração de Imóveis",
      "fundamental_signal": 0,
      "vol_signal": 0,
      "posicao_setorial": "melhor",
      "preco": 28.969999313354492,
      "vol_anualizada_30d": 0.20704953090636954,
      "alto_vol_persistente": 0,
      "mma9": 29.27777777777778,
      "mma10": 29.225,
      "mma26": 28.79115390777588,
      "mma50": 29.733199996948244,
      "mma150": 30.666800015767414,
      "mma200": 30.088850059509276,
      "pct_to_mma10": -0.8725429825338211,
      "pct_to_mma50": -2.5668299532915566,
      "sup_min_by_mslf": 27.2,
      "sup_med_by_mslf": 27.5,
      "sup_max_by_mslf": 28.8,
      "res_min_by_mslf": 29.0,
      "res_med_by_mslf": 29.9,
      "res_max_by_mslf": 36.0,
      "std_raking_value_by_mslf": 2,
      "momentum_break_by_mslf": 0,
      "pl": 12.17,
      "pvp": 2.3,
      "ev_ebit": 9.38,
      "roic": 17.3,
      "cres_rec_5a": 19.9,
      "div_liq_vm": 0.3,
      "avaliacao_fundamentalista": 29,
      "distortion_ranking": 34
    },
    "NATU3": {
      "ticker": "NATU3",
      "setor": null,
      "subsetor": "Produtos de Uso Pessoal",
      "fundamental_signal": 0,
      "vol_signal": -1,
      "posicao_setorial": "pior",
      "preco": 8.270000457763672,
      "vol_anualizada_30d": 0.48264821401983354,
      "alto_vol_persistente": 0,
      "mma9": 8.232222292158339,
      "mma10": 8.18100004196167,
      "mma26": 8.572307715049156,
      "mma50": 9.33699999809265,
      "mma150": 8.945733289718628,
      "mma200": 8.876499967575073,
      "pct_to_mma10": 1.0878916433871622,
      "pct_to_mma50": -11.427648501091829,
      "sup_min_by_mslf": "Abismo",
      "sup_med_by_mslf": 7.1,
      "sup_max_by_mslf": 8.1,
      "res_min_by_mslf": 8.4,
      "res_med_by_mslf": 8.5,
      "res_max_by_mslf": 8.6,
      "std_raking_value_by_mslf": 1,
      "momentum_break_by_mslf": 0,
      "pl": -4.89,
      "pvp": 0.91,
      "ev_ebit": 7.12,
      "roic": 11.6,
      "cres_rec_5a": 1.8,
      "div_liq_vm": 0.35,
      "avaliacao_fundamentalista": 19,
      "distortion_ranking": 37
    },
    "PETR3": {
      "ticker": "PETR3",
      "setor": null,
      "subsetor": "Exploração. Refino e Distribuição",
      "fundamental_signal": 0,
      "vol_signal": 0,
      "posicao_setorial": "",
      "preco": 41.68000030517578,
      "vol_anualizada_30d": 0.23157471716763386,
      "alto_vol_persistente": 0,
      "mma9": 42.18111080593533,
      "mma10": 42.36099967956543,
      "mma26": 44.154230704674355,
      "mma50": 47.426600036621096,
      "mma150": 43.42713342030843,
      "mma200": 40.8912500667572,
      "pct_to_mma10": -1.6076093093670731,
      "pct_to_mma50": -12.116828376919281,
      "sup_min_by_mslf": 41.4,
      "sup_med_by_mslf": 41.5,
      "sup_max_by_mslf": 41.6,
      "res_min_by_mslf": 41.7,
      "res_med_by_mslf": 41.8,
      "res_max_by_mslf": 41.9,
      "std_raking_value_by_mslf": 1,
      "momentum_break_by_mslf": 0,
      "pl": 4.99,
      "pvp": 1.21,
      "ev_ebit": 4.8,
      "roic": 16.8,
      "cres_rec_5a": -2.9,
      "div_liq_vm": 0.6,
      "avaliacao_fundamentalista": 29,
      "distortion_ranking": 22
    },
    "PETR4": {
      "ticker": "PETR4",
      "setor": null,
      "subsetor": "Exploração. Refino e Distribuição",
      "fundamental_signal": 0,
      "vol_signal": 0,
      "posicao_setorial": "",
      "preco": 37.689998626708984,
      "vol_anualizada_30d": 0.21380996503696917,
      "alto_vol_persistente": 0,
      "mma9": 38.052222357855904,
      "mma10": 38.18000030517578,
      "mma26": 39.609615325927734,
      "mma50": 42.65959991455078,
      "mma150": 39.82006669362386,
      "mma200": 37.64510004043579,
      "pct_to_mma10": -1.2833988332901374,
      "pct_to_mma50": -11.649432478964046,
      "sup_min_by_mslf": 37.2,
      "sup_med_by_mslf": 37.3,
      "sup_max_by_mslf": 37.5,
      "res_min_by_mslf": 37.8,
      "res_med_by_mslf": 38.2,
      "res_max_by_mslf": 38.3,
      "std_raking_value_by_mslf": 2,
      "momentum_break_by_mslf": 0,
      "pl": 4.51,
      "pvp": 1.09,
      "ev_ebit": 4.47,
      "roic": 16.8,
      "cres_rec_5a": -2.9,
      "div_liq_vm": 0.67,
      "avaliacao_fundamentalista": 30,
      "distortion_ranking": 21
    },
    "POMO4": {
      "ticker": "POMO4",
      "setor": null,
      "subsetor": "Material Rodoviário",
      "fundamental_signal": 1,
      "vol_signal": 0,
      "posicao_setorial": "melhor",
      "preco": 5.760000228881836,
      "vol_anualizada_30d": 0.2864408308317319,
      "alto_vol_persistente": 0,
      "mma9": 5.887777752346462,
      "mma10": 5.87999997138977,
      "mma26": 5.871538418989915,
      "mma50": 6.038799972534179,
      "mma150": 6.1512908299764,
      "mma200": 6.5171498417854306,
      "pct_to_mma10": -2.040811957343796,
      "pct_to_mma50": -4.616807062999063,
      "sup_min_by_mslf": "Abismo",
      "sup_med_by_mslf": "Abismo",
      "sup_max_by_mslf": 5.3,
      "res_min_by_mslf": 7.0,
      "res_med_by_mslf": 7.1,
      "res_max_by_mslf": 7.2,
      "std_raking_value_by_mslf": 1,
      "momentum_break_by_mslf": -1,
      "pl": 5.76,
      "pvp": 1.77,
      "ev_ebit": 6.46,
      "roic": 20.5,
      "cres_rec_5a": 24.2,
      "div_liq_vm": 0.22,
      "avaliacao_fundamentalista": 36,
      "distortion_ranking": 22
    },
    "PRIO3": {
      "ticker": "PRIO3",
      "setor": null,
      "subsetor": "Exploração. Refino e Distribuição",
      "fundamental_signal": 0,
      "vol_signal": 0,
      "posicao_setorial": "",
      "preco": 52.970001220703125,
      "vol_anualizada_30d": 0.3166208592243968,
      "alto_vol_persistente": 0,
      "mma9": 53.05888917711046,
      "mma10": 53.363000106811526,
      "mma26": 57.55923080444336,
      "mma50": 61.65120010375976,
      "mma150": 55.120266596476235,
      "mma200": 50.77419996261597,
      "pct_to_mma10": -0.7364632522942369,
      "pct_to_mma50": -14.081151491692081,
      "sup_min_by_mslf": 43.0,
      "sup_med_by_mslf": 43.3,
      "sup_max_by_mslf": 43.8,
      "res_min_by_mslf": 73.0,
      "res_med_by_mslf": "Foguete",
      "res_max_by_mslf": "Foguete",
      "std_raking_value_by_mslf": 1,
      "momentum_break_by_mslf": 1,
      "pl": 17.84,
      "pvp": 1.74,
      "ev_ebit": 20.97,
      "roic": 6.4,
      "cres_rec_5a": 36.8,
      "div_liq_vm": 0.52,
      "avaliacao_fundamentalista": 19,
      "distortion_ranking": 29
    },
    "PSSA3": {
      "ticker": "PSSA3",
      "setor": null,
      "subsetor": "Seguradoras",
      "fundamental_signal": 0,
      "vol_signal": 1,
      "posicao_setorial": "melhor",
      "preco": 53.470001220703125,
      "vol_anualizada_30d": 0.18014165211614988,
      "alto_vol_persistente": 0,
      "mma9": 53.17222171359592,
      "mma10": 53.07399940490723,
      "mma26": 51.04076928358812,
      "mma50": 50.31720016479492,
      "mma150": 49.880266723632815,
      "mma200": 49.419150009155274,
      "pct_to_mma10": 0.7461314772507687,
      "pct_to_mma50": 6.265851529064418,
      "sup_min_by_mslf": 52.9,
      "sup_med_by_mslf": 53.1,
      "sup_max_by_mslf": 53.2,
      "res_min_by_mslf": 53.5,
      "res_med_by_mslf": 53.6,
      "res_max_by_mslf": 53.8,
      "std_raking_value_by_mslf": 2,
      "momentum_break_by_mslf": 0,
      "pl": 9.38,
      "pvp": 2.23,
      "ev_ebit": 0.52,
      "roic": 77.5,
      "cres_rec_5a": 15.8,
      "div_liq_vm": -0.38,
      "avaliacao_fundamentalista": 27,
      "distortion_ranking": 60
    },
    "RADL3": {
      "ticker": "RADL3",
      "setor": null,
      "subsetor": "Medicamentos e Outros Produtos",
      "fundamental_signal": 0,
      "vol_signal": 0,
      "posicao_setorial": "pior",
      "preco": 17.450000762939453,
      "vol_anualizada_30d": 0.3426043333286818,
      "alto_vol_persistente": 0,
      "mma9": 17.077777862548828,
      "mma10": 17.070000076293944,
      "mma26": 17.352307833158054,
      "mma50": 18.72540012359619,
      "mma150": 22.2981751759847,
      "mma200": 21.568778324127198,
      "pct_to_mma10": 2.2261317220099914,
      "pct_to_mma50": -6.811065997193759,
      "sup_min_by_mslf": 17.1,
      "sup_med_by_mslf": 17.2,
      "sup_max_by_mslf": 17.3,
      "res_min_by_mslf": 17.5,
      "res_med_by_mslf": 18.0,
      "res_max_by_mslf": 18.2,
      "std_raking_value_by_mslf": 3,
      "momentum_break_by_mslf": 0,
      "pl": 23.58,
      "pvp": 4.16,
      "ev_ebit": 12.08,
      "roic": 15.6,
      "cres_rec_5a": 15.4,
      "div_liq_vm": 0.1,
      "avaliacao_fundamentalista": 22,
      "distortion_ranking": 39
    },
    "RAIL3": {
      "ticker": "RAIL3",
      "setor": null,
      "subsetor": "Transporte Ferroviário",
      "fundamental_signal": 0,
      "vol_signal": 0,
      "posicao_setorial": "pior",
      "preco": 13.59000015258789,
      "vol_anualizada_30d": 0.2901254559368966,
      "alto_vol_persistente": 0,
      "mma9": 13.444444338480631,
      "mma10": 13.389999866485596,
      "mma26": 13.335384552295391,
      "mma50": 14.295000038146974,
      "mma150": 15.21633337020874,
      "mma200": 15.299200005531311,
      "pct_to_mma10": 1.4936541306686957,
      "pct_to_mma50": -4.931793519956299,
      "sup_min_by_mslf": "Abismo",
      "sup_med_by_mslf": "Abismo",
      "sup_max_by_mslf": 12.2,
      "res_min_by_mslf": 14.2,
      "res_med_by_mslf": 14.6,
      "res_max_by_mslf": 14.8,
      "std_raking_value_by_mslf": 1,
      "momentum_break_by_mslf": -1,
      "pl": 24.27,
      "pvp": 1.82,
      "ev_ebit": 7.55,
      "roic": 12.1,
      "cres_rec_5a": 16.0,
      "div_liq_vm": 0.69,
      "avaliacao_fundamentalista": 25,
      "distortion_ranking": 40
    },
    "RDOR3": {
      "ticker": "RDOR3",
      "setor": null,
      "subsetor": "ServMédHospit Análises e Diagnósticos00",
      "fundamental_signal": 0,
      "vol_signal": 0,
      "posicao_setorial": "melhor",
      "preco": 35.15999984741211,
      "vol_anualizada_30d": 0.25665891511811395,
      "alto_vol_persistente": 0,
      "mma9": 34.91222169664171,
      "mma10": 34.85499954223633,
      "mma26": 34.035384544959435,
      "mma50": 35.13700004577637,
      "mma150": 39.37513326009115,
      "mma200": 40.18204996109009,
      "pct_to_mma10": 0.8750546813411667,
      "pct_to_mma50": 0.06545749951839164,
      "sup_min_by_mslf": 34.8,
      "sup_med_by_mslf": 35.0,
      "sup_max_by_mslf": 35.1,
      "res_min_by_mslf": 37.7,
      "res_med_by_mslf": 38.6,
      "res_max_by_mslf": 38.7,
      "std_raking_value_by_mslf": 3,
      "momentum_break_by_mslf": 0,
      "pl": 17.41,
      "pvp": 4.07,
      "ev_ebit": 8.33,
      "roic": 15.2,
      "cres_rec_5a": 29.3,
      "div_liq_vm": 0.09,
      "avaliacao_fundamentalista": 28,
      "distortion_ranking": 51
    },
    "RECV3": {
      "ticker": "RECV3",
      "setor": null,
      "subsetor": "Exploração. Refino e Distribuição",
      "fundamental_signal": 0,
      "vol_signal": 0,
      "posicao_setorial": "melhor",
      "preco": 9.430000305175781,
      "vol_anualizada_30d": 0.31889413355316476,
      "alto_vol_persistente": 0,
      "mma9": 9.840000046624077,
      "mma10": 9.867000007629395,
      "mma26": 10.328076912806583,
      "mma50": 11.318600006103516,
      "mma150": 11.668266671498616,
      "mma200": 11.826050004959107,
      "pct_to_mma10": -4.428901409908941,
      "pct_to_mma50": -16.685806547711852,
      "sup_min_by_mslf": "Abismo",
      "sup_med_by_mslf": "Abismo",
      "sup_max_by_mslf": 9.4,
      "res_min_by_mslf": 11.5,
      "res_med_by_mslf": 12.3,
      "res_max_by_mslf": 12.4,
      "std_raking_value_by_mslf": 1,
      "momentum_break_by_mslf": -1,
      "pl": 5.18,
      "pvp": 0.66,
      "ev_ebit": 7.15,
      "roic": 9.4,
      "cres_rec_5a": 16.2,
      "div_liq_vm": 0.55,
      "avaliacao_fundamentalista": 31,
      "distortion_ranking": 14
    },
    "RENT3": {
      "ticker": "RENT3",
      "setor": null,
      "subsetor": "Aluguel de carros",
      "fundamental_signal": 0,
      "vol_signal": 0,
      "posicao_setorial": "",
      "preco": 40.459999084472656,
      "vol_anualizada_30d": 0.3123768180103306,
      "alto_vol_persistente": 0,
      "mma9": 41.693333095974396,
      "mma10": 41.70199966430664,
      "mma26": 41.0788459777832,
      "mma50": 43.06300010681152,
      "mma150": 45.648200022379555,
      "mma200": 44.13255004882812,
      "pct_to_mma10": -2.9782758376861027,
      "pct_to_mma50": -6.044634641995447,
      "sup_min_by_mslf": 40.2,
      "sup_med_by_mslf": 40.3,
      "sup_max_by_mslf": 40.4,
      "res_min_by_mslf": 40.9,
      "res_med_by_mslf": 41.1,
      "res_max_by_mslf": 41.2,
      "std_raking_value_by_mslf": 1,
      "momentum_break_by_mslf": 0,
      "pl": 20.23,
      "pvp": 1.73,
      "ev_ebit": 9.61,
      "roic": 12.4,
      "cres_rec_5a": 40.1,
      "div_liq_vm": 0.71,
      "avaliacao_fundamentalista": 25,
      "distortion_ranking": 28
    },
    "SANB11": {
      "ticker": "SANB11",
      "setor": null,
      "subsetor": "Bancos",
      "fundamental_signal": 0,
      "vol_signal": 1,
      "posicao_setorial": "melhor",
      "preco": 26.860000610351562,
      "vol_anualizada_30d": 0.14713732720603295,
      "alto_vol_persistente": 0,
      "mma9": 26.643333435058594,
      "mma10": 26.654000091552735,
      "mma26": 26.876153799203728,
      "mma50": 27.416199951171876,
      "mma150": 31.189266624450685,
      "mma200": 30.907750005722047,
      "pct_to_mma10": 0.7728690556435981,
      "pct_to_mma50": -2.0287251399205655,
      "sup_min_by_mslf": 26.2,
      "sup_med_by_mslf": 26.3,
      "sup_max_by_mslf": 26.8,
      "res_min_by_mslf": 27.0,
      "res_med_by_mslf": 27.1,
      "res_max_by_mslf": 27.5,
      "std_raking_value_by_mslf": 1,
      "momentum_break_by_mslf": 0,
      "pl": 6.5,
      "pvp": 1.04,
      "ev_ebit": 0.0,
      "roic": 0.0,
      "cres_rec_5a": 3.3,
      "div_liq_vm": 0.0,
      "avaliacao_fundamentalista": 30,
      "distortion_ranking": 41
    },
    "SBSP3": {
      "ticker": "SBSP3",
      "setor": null,
      "subsetor": "Água e Saneamento",
      "fundamental_signal": 0,
      "vol_signal": 0,
      "posicao_setorial": "melhor",
      "preco": 29.860000610351562,
      "vol_anualizada_30d": 0.22925477778618317,
      "alto_vol_persistente": 0,
      "mma9": 29.583333333333332,
      "mma10": 29.44099998474121,
      "mma26": 28.256538537832405,
      "mma50": 29.411480178833006,
      "mma150": 29.101064440409342,
      "mma200": 28.200743703842164,
      "pct_to_mma10": 1.4231874794589612,
      "pct_to_mma50": 1.5249842197379428,
      "sup_min_by_mslf": 23.4,
      "sup_med_by_mslf": 24.0,
      "sup_max_by_mslf": 25.9,
      "res_min_by_mslf": 35.3,
      "res_med_by_mslf": "Foguete",
      "res_max_by_mslf": "Foguete",
      "std_raking_value_by_mslf": 1,
      "momentum_break_by_mslf": 1,
      "pl": 12.04,
      "pvp": 2.41,
      "ev_ebit": 10.0,
      "roic": 13.3,
      "cres_rec_5a": 21.0,
      "div_liq_vm": 0.31,
      "avaliacao_fundamentalista": 28,
      "distortion_ranking": 56
    },
    "SLCE3": {
      "ticker": "SLCE3",
      "setor": null,
      "subsetor": "Agricultura",
      "fundamental_signal": 0,
      "vol_signal": 0,
      "posicao_setorial": "pior",
      "preco": 12.75,
      "vol_anualizada_30d": 0.19480319220397674,
      "alto_vol_persistente": 0,
      "mma9": 12.953333324856228,
      "mma10": 13.003999996185303,
      "mma26": 13.88961542569674,
      "mma50": 15.357000064849853,
      "mma150": 15.938185087839763,
      "mma200": 15.565016489028931,
      "pct_to_mma10": -1.9532451265750064,
      "pct_to_mma50": -16.97597222010132,
      "sup_min_by_mslf": "Abismo",
      "sup_med_by_mslf": "Abismo",
      "sup_max_by_mslf": 12.6,
      "res_min_by_mslf": 15.1,
      "res_med_by_mslf": 15.4,
      "res_max_by_mslf": 15.5,
      "std_raking_value_by_mslf": 1,
      "momentum_break_by_mslf": -1,
      "pl": 19.62,
      "pvp": 1.2,
      "ev_ebit": 7.99,
      "roic": 9.8,
      "cres_rec_5a": 2.4,
      "div_liq_vm": 1.0,
      "avaliacao_fundamentalista": 19,
      "distortion_ranking": 27
    },
    "SMFT3": {
      "ticker": "SMFT3",
      "setor": null,
      "subsetor": "Atividades Esportivas",
      "fundamental_signal": 0,
      "vol_signal": 0,
      "posicao_setorial": "pior",
      "preco": 20.09000015258789,
      "vol_anualizada_30d": 0.236546278188887,
      "alto_vol_persistente": 0,
      "mma9": 19.628889083862305,
      "mma10": 19.55100021362305,
      "mma26": 19.018461594214806,
      "mma50": 18.81599998474121,
      "mma150": 20.529321250915526,
      "mma200": 21.70089093208313,
      "pct_to_mma10": 2.75689188826907,
      "pct_to_mma50": 6.770834230866428,
      "sup_min_by_mslf": 19.4,
      "sup_med_by_mslf": 19.6,
      "sup_max_by_mslf": 19.9,
      "res_min_by_mslf": 22.0,
      "res_med_by_mslf": 22.1,
      "res_max_by_mslf": 22.5,
      "std_raking_value_by_mslf": 2,
      "momentum_break_by_mslf": 0,
      "pl": 17.94,
      "pvp": 2.09,
      "ev_ebit": 8.43,
      "roic": 10.5,
      "cres_rec_5a": 51.5,
      "div_liq_vm": 0.33,
      "avaliacao_fundamentalista": 26,
      "distortion_ranking": 64
    },
    "SUZB3": {
      "ticker": "SUZB3",
      "setor": null,
      "subsetor": "Papel e Celulose",
      "fundamental_signal": 0,
      "vol_signal": 0,
      "posicao_setorial": "melhor",
      "preco": 40.66999816894531,
      "vol_anualizada_30d": 0.25649206413440123,
      "alto_vol_persistente": 0,
      "mma9": 40.73111089070638,
      "mma10": 40.85299987792969,
      "mma26": 41.51384647075947,
      "mma50": 42.17160018920899,
      "mma150": 48.42280001322428,
      "mma200": 48.52765001296997,
      "pct_to_mma10": -0.4479517037456095,
      "pct_to_mma50": -3.560694907299036,
      "sup_min_by_mslf": "Abismo",
      "sup_med_by_mslf": "Abismo",
      "sup_max_by_mslf": 39.2,
      "res_min_by_mslf": 48.9,
      "res_med_by_mslf": 49.5,
      "res_max_by_mslf": 50.1,
      "std_raking_value_by_mslf": 1,
      "momentum_break_by_mslf": -1,
      "pl": 4.52,
      "pvp": 1.07,
      "ev_ebit": 12.67,
      "roic": 6.8,
      "cres_rec_5a": 3.1,
      "div_liq_vm": 1.33,
      "avaliacao_fundamentalista": 20,
      "distortion_ranking": 44
    },
    "TAEE11": {
      "ticker": "TAEE11",
      "setor": null,
      "subsetor": "Energia Elétrica",
      "fundamental_signal": 0,
      "vol_signal": 1,
      "posicao_setorial": "",
      "preco": 40.52000045776367,
      "vol_anualizada_30d": 0.16668008438142995,
      "alto_vol_persistente": 0,
      "mma9": 40.17222213745117,
      "mma10": 40.13400001525879,
      "mma26": 39.574615478515625,
      "mma50": 39.958800048828124,
      "mma150": 41.66573348999023,
      "mma200": 40.797500133514404,
      "pct_to_mma10": 0.9617791457570243,
      "pct_to_mma50": 1.4044476016541603,
      "sup_min_by_mslf": 36.4,
      "sup_med_by_mslf": 36.7,
      "sup_max_by_mslf": 37.0,
      "res_min_by_mslf": 46.1,
      "res_med_by_mslf": "Foguete",
      "res_max_by_mslf": "Foguete",
      "std_raking_value_by_mslf": 1,
      "momentum_break_by_mslf": 1,
      "pl": 8.91,
      "pvp": 1.75,
      "ev_ebit": 10.26,
      "roic": 10.7,
      "cres_rec_5a": 11.8,
      "div_liq_vm": 0.24,
      "avaliacao_fundamentalista": 25,
      "distortion_ranking": 55
    },
    "TIMS3": {
      "ticker": "TIMS3",
      "setor": null,
      "subsetor": "Telecomunicações",
      "fundamental_signal": -1,
      "vol_signal": 0,
      "posicao_setorial": "pior",
      "preco": 22.510000228881836,
      "vol_anualizada_30d": 0.25831801667982035,
      "alto_vol_persistente": 0,
      "mma9": 22.40999984741211,
      "mma10": 22.398999786376955,
      "mma26": 22.155384650597206,
      "mma50": 22.833400039672853,
      "mma150": 24.44400000254313,
      "mma200": 24.283100023269654,
      "pct_to_mma10": 0.4955598176861082,
      "pct_to_mma50": -1.416345398535094,
      "sup_min_by_mslf": 22.3,
      "sup_med_by_mslf": 22.4,
      "sup_max_by_mslf": 22.5,
      "res_min_by_mslf": 22.7,
      "res_med_by_mslf": 22.9,
      "res_max_by_mslf": 23.0,
      "std_raking_value_by_mslf": 2,
      "momentum_break_by_mslf": 0,
      "pl": 2251.0,
      "pvp": 2.2,
      "ev_ebit": 257.0,
      "roic": 0.4,
      "cres_rec_5a": -69.6,
      "div_liq_vm": -0.06,
      "avaliacao_fundamentalista": 7,
      "distortion_ranking": 63
    },
    "TOTS3": {
      "ticker": "TOTS3",
      "setor": null,
      "subsetor": "Programas e Serviços",
      "fundamental_signal": 0,
      "vol_signal": -1,
      "posicao_setorial": "pior",
      "preco": 29.049999237060547,
      "vol_anualizada_30d": 0.44698580273141064,
      "alto_vol_persistente": 0,
      "mma9": 28.670000076293945,
      "mma10": 28.557999992370604,
      "mma26": 29.745384583106407,
      "mma50": 30.9311999130249,
      "mma150": 36.93166665395101,
      "mma200": 38.77149998664856,
      "pct_to_mma10": 1.7228070762006533,
      "pct_to_mma50": -6.081887160065183,
      "sup_min_by_mslf": 28.5,
      "sup_med_by_mslf": 28.9,
      "sup_max_by_mslf": 29.0,
      "res_min_by_mslf": 29.1,
      "res_med_by_mslf": 29.5,
      "res_max_by_mslf": 29.8,
      "std_raking_value_by_mslf": 2,
      "momentum_break_by_mslf": 0,
      "pl": 18.86,
      "pvp": 3.51,
      "ev_ebit": 10.53,
      "roic": 20.3,
      "cres_rec_5a": 15.1,
      "div_liq_vm": 0.2,
      "avaliacao_fundamentalista": 25,
      "distortion_ranking": 36
    },
    "UGPA3": {
      "ticker": "UGPA3",
      "setor": null,
      "subsetor": "Exploração. Refino e Distribuição",
      "fundamental_signal": 0,
      "vol_signal": 0,
      "posicao_setorial": "",
      "preco": 27.770000457763672,
      "vol_anualizada_30d": 0.29150154894829894,
      "alto_vol_persistente": 0,
      "mma9": 26.27666685316298,
      "mma10": 26.198000144958495,
      "mma26": 25.419230754558857,
      "mma50": 27.190000076293945,
      "mma150": 25.80593335469564,
      "mma200": 24.714799995422364,
      "pct_to_mma10": 6.000459211035198,
      "pct_to_mma50": 2.133138579780329,
      "sup_min_by_mslf": 22.0,
      "sup_med_by_mslf": 22.7,
      "sup_max_by_mslf": 23.2,
      "res_min_by_mslf": 30.8,
      "res_med_by_mslf": "Foguete",
      "res_max_by_mslf": "Foguete",
      "std_raking_value_by_mslf": 2,
      "momentum_break_by_mslf": 1,
      "pl": 10.32,
      "pvp": 1.88,
      "ev_ebit": 7.8,
      "roic": 14.1,
      "cres_rec_5a": 4.0,
      "div_liq_vm": 0.45,
      "avaliacao_fundamentalista": 26,
      "distortion_ranking": 60
    },
    "USIM5": {
      "ticker": "USIM5",
      "setor": null,
      "subsetor": "Siderurgia",
      "fundamental_signal": -1,
      "vol_signal": -1,
      "posicao_setorial": "pior",
      "preco": 8.710000038146973,
      "vol_anualizada_30d": 0.5347110249502638,
      "alto_vol_persistente": 0,
      "mma9": 8.54111131032308,
      "mma10": 8.553000164031982,
      "mma26": 9.82076938335712,
      "mma50": 9.473200063705445,
      "mma150": 7.43866668065389,
      "mma200": 6.801450011730194,
      "pct_to_mma10": 1.8356117280954125,
      "pct_to_mma50": -8.056411987777087,
      "sup_min_by_mslf": 6.2,
      "sup_med_by_mslf": 6.3,
      "sup_max_by_mslf": 6.4,
      "res_min_by_mslf": 12.2,
      "res_med_by_mslf": "Foguete",
      "res_max_by_mslf": "Foguete",
      "std_raking_value_by_mslf": 1,
      "momentum_break_by_mslf": 1,
      "pl": -4.19,
      "pvp": 0.53,
      "ev_ebit": 15.79,
      "roic": 3.3,
      "cres_rec_5a": -7.8,
      "div_liq_vm": -0.05,
      "avaliacao_fundamentalista": 8,
      "distortion_ranking": 53
    },
    "VALE3": {
      "ticker": "VALE3",
      "setor": null,
      "subsetor": "Minerais Metálicos",
      "fundamental_signal": 0,
      "vol_signal": 0,
      "posicao_setorial": "",
      "preco": 77.88999938964844,
      "vol_anualizada_30d": 0.2578896039194514,
      "alto_vol_persistente": 0,
      "mma9": 78.16555531819661,
      "mma10": 78.28699951171875,
      "mma26": 79.58076917208157,
      "mma50": 80.93300003051758,
      "mma150": 80.1191334025065,
      "mma200": 75.41905004501342,
      "pct_to_mma10": -0.5071086189870937,
      "pct_to_mma50": -3.7599009547671627,
      "sup_min_by_mslf": 64.0,
      "sup_med_by_mslf": 65.3,
      "sup_max_by_mslf": 65.9,
      "res_min_by_mslf": 91.6,
      "res_med_by_mslf": "Foguete",
      "res_max_by_mslf": "Foguete",
      "std_raking_value_by_mslf": 1,
      "momentum_break_by_mslf": 1,
      "pl": 22.19,
      "pvp": 1.81,
      "ev_ebit": 6.03,
      "roic": 17.9,
      "cres_rec_5a": -5.3,
      "div_liq_vm": 0.2,
      "avaliacao_fundamentalista": 22,
      "distortion_ranking": 38
    },
    "VAMO3": {
      "ticker": "VAMO3",
      "setor": null,
      "subsetor": "Aluguel de carros",
      "fundamental_signal": 0,
      "vol_signal": -1,
      "posicao_setorial": "",
      "preco": 2.819999933242798,
      "vol_anualizada_30d": 0.4305918781000492,
      "alto_vol_persistente": 0,
      "mma9": 2.82222220632765,
      "mma10": 2.8209999799728394,
      "mma26": 2.8600000051351695,
      "mma50": 3.222400007247925,
      "mma150": 3.6585281244913737,
      "mma200": 3.594446097612381,
      "pct_to_mma10": -0.035450079303124715,
      "pct_to_mma50": -12.487589160254341,
      "sup_min_by_mslf": "Abismo",
      "sup_med_by_mslf": "Abismo",
      "sup_max_by_mslf": 2.7,
      "res_min_by_mslf": 3.6,
      "res_med_by_mslf": 3.7,
      "res_max_by_mslf": 3.8,
      "std_raking_value_by_mslf": 1,
      "momentum_break_by_mslf": -1,
      "pl": 11.28,
      "pvp": 1.32,
      "ev_ebit": 5.77,
      "roic": 15.3,
      "cres_rec_5a": 10.2,
      "div_liq_vm": 3.44,
      "avaliacao_fundamentalista": 29,
      "distortion_ranking": 20
    },
    "VBBR3": {
      "ticker": "VBBR3",
      "setor": null,
      "subsetor": "Exploração. Refino e Distribuição",
      "fundamental_signal": 0,
      "vol_signal": 0,
      "posicao_setorial": "",
      "preco": 30.1299991607666,
      "vol_anualizada_30d": 0.24811178265969283,
      "alto_vol_persistente": 0,
      "mma9": 29.733333163791233,
      "mma10": 29.69899978637695,
      "mma26": 29.347307425278885,
      "mma50": 31.006599731445313,
      "mma150": 29.551854921976727,
      "mma200": 27.83165011405945,
      "pct_to_mma10": 1.4512252179864689,
      "pct_to_mma50": -2.827141893245739,
      "sup_min_by_mslf": 24.2,
      "sup_med_by_mslf": 24.6,
      "sup_max_by_mslf": 25.3,
      "res_min_by_mslf": 33.3,
      "res_med_by_mslf": 34.2,
      "res_max_by_mslf": "Foguete",
      "std_raking_value_by_mslf": 1,
      "momentum_break_by_mslf": 0,
      "pl": 12.0,
      "pvp": 1.66,
      "ev_ebit": 10.26,
      "roic": 9.9,
      "cres_rec_5a": 5.9,
      "div_liq_vm": 0.5,
      "avaliacao_fundamentalista": 22,
      "distortion_ranking": 46
    },
    "VIVA3": {
      "ticker": "VIVA3",
      "setor": null,
      "subsetor": "Acessórios",
      "fundamental_signal": 1,
      "vol_signal": 0,
      "posicao_setorial": "pior",
      "preco": 22.690000534057617,
      "vol_anualizada_30d": 0.3099994416202567,
      "alto_vol_persistente": 0,
      "mma9": 22.875555674235027,
      "mma10": 22.776000022888184,
      "mma26": 21.706538347097542,
      "mma50": 22.85499996185303,
      "mma150": 27.443666661580405,
      "mma200": 28.06029999732971,
      "pct_to_mma10": -0.3775882013704923,
      "pct_to_mma50": -0.7219401797016397,
      "sup_min_by_mslf": "Abismo",
      "sup_med_by_mslf": 16.3,
      "sup_max_by_mslf": 21.2,
      "res_min_by_mslf": 23.9,
      "res_med_by_mslf": 24.4,
      "res_max_by_mslf": 24.9,
      "std_raking_value_by_mslf": 1,
      "momentum_break_by_mslf": 0,
      "pl": 9.15,
      "pvp": 1.77,
      "ev_ebit": 7.14,
      "roic": 17.5,
      "cres_rec_5a": 18.2,
      "div_liq_vm": 0.04,
      "avaliacao_fundamentalista": 33,
      "distortion_ranking": 39
    },
    "VIVT3": {
      "ticker": "VIVT3",
      "setor": null,
      "subsetor": "Telecomunicações",
      "fundamental_signal": 0,
      "vol_signal": 0,
      "posicao_setorial": "melhor",
      "preco": 34.66999816894531,
      "vol_anualizada_30d": 0.24609297718319284,
      "alto_vol_persistente": 0,
      "mma9": 34.41888893975152,
      "mma10": 34.40499992370606,
      "mma26": 33.723461591280426,
      "mma50": 35.13380004882813,
      "mma150": 36.96206675211589,
      "mma200": 36.10460010528564,
      "pct_to_mma10": 0.7702317855744664,
      "pct_to_mma50": -1.320101666310603,
      "sup_min_by_mslf": 33.9,
      "sup_med_by_mslf": 34.0,
      "sup_max_by_mslf": 34.2,
      "res_min_by_mslf": 35.0,
      "res_med_by_mslf": 35.1,
      "res_max_by_mslf": 35.4,
      "std_raking_value_by_mslf": 1,
      "momentum_break_by_mslf": 0,
      "pl": 17.6,
      "pvp": 1.61,
      "ev_ebit": 12.05,
      "roic": 8.8,
      "cres_rec_5a": 7.8,
      "div_liq_vm": 0.1,
      "avaliacao_fundamentalista": 17,
      "distortion_ranking": 58
    },
    "WEGE3": {
      "ticker": "WEGE3",
      "setor": null,
      "subsetor": "Motores. Compressores e Outros",
      "fundamental_signal": 0,
      "vol_signal": 0,
      "posicao_setorial": "pior",
      "preco": 46.27000045776367,
      "vol_anualizada_30d": 0.25095002375136044,
      "alto_vol_persistente": 0,
      "mma9": 46.5533332824707,
      "mma10": 46.4689998626709,
      "mma26": 44.5515383206881,
      "mma50": 44.33640007019043,
      "mma150": 47.345200017293294,
      "mma200": 45.470449943542484,
      "pct_to_mma10": -0.4282412048792235,
      "pct_to_mma50": 4.3612029495225055,
      "sup_min_by_mslf": 45.8,
      "sup_med_by_mslf": 46.0,
      "sup_max_by_mslf": 46.2,
      "res_min_by_mslf": 46.5,
      "res_med_by_mslf": 46.9,
      "res_max_by_mslf": 47.1,
      "std_raking_value_by_mslf": 3,
      "momentum_break_by_mslf": 0,
      "pl": 30.85,
      "pvp": 10.94,
      "ev_ebit": 20.82,
      "roic": 26.0,
      "cres_rec_5a": 12.6,
      "div_liq_vm": -0.02,
      "avaliacao_fundamentalista": 21,
      "distortion_ranking": 59
    },
    "YDUQ3": {
      "ticker": "YDUQ3",
      "setor": null,
      "subsetor": "Serviços Educacionais",
      "fundamental_signal": 0,
      "vol_signal": 0,
      "posicao_setorial": "pior",
      "preco": 8.8100004196167,
      "vol_anualizada_30d": 0.3496908919628765,
      "alto_vol_persistente": 0,
      "mma9": 8.874444325764975,
      "mma10": 8.839999866485595,
      "mma26": 8.806922967617329,
      "mma50": 9.338399934768677,
      "mma150": 11.436066649754842,
      "mma200": 11.808699986934663,
      "pct_to_mma10": -0.3393602638234232,
      "pct_to_mma50": -5.658351739516362,
      "sup_min_by_mslf": "Abismo",
      "sup_med_by_mslf": "Abismo",
      "sup_max_by_mslf": 7.8,
      "res_min_by_mslf": 9.4,
      "res_med_by_mslf": 9.5,
      "res_max_by_mslf": 9.9,
      "std_raking_value_by_mslf": 1,
      "momentum_break_by_mslf": -1,
      "pl": 20.49,
      "pvp": 0.81,
      "ev_ebit": 7.5,
      "roic": 10.9,
      "cres_rec_5a": 5.7,
      "div_liq_vm": 1.78,
      "avaliacao_fundamentalista": 22,
      "distortion_ranking": 39
    }
  },
  "warnings": [],
  "failed_tickers": []
}